Workbook

Sheet Cryptos
A1: ID | B1: Ticker | C1: Apertura | D1: Estado | E1: Cierre | F1: Dias | G1: Unidades | H1: Valor Compra | I1: Valor Actual | J1: Valor Venta | K1: Total Compra | L1: Total Venta | M1: Ganancias (%) | N1: Ganancias Bruta | P1: Ticker | Q1: Unidades | R1: % Cartera | S1: PPC | T1: Total (Abierto) | U1: Ganancias (%) | V1: Ganancias Tot | AC1: Crypto | AD1: USD
A2: Binance | B2: BTC | C2: 44305 | D2: CERRADA | F2: =if(B2=0,"...", IF(E2=0,today()-C2,E2-C2)) -> 1812 | G2: 0.0052924 | H2: 56496.11 | I2: =IF(B2=0,"...",IF(D2="CERRADA","-",VLOOKUP(B2,$AC$2:$AD$27,2,FALSE))) -> - | J2: =IF(B2=0,"...",IF(D2="CERRADA","Valor Venta",I2*(1-VLOOKUP(A2,Config!$B$3:$C$22,2,FALSE)))) -> Valor Venta | K2: =if(B2=0,"...",G2*H2) -> 299.00001 | L2: =IF(B2=0,"...",G2*J2) -> #VALUE! | M2: =if(B2=0,"...",L2/K2-1) -> #VALUE! | N2: =if(B2=0,"...",L2-K2) -> #VALUE! | P2: {=Unique(B10:B200)} -> BTC | Q2: =if(P2=0,"...",sumifs($G$2:$G$124,$B$2:$B$124,P2,$D$2:$D$124,"ABIERTA")) -> 0.01699 | R2: =if(P2=0,"",T2/$Y$18) -> #ERROR! | S2: =if(Q2=0,"...",if(P2=0,"...",sumifs($K$2:$K$124,$B$2:$B$124,P2,$D$2:$D$124,"ABIERTA")/Q2)) -> 65950.872 | T2: =if(P2=0,"...",sumifs($L$2:$L$124,$B$2:$B$124,P2,$D$2:$D$124,"ABIERTA")) -> 1129.1946 | U2: =if(Q2=0,"...",if(P2=0,"...",V2/(T2-V2))) -> 0.0077547571 | V2: =if(Q2=0,"...",if(P2=0,"...",sumifs($N$2:$N$124,$B$2:$B$124,P2,$D$2:$D$124,"ABIERTA"))) -> 8.6892465 | AC2: BTC | AD2: =IFERROR(__xludf.DUMMYFUNCTION("IFERROR(GOOGLEFINANCE(""CURRENCY:""&AC2&""USD""),GECKOPRICE(AC2,""USD""))"),66948.35) -> 66948.35
A3: Binance | B3: BNB | C3: 44439 | D3: ABIERTA | F3: =if(B3=0,"...", IF(E3=0,today()-C3,E3-C3)) -> 1678 | G3: 0.08891975 | H3: 562.3 | I3: =IF(B3=0,"...",IF(D3="CERRADA","-",VLOOKUP(B3,$AC$2:$AD$27,2,FALSE))) -> 593.33979 | J3: =IF(B3=0,"...",IF(D3="CERRADA","Valor Venta",I3*(1-VLOOKUP(A3,Config!$B$3:$C$22,2,FALSE)))) -> 589.03215 | K3: =if(B3=0,"...",G3*H3) -> 49.999575 | L3: =IF(B3=0,"...",G3*J3) -> 52.376591 | M3: =if(B3=0,"...",L3/K3-1) -> 0.047540721 | N3: =if(B3=0,"...",L3-K3) -> 2.3770158 | P3: DOT | Q3: =if(P3=0,"...",sumifs($G$2:$G$124,$B$2:$B$124,P3,$D$2:$D$124,"ABIERTA")) -> 24.63 | R3: =if(P3=0,"",T3/$Y$18) -> #ERROR! | S3: =if(Q3=0,"...",if(P3=0,"...",sumifs($K$2:$K$124,$B$2:$B$124,P3,$D$2:$D$124,"ABIERTA")/Q3)) -> 4.208 | T3: =if(P3=0,"...",sumifs($L$2:$L$124,$B$2:$B$124,P3,$D$2:$D$124,"ABIERTA")) -> 30.006496 | U3: =if(Q3=0,"...",if(P3=0,"...",V3/(T3-V3))) -> -0.71048229 | V3: =if(Q3=0,"...",if(P3=0,"...",sumifs($N$2:$N$124,$B$2:$B$124,P3,$D$2:$D$124,"ABIERTA"))) -> -73.636544 | AC3: BNB | AD3: =IFERROR(__xludf.DUMMYFUNCTION("IFERROR(GOOGLEFINANCE(""CURRENCY:""&AC3&""USD""),GECKOPRICE(AC3,""USD""))"),593.3397941) -> 593.33979
A4: Binance | B4: AVAX | C4: 44529 | D4: CERRADA | F4: =if(B4=0,"...", IF(E4=0,today()-C4,E4-C4)) -> 1588 | G4: 0.42 | H4: 119.05 | I4: =IF(B4=0,"...",IF(D4="CERRADA","-",VLOOKUP(B4,$AC$2:$AD$27,2,FALSE))) -> - | J4: 33.62 | K4: =if(B4=0,"...",G4*H4) -> 50.001 | L4: =IF(B4=0,"...",G4*J4) -> 14.1204 | M4: =if(B4=0,"...",L4/K4-1) -> -0.71759765 | N4: =if(B4=0,"...",L4-K4) -> -35.8806 | P4: SOL | Q4: =if(P4=0,"...",sumifs($G$2:$G$124,$B$2:$B$124,P4,$D$2:$D$124,"ABIERTA")) -> 9.646 | R4: =if(P4=0,"",T4/$Y$18) -> #ERROR! | S4: =if(Q4=0,"...",if(P4=0,"...",sumifs($K$2:$K$124,$B$2:$B$124,P4,$D$2:$D$124,"ABIERTA")/Q4)) -> 154.17525 | T4: =if(P4=0,"...",sumifs($L$2:$L$124,$B$2:$B$124,P4,$D$2:$D$124,"ABIERTA")) -> 764.22082 | U4: =if(Q4=0,"...",if(P4=0,"...",V4/(T4-V4))) -> -0.48612563 | V4: =if(Q4=0,"...",if(P4=0,"...",sumifs($N$2:$N$124,$B$2:$B$124,P4,$D$2:$D$124,"ABIERTA"))) -> -722.95361 | AC4: AVAX
A5: Binance | B5: BTC | C5: 44530 | D5: CERRADA | F5: =if(B5=0,"...", IF(E5=0,today()-C5,E5-C5)) -> 1587 | G5: 0.00173 | H5: 48000 | I5: =IF(B5=0,"...",IF(D5="CERRADA","-",VLOOKUP(B5,$AC$2:$AD$27,2,FALSE))) -> - | J5: =IF(B5=0,"...",IF(D5="CERRADA","Valor Venta",I5*(1-VLOOKUP(A5,Config!$B$3:$C$22,2,FALSE)))) -> Valor Venta | K5: =if(B5=0,"...",G5*H5) -> 83.04 | L5: =IF(B5=0,"...",G5*J5) -> #VALUE! | M5: =if(B5=0,"...",L5/K5-1) -> #VALUE! | N5: =if(B5=0,"...",L5-K5) -> #VALUE! | P5: RUNE | Q5: =if(P5=0,"...",sumifs($G$2:$G$124,$B$2:$B$124,P5,$D$2:$D$124,"ABIERTA")) -> 0 | R5: =if(P5=0,"",T5/$Y$18) -> #ERROR! | S5: =if(Q5=0,"...",if(P5=0,"...",sumifs($K$2:$K$124,$B$2:$B$124,P5,$D$2:$D$124,"ABIERTA")/Q5)) -> ... | T5: =if(P5=0,"...",sumifs($L$2:$L$124,$B$2:$B$124,P5,$D$2:$D$124,"ABIERTA")) -> 0 | U5: =if(Q5=0,"...",if(P5=0,"...",V5/(T5-V5))) -> ... | V5: =if(Q5=0,"...",if(P5=0,"...",sumifs($N$2:$N$124,$B$2:$B$124,P5,$D$2:$D$124,"ABIERTA"))) -> ... | AC5: ETH | AD5: =IFERROR(__xludf.DUMMYFUNCTION("IFERROR(GOOGLEFINANCE(""CURRENCY:""&AC5&""USD""),GECKOPRICE(AC5,""USD""))"),2039.8307000000002) -> 2039.8307
A6: Binance | B6: ETH | C6: 44577 | D6: CERRADA | F6: =if(B6=0,"...", IF(E6=0,today()-C6,E6-C6)) -> 1540 | G6: 0.0173 | H6: 3352.6 | I6: =IF(B6=0,"...",IF(D6="CERRADA","-",VLOOKUP(B6,$AC$2:$AD$27,2,FALSE))) -> - | J6: 2744 | K6: =if(B6=0,"...",G6*H6) -> 57.99998 | L6: =IF(B6=0,"...",G6*J6) -> 47.4712 | M6: =if(B6=0,"...",L6/K6-1) -> -0.18153075 | N6: =if(B6=0,"...",L6-K6) -> -10.52878 | P6: MATIC | Q6: =if(P6=0,"...",sumifs($G$2:$G$124,$B$2:$B$124,P6,$D$2:$D$124,"ABIERTA")) -> 0 | R6: =if(P6=0,"",T6/$Y$18) -> #ERROR! | S6: =if(Q6=0,"...",if(P6=0,"...",sumifs($K$2:$K$124,$B$2:$B$124,P6,$D$2:$D$124,"ABIERTA")/Q6)) -> ... | T6: =if(P6=0,"...",sumifs($L$2:$L$124,$B$2:$B$124,P6,$D$2:$D$124,"ABIERTA")) -> 0 | U6: =if(Q6=0,"...",if(P6=0,"...",V6/(T6-V6))) -> ... | V6: =if(Q6=0,"...",if(P6=0,"...",sumifs($N$2:$N$124,$B$2:$B$124,P6,$D$2:$D$124,"ABIERTA"))) -> ... | AC6: DOT | AD6: =IFERROR(__xludf.DUMMYFUNCTION("IFERROR(GOOGLEFINANCE(""CURRENCY:""&AC6&""USD""),GECKOPRICE(AC6,""USD""))"),1.2272) -> 1.2272
A7: Binance | B7: BTC | C7: 44676 | D7: CERRADA | F7: =if(B7=0,"...", IF(E7=0,today()-C7,E7-C7)) -> 1441 | G7: 0.003532468 | H7: 38500 | I7: =IF(B7=0,"...",IF(D7="CERRADA","-",VLOOKUP(B7,$AC$2:$AD$27,2,FALSE))) -> - | J7: =IF(B7=0,"...",IF(D7="CERRADA","Valor Venta",I7*(1-VLOOKUP(A7,Config!$B$3:$C$22,2,FALSE)))) -> Valor Venta | K7: =if(B7=0,"...",G7*H7) -> 136.00002 | L7: =IF(B7=0,"...",G7*J7) -> #VALUE! | M7: =if(B7=0,"...",L7/K7-1) -> #VALUE! | N7: =if(B7=0,"...",L7-K7) -> #VALUE! | P7: ADA | Q7: =if(P7=0,"...",sumifs($G$2:$G$124,$B$2:$B$124,P7,$D$2:$D$124,"ABIERTA")) -> 0 | R7: =if(P7=0,"",T7/$Y$18) -> #ERROR! | S7: =if(Q7=0,"...",if(P7=0,"...",sumifs($K$2:$K$124,$B$2:$B$124,P7,$D$2:$D$124,"ABIERTA")/Q7)) -> ... | T7: =if(P7=0,"...",sumifs($L$2:$L$124,$B$2:$B$124,P7,$D$2:$D$124,"ABIERTA")) -> 0 | U7: =if(Q7=0,"...",if(P7=0,"...",V7/(T7-V7))) -> ... | V7: =if(Q7=0,"...",if(P7=0,"...",sumifs($N$2:$N$124,$B$2:$B$124,P7,$D$2:$D$124,"ABIERTA"))) -> ... | AC7: SOL | AD7: =IFERROR(__xludf.DUMMYFUNCTION("IFERROR(GOOGLEFINANCE(""CURRENCY:""&AC7&""USD""),GECKOPRICE(AC7,""USD""))"),79.8061) -> 79.8061
A8: Binance | B8: BTC | C8: 44689 | D8: CERRADA | F8: =if(B8=0,"...", IF(E8=0,today()-C8,E8-C8)) -> 1428 | G8: 0.005571031 | H8: 35900 | I8: =IF(B8=0,"...",IF(D8="CERRADA","-",VLOOKUP(B8,$AC$2:$AD$27,2,FALSE))) -> - | J8: =IF(B8=0,"...",IF(D8="CERRADA","Valor Venta",I8*(1-VLOOKUP(A8,Config!$B$3:$C$22,2,FALSE)))) -> Valor Venta | K8: =if(B8=0,"...",G8*H8) -> 200.00001 | L8: =IF(B8=0,"...",G8*J8) -> #VALUE! | M8: =if(B8=0,"...",L8/K8-1) -> #VALUE! | N8: =if(B8=0,"...",L8-K8) -> #VALUE! | P8: XTZ | Q8: =if(P8=0,"...",sumifs($G$2:$G$124,$B$2:$B$124,P8,$D$2:$D$124,"ABIERTA")) -> 0 | R8: =if(P8=0,"",T8/$Y$18) -> #ERROR! | S8: =if(Q8=0,"...",if(P8=0,"...",sumifs($K$2:$K$124,$B$2:$B$124,P8,$D$2:$D$124,"ABIERTA")/Q8)) -> ... | T8: =if(P8=0,"...",sumifs($L$2:$L$124,$B$2:$B$124,P8,$D$2:$D$124,"ABIERTA")) -> 0 | U8: =if(Q8=0,"...",if(P8=0,"...",V8/(T8-V8))) -> ... | V8: =if(Q8=0,"...",if(P8=0,"...",sumifs($N$2:$N$124,$B$2:$B$124,P8,$D$2:$D$124,"ABIERTA"))) -> ... | AC8: RUNE
A9: Binance | B9: BTC | C9: 45037 | D9: CERRADA | F9: =if(B9=0,"...", IF(E9=0,today()-C9,E9-C9)) -> 1080 | G9: 0.010690122 | H9: 28082 | I9: =IF(B9=0,"...",IF(D9="CERRADA","-",VLOOKUP(B9,$AC$2:$AD$27,2,FALSE))) -> - | J9: =IF(B9=0,"...",IF(D9="CERRADA","Valor Venta",I9*(1-VLOOKUP(A9,Config!$B$3:$C$22,2,FALSE)))) -> Valor Venta | K9: =if(B9=0,"...",G9*H9) -> 300.20001 | L9: =IF(B9=0,"...",G9*J9) -> #VALUE! | M9: =if(B9=0,"...",L9/K9-1) -> #VALUE! | N9: =if(B9=0,"...",L9-K9) -> #VALUE! | P9: SAND | Q9: =if(P9=0,"...",sumifs($G$2:$G$124,$B$2:$B$124,P9,$D$2:$D$124,"ABIERTA")) -> 0 | R9: =if(P9=0,"",T9/$Y$18) -> #ERROR! | S9: =if(Q9=0,"...",if(P9=0,"...",sumifs($K$2:$K$124,$B$2:$B$124,P9,$D$2:$D$124,"ABIERTA")/Q9)) -> ... | T9: =if(P9=0,"...",sumifs($L$2:$L$124,$B$2:$B$124,P9,$D$2:$D$124,"ABIERTA")) -> 0 | U9: =if(Q9=0,"...",if(P9=0,"...",V9/(T9-V9))) -> ... | V9: =if(Q9=0,"...",if(P9=0,"...",sumifs($N$2:$N$124,$B$2:$B$124,P9,$D$2:$D$124,"ABIERTA"))) -> ... | AC9: MATIC
A10: Binance | B10: BTC | C10: 45123 | D10: CERRADA | F10: =if(B10=0,"...", IF(E10=0,today()-C10,E10-C10)) -> 994 | G10: 0.011229977 | H10: 30277 | I10: =IF(B10=0,"...",IF(D10="CERRADA","-",VLOOKUP(B10,$AC$2:$AD$27,2,FALSE))) -> - | J10: =IF(B10=0,"...",IF(D10="CERRADA","Valor Venta",I10*(1-VLOOKUP(A10,Config!$B$3:$C$22,2,FALSE)))) -> Valor Venta | K10: =if(B10=0,"...",G10*H10) -> 340.01001 | L10: =IF(B10=0,"...",G10*J10) -> #VALUE! | M10: =if(B10=0,"...",L10/K10-1) -> #VALUE! | N10: =if(B10=0,"...",L10-K10) -> #VALUE! | P10: CRV | Q10: =if(P10=0,"...",sumifs($G$2:$G$124,$B$2:$B$124,P10,$D$2:$D$124,"ABIERTA")) -> 0 | R10: =if(P10=0,"",T10/$Y$18) -> #ERROR! | S10: =if(Q10=0,"...",if(P10=0,"...",sumifs($K$2:$K$124,$B$2:$B$124,P10,$D$2:$D$124,"ABIERTA")/Q10)) -> ... | T10: =if(P10=0,"...",sumifs($L$2:$L$124,$B$2:$B$124,P10,$D$2:$D$124,"ABIERTA")) -> 0 | U10: =if(Q10=0,"...",if(P10=0,"...",V10/(T10-V10))) -> ... | V10: =if(Q10=0,"...",if(P10=0,"...",sumifs($N$2:$N$124,$B$2:$B$124,P10,$D$2:$D$124,"ABIERTA"))) -> ... | AC10: UNI
A11: Binance | B11: BTC | C11: 45180 | D11: CERRADA | F11: =if(B11=0,"...", IF(E11=0,today()-C11,E11-C11)) -> 937 | G11: 0.004909613 | H11: 25148.62 | I11: =IF(B11=0,"...",IF(D11="CERRADA","-",VLOOKUP(B11,$AC$2:$AD$27,2,FALSE))) -> - | J11: =IF(B11=0,"...",IF(D11="CERRADA","Valor Venta",I11*(1-VLOOKUP(A11,Config!$B$3:$C$22,2,FALSE)))) -> Valor Venta | K11: =if(B11=0,"...",G11*H11) -> 123.46999 | L11: =IF(B11=0,"...",G11*J11) -> #VALUE! | M11: =if(B11=0,"...",L11/K11-1) -> #VALUE! | N11: =if(B11=0,"...",L11-K11) -> #VALUE! | P11: MANA | Q11: =if(P11=0,"...",sumifs($G$2:$G$124,$B$2:$B$124,P11,$D$2:$D$124,"ABIERTA")) -> 0 | R11: =if(P11=0,"",T11/$Y$18) -> #ERROR! | S11: =if(Q11=0,"...",if(P11=0,"...",sumifs($K$2:$K$124,$B$2:$B$124,P11,$D$2:$D$124,"ABIERTA")/Q11)) -> ... | T11: =if(P11=0,"...",sumifs($L$2:$L$124,$B$2:$B$124,P11,$D$2:$D$124,"ABIERTA")) -> 0 | U11: =if(Q11=0,"...",if(P11=0,"...",V11/(T11-V11))) -> ... | V11: =if(Q11=0,"...",if(P11=0,"...",sumifs($N$2:$N$124,$B$2:$B$124,P11,$D$2:$D$124,"ABIERTA"))) -> ... | AC11: SAND
A12: Binance | B12: DOT | C12: 45204 | D12: CERRADA | E12: 45265 | F12: =if(B12=0,"...", IF(E12=0,today()-C12,E12-C12)) -> 61 | G12: 4.9788399 | H12: 4.02 | I12: =IF(B12=0,"...",IF(D12="CERRADA","-",VLOOKUP(B12,$AC$2:$AD$27,2,FALSE))) -> - | J12: 5.77 | K12: =if(B12=0,"...",G12*H12) -> 20.014937 | L12: =IF(B12=0,"...",G12*J12) -> 28.727906 | M12: =if(B12=0,"...",L12/K12-1) -> 0.43532338 | N12: =if(B12=0,"...",L12-K12) -> 8.7129699 | P12: 1INCH | Q12: =if(P12=0,"...",sumifs($G$2:$G$124,$B$2:$B$124,P12,$D$2:$D$124,"ABIERTA")) -> 0 | R12: =if(P12=0,"",T12/$Y$18) -> #ERROR! | S12: =if(Q12=0,"...",if(P12=0,"...",sumifs($K$2:$K$124,$B$2:$B$124,P12,$D$2:$D$124,"ABIERTA")/Q12)) -> ... | T12: =if(P12=0,"...",sumifs($L$2:$L$124,$B$2:$B$124,P12,$D$2:$D$124,"ABIERTA")) -> 0 | U12: =if(Q12=0,"...",if(P12=0,"...",V12/(T12-V12))) -> ... | V12: =if(Q12=0,"...",if(P12=0,"...",sumifs($N$2:$N$124,$B$2:$B$124,P12,$D$2:$D$124,"ABIERTA"))) -> ... | AC12: SAND
A13: Binance | B13: BTC | C13: 45204 | D13: CERRADA | F13: =if(B13=0,"...", IF(E13=0,today()-C13,E13-C13)) -> 913 | G13: 0.002669717 | H13: 27482.31 | I13: =IF(B13=0,"...",IF(D13="CERRADA","-",VLOOKUP(B13,$AC$2:$AD$27,2,FALSE))) -> - | J13: =IF(B13=0,"...",IF(D13="CERRADA","Valor Venta",I13*(1-VLOOKUP(A13,Config!$B$3:$C$22,2,FALSE)))) -> Valor Venta | K13: =if(B13=0,"...",G13*H13) -> 73.36999 | L13: =IF(B13=0,"...",G13*J13) -> #VALUE! | M13: =if(B13=0,"...",L13/K13-1) -> #VALUE! | N13: =if(B13=0,"...",L13-K13) -> #VALUE! | P13: NEAR | Q13: =if(P13=0,"...",sumifs($G$2:$G$124,$B$2:$B$124,P13,$D$2:$D$124,"ABIERTA")) -> 0 | R13: =if(P13=0,"",T13/$Y$18) -> #ERROR! | S13: =if(Q13=0,"...",if(P13=0,"...",sumifs($K$2:$K$124,$B$2:$B$124,P13,$D$2:$D$124,"ABIERTA")/Q13)) -> ... | T13: =if(P13=0,"...",sumifs($L$2:$L$124,$B$2:$B$124,P13,$D$2:$D$124,"ABIERTA")) -> 0 | U13: =if(Q13=0,"...",if(P13=0,"...",V13/(T13-V13))) -> ... | V13: =if(Q13=0,"...",if(P13=0,"...",sumifs($N$2:$N$124,$B$2:$B$124,P13,$D$2:$D$124,"ABIERTA"))) -> ... | AC13: ONE
A14: Binance | B14: BTC | C14: 45236 | D14: CERRADA | F14: =if(B14=0,"...", IF(E14=0,today()-C14,E14-C14)) -> 881 | G14: 0.002873563 | H14: 34800 | I14: =IF(B14=0,"...",IF(D14="CERRADA","-",VLOOKUP(B14,$AC$2:$AD$27,2,FALSE))) -> - | J14: =IF(B14=0,"...",IF(D14="CERRADA","Valor Venta",I14*(1-VLOOKUP(A14,Config!$B$3:$C$22,2,FALSE)))) -> Valor Venta | K14: =if(B14=0,"...",G14*H14) -> 99.999992 | L14: =IF(B14=0,"...",G14*J14) -> #VALUE! | M14: =if(B14=0,"...",L14/K14-1) -> #VALUE! | N14: =if(B14=0,"...",L14-K14) -> #VALUE! | P14: GALA | Q14: =if(P14=0,"...",sumifs($G$2:$G$124,$B$2:$B$124,P14,$D$2:$D$124,"ABIERTA")) -> 0 | R14: =if(P14=0,"",T14/$Y$18) -> #ERROR! | S14: =if(Q14=0,"...",if(P14=0,"...",sumifs($K$2:$K$124,$B$2:$B$124,P14,$D$2:$D$124,"ABIERTA")/Q14)) -> ... | T14: =if(P14=0,"...",sumifs($L$2:$L$124,$B$2:$B$124,P14,$D$2:$D$124,"ABIERTA")) -> 0 | U14: =if(Q14=0,"...",if(P14=0,"...",V14/(T14-V14))) -> ... | V14: =if(Q14=0,"...",if(P14=0,"...",sumifs($N$2:$N$124,$B$2:$B$124,P14,$D$2:$D$124,"ABIERTA"))) -> ... | AC14: RNDR
A15: Binance | B15: DOT | C15: 45236 | D15: CERRADA | E15: 45265 | F15: =if(B15=0,"...", IF(E15=0,today()-C15,E15-C15)) -> 29 | G15: 4.338843 | H15: 4.84 | I15: =IF(B15=0,"...",IF(D15="CERRADA","-",VLOOKUP(B15,$AC$2:$AD$27,2,FALSE))) -> - | J15: 5.77 | K15: =if(B15=0,"...",G15*H15) -> 21 | L15: =IF(B15=0,"...",G15*J15) -> 25.035124 | M15: =if(B15=0,"...",L15/K15-1) -> 0.19214876 | N15: =if(B15=0,"...",L15-K15) -> 4.035124 | P15: KSM | Q15: =if(P15=0,"...",sumifs($G$2:$G$124,$B$2:$B$124,P15,$D$2:$D$124,"ABIERTA")) -> 0 | R15: =if(P15=0,"",T15/$Y$18) -> #ERROR! | S15: =if(Q15=0,"...",if(P15=0,"...",sumifs($K$2:$K$124,$B$2:$B$124,P15,$D$2:$D$124,"ABIERTA")/Q15)) -> ... | T15: =if(P15=0,"...",sumifs($L$2:$L$124,$B$2:$B$124,P15,$D$2:$D$124,"ABIERTA")) -> 0 | U15: =if(Q15=0,"...",if(P15=0,"...",V15/(T15-V15))) -> ... | V15: =if(Q15=0,"...",if(P15=0,"...",sumifs($N$2:$N$124,$B$2:$B$124,P15,$D$2:$D$124,"ABIERTA"))) -> ... | AC15: 1INCH
A16: Binance | B16: BTC | C16: 45246 | D16: CERRADA | F16: =if(B16=0,"...", IF(E16=0,today()-C16,E16-C16)) -> 871 | G16: 0.00273 | H16: 36630.04 | I16: =IF(B16=0,"...",IF(D16="CERRADA","-",VLOOKUP(B16,$AC$2:$AD$27,2,FALSE))) -> - | J16: =IF(B16=0,"...",IF(D16="CERRADA","Valor Venta",I16*(1-VLOOKUP(A16,Config!$B$3:$C$22,2,FALSE)))) -> Valor Venta | K16: =if(B16=0,"...",G16*H16) -> 100.00001 | L16: =IF(B16=0,"...",G16*J16) -> #VALUE! | M16: =if(B16=0,"...",L16/K16-1) -> #VALUE! | N16: =if(B16=0,"...",L16-K16) -> #VALUE! | P16: SEI | Q16: =if(P16=0,"...",sumifs($G$2:$G$124,$B$2:$B$124,P16,$D$2:$D$124,"ABIERTA")) -> 0 | R16: =if(P16=0,"",T16/$Y$18) -> #ERROR! | S16: =if(Q16=0,"...",if(P16=0,"...",sumifs($K$2:$K$124,$B$2:$B$124,P16,$D$2:$D$124,"ABIERTA")/Q16)) -> ... | T16: =if(P16=0,"...",sumifs($L$2:$L$124,$B$2:$B$124,P16,$D$2:$D$124,"ABIERTA")) -> 0 | U16: =if(Q16=0,"...",if(P16=0,"...",V16/(T16-V16))) -> ... | V16: =if(Q16=0,"...",if(P16=0,"...",sumifs($N$2:$N$124,$B$2:$B$124,P16,$D$2:$D$124,"ABIERTA"))) -> ... | AC16: RONIN
A17: Binance | B17: SOL | C17: 45254 | D17: CERRADA | E17: 45263 | F17: =if(B17=0,"...", IF(E17=0,today()-C17,E17-C17)) -> 9 | G17: 0.79 | H17: 58.06 | I17: =IF(B17=0,"...",IF(D17="CERRADA","-",VLOOKUP(B17,$AC$2:$AD$27,2,FALSE))) -> - | J17: 64.15 | K17: =if(B17=0,"...",G17*H17) -> 45.8674 | L17: =IF(B17=0,"...",G17*J17) -> 50.6785 | M17: =if(B17=0,"...",L17/K17-1) -> 0.10489149 | N17: =if(B17=0,"...",L17-K17) -> 4.8111 | P17: LINK | Q17: =if(P17=0,"...",sumifs($G$2:$G$124,$B$2:$B$124,P17,$D$2:$D$124,"ABIERTA")) -> 0 | R17: =if(P17=0,"",T17/$Y$18) -> #ERROR! | S17: =if(Q17=0,"...",if(P17=0,"...",sumifs($K$2:$K$124,$B$2:$B$124,P17,$D$2:$D$124,"ABIERTA")/Q17)) -> ... | T17: =if(P17=0,"...",sumifs($L$2:$L$124,$B$2:$B$124,P17,$D$2:$D$124,"ABIERTA")) -> 0 | U17: =if(Q17=0,"...",if(P17=0,"...",V17/(T17-V17))) -> ... | V17: =if(Q17=0,"...",if(P17=0,"...",sumifs($N$2:$N$124,$B$2:$B$124,P17,$D$2:$D$124,"ABIERTA"))) -> ... | AC17: GALA
A18: Binance | B18: SOL | C18: 45254 | D18: CERRADA | E18: 45263 | F18: =if(B18=0,"...", IF(E18=0,today()-C18,E18-C18)) -> 9 | G18: 0.77 | H18: 58.16 | I18: =IF(B18=0,"...",IF(D18="CERRADA","-",VLOOKUP(B18,$AC$2:$AD$27,2,FALSE))) -> - | J18: 64.15 | K18: =if(B18=0,"...",G18*H18) -> 44.7832 | L18: =IF(B18=0,"...",G18*J18) -> 49.3955 | M18: =if(B18=0,"...",L18/K18-1) -> 0.10299175 | N18: =if(B18=0,"...",L18-K18) -> 4.6123 | P18: AVAX | Q18: =if(P18=0,"...",sumifs($G$2:$G$124,$B$2:$B$124,P18,$D$2:$D$124,"ABIERTA")) -> 0 | R18: =if(P18=0,"",T18/$Y$18) -> #ERROR! | S18: =if(Q18=0,"...",if(P18=0,"...",sumifs($K$2:$K$124,$B$2:$B$124,P18,$D$2:$D$124,"ABIERTA")/Q18)) -> ... | T18: =if(P18=0,"...",sumifs($L$2:$L$124,$B$2:$B$124,P18,$D$2:$D$124,"ABIERTA")) -> 0 | U18: =if(Q18=0,"...",if(P18=0,"...",V18/(T18-V18))) -> ... | V18: =if(Q18=0,"...",if(P18=0,"...",sumifs($N$2:$N$124,$B$2:$B$124,P18,$D$2:$D$124,"ABIERTA"))) -> ... | X18: Tenencias Actuales | Y18: =SUMIFS(L2:L150,D2:D150,"ABIERTA") -> #ERROR! | Z18: Total Acumulado | AA18: =SUM(L2:L150) -> #VALUE! | AC18: KSM
A19: Binance | B19: RUNE | C19: 45264 | D19: CERRADA | E19: 45268 | F19: =if(B19=0,"...", IF(E19=0,today()-C19,E19-C19)) -> 4 | G19: 13.2 | H19: 6.75 | I19: =IF(B19=0,"...",IF(D19="CERRADA","-",VLOOKUP(B19,$AC$2:$AD$27,2,FALSE))) -> - | J19: 6.6 | K19: =if(B19=0,"...",G19*H19) -> 89.1 | L19: =IF(B19=0,"...",G19*J19) -> 87.12 | M19: =if(B19=0,"...",L19/K19-1) -> -0.022222222 | N19: =if(B19=0,"...",L19-K19) -> -1.98 | P19: SHIB | Q19: =if(P19=0,"...",sumifs($G$2:$G$124,$B$2:$B$124,P19,$D$2:$D$124,"ABIERTA")) -> 0 | R19: =if(P19=0,"",T19/$Y$18) -> #ERROR! | S19: =if(Q19=0,"...",if(P19=0,"...",sumifs($K$2:$K$124,$B$2:$B$124,P19,$D$2:$D$124,"ABIERTA")/Q19)) -> ... | T19: =if(P19=0,"...",sumifs($L$2:$L$124,$B$2:$B$124,P19,$D$2:$D$124,"ABIERTA")) -> 0 | U19: =if(Q19=0,"...",if(P19=0,"...",V19/(T19-V19))) -> ... | V19: =if(Q19=0,"...",if(P19=0,"...",sumifs($N$2:$N$124,$B$2:$B$124,P19,$D$2:$D$124,"ABIERTA"))) -> ... | AC19: SEI
A20: Binance | B20: MATIC | C20: 45268 | D20: CERRADA | F20: =if(B20=0,"...", IF(E20=0,today()-C20,E20-C20)) -> 849 | G20: 44.4 | H20: 0.9 | I20: =IF(B20=0,"...",IF(D20="CERRADA","-",VLOOKUP(B20,$AC$2:$AD$27,2,FALSE))) -> - | J20: 0.9 | K20: =if(B20=0,"...",G20*H20) -> 39.96 | L20: =IF(B20=0,"...",G20*J20) -> 39.96 | M20: =if(B20=0,"...",L20/K20-1) -> 0 | N20: =if(B20=0,"...",L20-K20) -> 0 | P20: RNDR | Q20: =if(P20=0,"...",sumifs($G$2:$G$124,$B$2:$B$124,P20,$D$2:$D$124,"ABIERTA")) -> 0 | R20: =if(P20=0,"",T20/$Y$18) -> #ERROR! | S20: =if(Q20=0,"...",if(P20=0,"...",sumifs($K$2:$K$124,$B$2:$B$124,P20,$D$2:$D$124,"ABIERTA")/Q20)) -> ... | T20: =if(P20=0,"...",sumifs($L$2:$L$124,$B$2:$B$124,P20,$D$2:$D$124,"ABIERTA")) -> 0 | U20: =if(Q20=0,"...",if(P20=0,"...",V20/(T20-V20))) -> ... | V20: =if(Q20=0,"...",if(P20=0,"...",sumifs($N$2:$N$124,$B$2:$B$124,P20,$D$2:$D$124,"ABIERTA"))) -> ... | X20: Ganancia Abierto | Y20: =SUMIFS(N2:N150,D2:D150,"ABIERTA") -> #ERROR! | Z20: Ganancia Acumulada | AA20: =SUM(N2:N150) -> #VALUE! | AC20: LINK
A21: Binance | B21: DOT | C21: 45268 | D21: CERRADA | F21: =if(B21=0,"...", IF(E21=0,today()-C21,E21-C21)) -> 849 | G21: 5.97 | H21: 6.7 | I21: =IF(B21=0,"...",IF(D21="CERRADA","-",VLOOKUP(B21,$AC$2:$AD$27,2,FALSE))) -> - | J21: 5.77 | K21: =if(B21=0,"...",G21*H21) -> 39.999 | L21: =IF(B21=0,"...",G21*J21) -> 34.4469 | M21: =if(B21=0,"...",L21/K21-1) -> -0.13880597 | N21: =if(B21=0,"...",L21-K21) -> -5.5521 | P21: AAVE | Q21: =if(P21=0,"...",sumifs($G$2:$G$124,$B$2:$B$124,P21,$D$2:$D$124,"ABIERTA")) -> 0.305 | R21: =if(P21=0,"",T21/$Y$18) -> #ERROR! | S21: =if(Q21=0,"...",if(P21=0,"...",sumifs($K$2:$K$124,$B$2:$B$124,P21,$D$2:$D$124,"ABIERTA")/Q21)) -> 331.2 | T21: =if(P21=0,"...",sumifs($L$2:$L$124,$B$2:$B$124,P21,$D$2:$D$124,"ABIERTA")) -> #ERROR! | U21: =if(Q21=0,"...",if(P21=0,"...",V21/(T21-V21))) -> #ERROR! | V21: =if(Q21=0,"...",if(P21=0,"...",sumifs($N$2:$N$124,$B$2:$B$124,P21,$D$2:$D$124,"ABIERTA"))) -> #ERROR! | AC21: SHIB
A22: Binance | B22: SOL | C22: 45268 | D22: CERRADA | E22: 45282 | F22: =if(B22=0,"...", IF(E22=0,today()-C22,E22-C22)) -> 14 | G22: 0.54 | H22: 73.22 | I22: =IF(B22=0,"...",IF(D22="CERRADA","-",VLOOKUP(B22,$AC$2:$AD$27,2,FALSE))) -> - | J22: 97 | K22: =if(B22=0,"...",G22*H22) -> 39.5388 | L22: =IF(B22=0,"...",G22*J22) -> 52.38 | M22: =if(B22=0,"...",L22/K22-1) -> 0.32477465 | N22: =if(B22=0,"...",L22-K22) -> 12.8412 | P22: TRX | Q22: =if(P22=0,"...",sumifs($G$2:$G$124,$B$2:$B$124,P22,$D$2:$D$124,"ABIERTA")) -> 316.1 | R22: =if(P22=0,"",T22/$Y$18) -> #ERROR! | S22: =if(Q22=0,"...",if(P22=0,"...",sumifs($K$2:$K$124,$B$2:$B$124,P22,$D$2:$D$124,"ABIERTA")/Q22)) -> 0.3163 | T22: =if(P22=0,"...",sumifs($L$2:$L$124,$B$2:$B$124,P22,$D$2:$D$124,"ABIERTA")) -> 99.699964 | U22: =if(Q22=0,"...",if(P22=0,"...",V22/(T22-V22))) -> -0.0028251545 | V22: =if(Q22=0,"...",if(P22=0,"...",sumifs($N$2:$N$124,$B$2:$B$124,P22,$D$2:$D$124,"ABIERTA"))) -> -0.28246582 | X22: (%) | Y22: =Y20/(Y18-Y20) -> #ERROR! | Z22: (%) | AA22: =AA20/(AA18-AA20) -> #VALUE! | AC22: RNDR
A23: Binance | B23: ADA | C23: 45269 | D23: CERRADA | F23: =if(B23=0,"...", IF(E23=0,today()-C23,E23-C23)) -> 848 | G23: 32.9 | H23: 0.61 | I23: =IF(B23=0,"...",IF(D23="CERRADA","-",VLOOKUP(B23,$AC$2:$AD$27,2,FALSE))) -> - | J23: 0.7614 | K23: =if(B23=0,"...",G23*H23) -> 20.069 | L23: =IF(B23=0,"...",G23*J23) -> 25.05006 | M23: =if(B23=0,"...",L23/K23-1) -> 0.24819672 | N23: =if(B23=0,"...",L23-K23) -> 4.98106 | P23: UNI | Q23: =if(P23=0,"...",sumifs($G$2:$G$124,$B$2:$B$124,P23,$D$2:$D$124,"ABIERTA")) -> 8.52 | R23: =if(P23=0,"",T23/$Y$18) -> #ERROR! | S23: =if(Q23=0,"...",if(P23=0,"...",sumifs($K$2:$K$124,$B$2:$B$124,P23,$D$2:$D$124,"ABIERTA")/Q23)) -> 10.547 | T23: =if(P23=0,"...",sumifs($L$2:$L$124,$B$2:$B$124,P23,$D$2:$D$124,"ABIERTA")) -> 0 | U23: =if(Q23=0,"...",if(P23=0,"...",V23/(T23-V23))) -> -1 | V23: =if(Q23=0,"...",if(P23=0,"...",sumifs($N$2:$N$124,$B$2:$B$124,P23,$D$2:$D$124,"ABIERTA"))) -> -89.86044 | AC23: AAVE | AD23: =IFERROR(__xludf.DUMMYFUNCTION("IFERROR(GOOGLEFINANCE(""CURRENCY:""&AC23&""USDT""),GECKOPRICE(AC23,""USD""))"),"#ERROR!") -> #ERROR!
A24: Binance | B24: ADA | C24: 45271 | D24: CERRADA | F24: =if(B24=0,"...", IF(E24=0,today()-C24,E24-C24)) -> 846 | G24: 35.5 | H24: 0.56 | I24: =IF(B24=0,"...",IF(D24="CERRADA","-",VLOOKUP(B24,$AC$2:$AD$27,2,FALSE))) -> - | J24: 0.7614 | K24: =if(B24=0,"...",G24*H24) -> 19.88 | L24: =IF(B24=0,"...",G24*J24) -> 27.0297 | M24: =if(B24=0,"...",L24/K24-1) -> 0.35964286 | N24: =if(B24=0,"...",L24-K24) -> 7.1497 | P24: DOGE | Q24: =if(P24=0,"...",sumifs($G$2:$G$124,$B$2:$B$124,P24,$D$2:$D$124,"ABIERTA")) -> 0 | R24: =if(P24=0,"",T24/$Y$18) -> #ERROR! | S24: =if(Q24=0,"...",if(P24=0,"...",sumifs($K$2:$K$124,$B$2:$B$124,P24,$D$2:$D$124,"ABIERTA")/Q24)) -> ... | T24: =if(P24=0,"...",sumifs($L$2:$L$124,$B$2:$B$124,P24,$D$2:$D$124,"ABIERTA")) -> 0 | U24: =if(Q24=0,"...",if(P24=0,"...",V24/(T24-V24))) -> ... | V24: =if(Q24=0,"...",if(P24=0,"...",sumifs($N$2:$N$124,$B$2:$B$124,P24,$D$2:$D$124,"ABIERTA"))) -> ... | AC24: TRX | AD24: =IFERROR(__xludf.DUMMYFUNCTION("IFERROR(GOOGLEFINANCE(""CURRENCY:""&AC24&""USDT""),GECKOPRICE(AC24,""USD""))"),0.317713) -> 0.317713
A25: Binance | B25: SOL | C25: 45271 | D25: CERRADA | E25: 45282 | F25: =if(B25=0,"...", IF(E25=0,today()-C25,E25-C25)) -> 11 | G25: 0.27 | H25: 74.07 | I25: =IF(B25=0,"...",IF(D25="CERRADA","-",VLOOKUP(B25,$AC$2:$AD$27,2,FALSE))) -> - | J25: 97 | K25: =if(B25=0,"...",G25*H25) -> 19.9989 | L25: =IF(B25=0,"...",G25*J25) -> 26.19 | M25: =if(B25=0,"...",L25/K25-1) -> 0.30957203 | N25: =if(B25=0,"...",L25-K25) -> 6.1911 | P25: FET | Q25: =if(P25=0,"...",sumifs($G$2:$G$124,$B$2:$B$124,P25,$D$2:$D$124,"ABIERTA")) -> 0 | R25: =if(P25=0,"",T25/$Y$18) -> #ERROR! | S25: =if(Q25=0,"...",if(P25=0,"...",sumifs($K$2:$K$124,$B$2:$B$124,P25,$D$2:$D$124,"ABIERTA")/Q25)) -> ... | T25: =if(P25=0,"...",sumifs($L$2:$L$124,$B$2:$B$124,P25,$D$2:$D$124,"ABIERTA")) -> 0 | U25: =if(Q25=0,"...",if(P25=0,"...",V25/(T25-V25))) -> ... | V25: =if(Q25=0,"...",if(P25=0,"...",sumifs($N$2:$N$124,$B$2:$B$124,P25,$D$2:$D$124,"ABIERTA"))) -> ... | AC25: UNI | AD25: =IFERROR(__xludf.DUMMYFUNCTION("IFERROR(GOOGLEFINANCE(""CURRENCY:""&AC25&""USDT""),GECKOPRICE(AC25,""USD""))"),"#ERROR!") -> #ERROR!
A26: Binance | B26: MATIC | C26: 45271 | D26: CERRADA | F26: =if(B26=0,"...", IF(E26=0,today()-C26,E26-C26)) -> 846 | G26: 22.8 | H26: 0.88 | I26: =IF(B26=0,"...",IF(D26="CERRADA","-",VLOOKUP(B26,$AC$2:$AD$27,2,FALSE))) -> - | J26: 0.9 | K26: =if(B26=0,"...",G26*H26) -> 20.064 | L26: =IF(B26=0,"...",G26*J26) -> 20.52 | M26: =if(B26=0,"...",L26/K26-1) -> 0.022727273 | N26: =if(B26=0,"...",L26-K26) -> 0.456 | P26: ETH | Q26: =if(P26=0,"...",sumifs($G$2:$G$124,$B$2:$B$124,P26,$D$2:$D$124,"ABIERTA")) -> 0 | R26: =if(P26=0,"",T26/$Y$18) -> #ERROR! | S26: =if(Q26=0,"...",if(P26=0,"...",sumifs($K$2:$K$124,$B$2:$B$124,P26,$D$2:$D$124,"ABIERTA")/Q26)) -> ... | T26: =if(P26=0,"...",sumifs($L$2:$L$124,$B$2:$B$124,P26,$D$2:$D$124,"ABIERTA")) -> 0 | U26: =if(Q26=0,"...",if(P26=0,"...",V26/(T26-V26))) -> ... | V26: =if(Q26=0,"...",if(P26=0,"...",sumifs($N$2:$N$124,$B$2:$B$124,P26,$D$2:$D$124,"ABIERTA"))) -> ... | X26: Config Gráficas | Y26: Tipo | Z26: column | AC26: DOGE
A27: Binance | B27: BTC | C27: 45271 | D27: CERRADA | F27: =if(B27=0,"...", IF(E27=0,today()-C27,E27-C27)) -> 846 | G27: 0.0015 | H27: 42346.67 | I27: =IF(B27=0,"...",IF(D27="CERRADA","-",VLOOKUP(B27,$AC$2:$AD$27,2,FALSE))) -> - | J27: =IF(B27=0,"...",IF(D27="CERRADA","Valor Venta",I27*(1-VLOOKUP(A27,Config!$B$3:$C$22,2,FALSE)))) -> Valor Venta | K27: =if(B27=0,"...",G27*H27) -> 63.520005 | L27: =IF(B27=0,"...",G27*J27) -> #VALUE! | M27: =if(B27=0,"...",L27/K27-1) -> #VALUE! | N27: =if(B27=0,"...",L27-K27) -> #VALUE! | P27: BNB | Q27: =if(P27=0,"...",sumifs($G$2:$G$124,$B$2:$B$124,P27,$D$2:$D$124,"ABIERTA")) -> 0.08891975 | R27: =if(P27=0,"",T27/$Y$18) -> #ERROR! | S27: =if(Q27=0,"...",if(P27=0,"...",sumifs($K$2:$K$124,$B$2:$B$124,P27,$D$2:$D$124,"ABIERTA")/Q27)) -> 562.3 | T27: =if(P27=0,"...",sumifs($L$2:$L$124,$B$2:$B$124,P27,$D$2:$D$124,"ABIERTA")) -> 52.376591 | U27: =if(Q27=0,"...",if(P27=0,"...",V27/(T27-V27))) -> 0.047540721 | V27: =if(Q27=0,"...",if(P27=0,"...",sumifs($N$2:$N$124,$B$2:$B$124,P27,$D$2:$D$124,"ABIERTA"))) -> 2.3770158 | Y27: Días | Z27: 14 | AC27: SUI | AD27: =IFERROR(__xludf.DUMMYFUNCTION("IFERROR(GOOGLEFINANCE(""CURRENCY:""&AC27&""USDT""),GECKOPRICE(AC27,""USD""))"),0.850209) -> 0.850209
A28: Binance | B28: BTC | C28: 45267 | D28: CERRADA | F28: =if(B28=0,"...", IF(E28=0,today()-C28,E28-C28)) -> 850 | G28: 0.00138 | H28: 43289.86 | I28: =IF(B28=0,"...",IF(D28="CERRADA","-",VLOOKUP(B28,$AC$2:$AD$27,2,FALSE))) -> - | J28: =IF(B28=0,"...",IF(D28="CERRADA","Valor Venta",I28*(1-VLOOKUP(A28,Config!$B$3:$C$22,2,FALSE)))) -> Valor Venta | K28: =if(B28=0,"...",G28*H28) -> 59.740007 | L28: =IF(B28=0,"...",G28*J28) -> #VALUE! | M28: =if(B28=0,"...",L28/K28-1) -> #VALUE! | N28: =if(B28=0,"...",L28-K28) -> #VALUE! | P28: RAY | Q28: =if(P28=0,"...",sumifs($G$2:$G$124,$B$2:$B$124,P28,$D$2:$D$124,"ABIERTA")) -> 8.6 | R28: =if(P28=0,"",T28/$Y$18) -> #ERROR! | S28: =if(Q28=0,"...",if(P28=0,"...",sumifs($K$2:$K$124,$B$2:$B$124,P28,$D$2:$D$124,"ABIERTA")/Q28)) -> 5.769 | T28: =if(P28=0,"...",sumifs($L$2:$L$124,$B$2:$B$124,P28,$D$2:$D$124,"ABIERTA")) -> 5.10484 | U28: =if(Q28=0,"...",if(P28=0,"...",V28/(T28-V28))) -> -0.89710764 | V28: =if(Q28=0,"...",if(P28=0,"...",sumifs($N$2:$N$124,$B$2:$B$124,P28,$D$2:$D$124,"ABIERTA"))) -> -44.50856 | AC28: RAY | AD28: =IFERROR(__xludf.DUMMYFUNCTION("IFERROR(GOOGLEFINANCE(""CURRENCY:""&AC28&""USDT""),GECKOPRICE(AC28,""USD""))"),0.597927) -> 0.597927
A29: Binance | B29: BTC | C29: 45267 | D29: CERRADA | F29: =if(B29=0,"...", IF(E29=0,today()-C29,E29-C29)) -> 850 | G29: 0.00138 | H29: 43350 | I29: =IF(B29=0,"...",IF(D29="CERRADA","-",VLOOKUP(B29,$AC$2:$AD$27,2,FALSE))) -> - | J29: =IF(B29=0,"...",IF(D29="CERRADA","Valor Venta",I29*(1-VLOOKUP(A29,Config!$B$3:$C$22,2,FALSE)))) -> Valor Venta | K29: =if(B29=0,"...",G29*H29) -> 59.823 | L29: =IF(B29=0,"...",G29*J29) -> #VALUE! | M29: =if(B29=0,"...",L29/K29-1) -> #VALUE! | N29: =if(B29=0,"...",L29-K29) -> #VALUE! | P29: RONIN | Q29: =if(P29=0,"...",sumifs($G$2:$G$124,$B$2:$B$124,P29,$D$2:$D$124,"ABIERTA")) -> 0 | R29: =if(P29=0,"",T29/$Y$18) -> #ERROR! | S29: =if(Q29=0,"...",if(P29=0,"...",sumifs($K$2:$K$124,$B$2:$B$124,P29,$D$2:$D$124,"ABIERTA")/Q29)) -> ... | T29: =if(P29=0,"...",sumifs($L$2:$L$124,$B$2:$B$124,P29,$D$2:$D$124,"ABIERTA")) -> 0 | U29: =if(Q29=0,"...",if(P29=0,"...",V29/(T29-V29))) -> ... | V29: =if(Q29=0,"...",if(P29=0,"...",sumifs($N$2:$N$124,$B$2:$B$124,P29,$D$2:$D$124,"ABIERTA"))) -> ... | AC29: XRP | AD29: =IFERROR(__xludf.DUMMYFUNCTION("IFERROR(GOOGLEFINANCE(""CURRENCY:""&AC29&""USDT""),GECKOPRICE(AC29,""USD""))"),1.3) -> 1.3
A30: Binance | B30: SOL | C30: 45236 | D30: CERRADA | E30: 45246 | F30: =if(B30=0,"...", IF(E30=0,today()-C30,E30-C30)) -> 10 | G30: 0.49 | H30: 40.08 | I30: =IF(B30=0,"...",IF(D30="CERRADA","-",VLOOKUP(B30,$AC$2:$AD$27,2,FALSE))) -> - | J30: 58.25 | K30: =if(B30=0,"...",G30*H30) -> 19.6392 | L30: =IF(B30=0,"...",G30*J30) -> 28.5425 | M30: =if(B30=0,"...",L30/K30-1) -> 0.45334331 | N30: =if(B30=0,"...",L30-K30) -> 8.9033 | P30: ONE | Q30: =if(P30=0,"...",sumifs($G$2:$G$124,$B$2:$B$124,P30,$D$2:$D$124,"ABIERTA")) -> 0 | R30: =if(P30=0,"",T30/$Y$18) -> #ERROR! | S30: =if(Q30=0,"...",if(P30=0,"...",sumifs($K$2:$K$124,$B$2:$B$124,P30,$D$2:$D$124,"ABIERTA")/Q30)) -> ... | T30: =if(P30=0,"...",sumifs($L$2:$L$124,$B$2:$B$124,P30,$D$2:$D$124,"ABIERTA")) -> 0 | U30: =if(Q30=0,"...",if(P30=0,"...",V30/(T30-V30))) -> ... | V30: =if(Q30=0,"...",if(P30=0,"...",sumifs($N$2:$N$124,$B$2:$B$124,P30,$D$2:$D$124,"ABIERTA"))) -> ...
A31: Binance | B31: SOL | C31: 45204 | D31: CERRADA | E31: 45246 | F31: =if(B31=0,"...", IF(E31=0,today()-C31,E31-C31)) -> 42 | G31: 0.88 | H31: 22.73 | I31: =IF(B31=0,"...",IF(D31="CERRADA","-",VLOOKUP(B31,$AC$2:$AD$27,2,FALSE))) -> - | J31: 58.25 | K31: =if(B31=0,"...",G31*H31) -> 20.0024 | L31: =IF(B31=0,"...",G31*J31) -> 51.26 | M31: =if(B31=0,"...",L31/K31-1) -> 1.5626925 | N31: =if(B31=0,"...",L31-K31) -> 31.2576 | P31: TRUMP | Q31: =if(P31=0,"...",sumifs($G$2:$G$124,$B$2:$B$124,P31,$D$2:$D$124,"ABIERTA")) -> 0 | R31: =if(P31=0,"",T31/$Y$18) -> #ERROR! | S31: =if(Q31=0,"...",if(P31=0,"...",sumifs($K$2:$K$124,$B$2:$B$124,P31,$D$2:$D$124,"ABIERTA")/Q31)) -> ... | T31: =if(P31=0,"...",sumifs($L$2:$L$124,$B$2:$B$124,P31,$D$2:$D$124,"ABIERTA")) -> 0 | U31: =if(Q31=0,"...",if(P31=0,"...",V31/(T31-V31))) -> ... | V31: =if(Q31=0,"...",if(P31=0,"...",sumifs($N$2:$N$124,$B$2:$B$124,P31,$D$2:$D$124,"ABIERTA"))) -> ...
A32: Binance | B32: BTC | C32: 45246 | D32: CERRADA | E32: 45253 | F32: =if(B32=0,"...", IF(E32=0,today()-C32,E32-C32)) -> 7 | G32: 0.00195 | H32: 35815.38 | I32: =IF(B32=0,"...",IF(D32="CERRADA","-",VLOOKUP(B32,$AC$2:$AD$27,2,FALSE))) -> - | J32: 37400 | K32: =if(B32=0,"...",G32*H32) -> 69.839991 | L32: =IF(B32=0,"...",G32*J32) -> 72.93 | M32: =if(B32=0,"...",L32/K32-1) -> 0.044244121 | N32: =if(B32=0,"...",L32-K32) -> 3.090009 | P32: ONDO | Q32: =if(P32=0,"...",sumifs($G$2:$G$124,$B$2:$B$124,P32,$D$2:$D$124,"ABIERTA")) -> 0 | R32: =if(P32=0,"",T32/$Y$18) -> #ERROR! | S32: =if(Q32=0,"...",if(P32=0,"...",sumifs($K$2:$K$124,$B$2:$B$124,P32,$D$2:$D$124,"ABIERTA")/Q32)) -> ... | T32: =if(P32=0,"...",sumifs($L$2:$L$124,$B$2:$B$124,P32,$D$2:$D$124,"ABIERTA")) -> 0 | U32: =if(Q32=0,"...",if(P32=0,"...",V32/(T32-V32))) -> ... | V32: =if(Q32=0,"...",if(P32=0,"...",sumifs($N$2:$N$124,$B$2:$B$124,P32,$D$2:$D$124,"ABIERTA"))) -> ...
A33: Binance | B33: BTC | C33: 45251 | D33: CERRADA | E33: 45253 | F33: =if(B33=0,"...", IF(E33=0,today()-C33,E33-C33)) -> 2 | G33: 0.00047 | H33: 36063.83 | I33: =IF(B33=0,"...",IF(D33="CERRADA","-",VLOOKUP(B33,$AC$2:$AD$27,2,FALSE))) -> - | J33: 37400 | K33: =if(B33=0,"...",G33*H33) -> 16.95 | L33: =IF(B33=0,"...",G33*J33) -> 17.578 | M33: =if(B33=0,"...",L33/K33-1) -> 0.037050141 | N33: =if(B33=0,"...",L33-K33) -> 0.6279999 | P33: XRP | Q33: =if(P33=0,"...",sumifs($G$2:$G$124,$B$2:$B$124,P33,$D$2:$D$124,"ABIERTA")) -> 32 | R33: =if(P33=0,"",T33/$Y$18) -> #ERROR! | S33: =if(Q33=0,"...",if(P33=0,"...",sumifs($K$2:$K$124,$B$2:$B$124,P33,$D$2:$D$124,"ABIERTA")/Q33)) -> 3.2356 | T33: =if(P33=0,"...",sumifs($L$2:$L$124,$B$2:$B$124,P33,$D$2:$D$124,"ABIERTA")) -> 41.297984 | U33: =if(Q33=0,"...",if(P33=0,"...",V33/(T33-V33))) -> -0.60113673 | V33: =if(Q33=0,"...",if(P33=0,"...",sumifs($N$2:$N$124,$B$2:$B$124,P33,$D$2:$D$124,"ABIERTA"))) -> -62.241216
A34: Binance | B34: MATIC | C34: 45271 | D34: CERRADA | F34: =if(B34=0,"...", IF(E34=0,today()-C34,E34-C34)) -> 846 | G34: 23.2 | H34: 0.86 | I34: =IF(B34=0,"...",IF(D34="CERRADA","-",VLOOKUP(B34,$AC$2:$AD$27,2,FALSE))) -> - | J34: 0.9 | K34: =if(B34=0,"...",G34*H34) -> 19.952 | L34: =IF(B34=0,"...",G34*J34) -> 20.88 | M34: =if(B34=0,"...",L34/K34-1) -> 0.046511628 | N34: =if(B34=0,"...",L34-K34) -> 0.928 | P34: SUI | Q34: =if(P34=0,"...",sumifs($G$2:$G$124,$B$2:$B$124,P34,$D$2:$D$124,"ABIERTA")) -> 27.6 | R34: =if(P34=0,"",T34/$Y$18) -> #ERROR! | S34: =if(Q34=0,"...",if(P34=0,"...",sumifs($K$2:$K$124,$B$2:$B$124,P34,$D$2:$D$124,"ABIERTA")/Q34)) -> 3.9621 | T34: =if(P34=0,"...",sumifs($L$2:$L$124,$B$2:$B$124,P34,$D$2:$D$124,"ABIERTA")) -> 23.295407 | U34: =if(Q34=0,"...",if(P34=0,"...",V34/(T34-V34))) -> -0.78697244 | V34: =if(Q34=0,"...",if(P34=0,"...",sumifs($N$2:$N$124,$B$2:$B$124,P34,$D$2:$D$124,"ABIERTA"))) -> -86.058553
A35: Binance | B35: ADA | C35: 45271 | D35: CERRADA | F35: =if(B35=0,"...", IF(E35=0,today()-C35,E35-C35)) -> 846 | G35: 36.1 | H35: 0.55 | I35: =IF(B35=0,"...",IF(D35="CERRADA","-",VLOOKUP(B35,$AC$2:$AD$27,2,FALSE))) -> - | J35: 0.7614 | K35: =if(B35=0,"...",G35*H35) -> 19.855 | L35: =IF(B35=0,"...",G35*J35) -> 27.48654 | M35: =if(B35=0,"...",L35/K35-1) -> 0.38436364 | N35: =if(B35=0,"...",L35-K35) -> 7.63154 | Q35: =if(P35=0,"...",sumifs($G$2:$G$124,$B$2:$B$124,P35,$D$2:$D$124,"ABIERTA")) -> ... | R35: =if(P35=0,"",T35/$Y$18) | S35: =if(Q35=0,"...",if(P35=0,"...",sumifs($K$2:$K$124,$B$2:$B$124,P35,$D$2:$D$124,"ABIERTA")/Q35)) -> ... | T35: =if(P35=0,"...",sumifs($L$2:$L$124,$B$2:$B$124,P35,$D$2:$D$124,"ABIERTA")) -> ... | U35: =if(Q35=0,"...",if(P35=0,"...",V35/(T35-V35))) -> ... | V35: =if(Q35=0,"...",if(P35=0,"...",sumifs($N$2:$N$124,$B$2:$B$124,P35,$D$2:$D$124,"ABIERTA"))) -> ...
A36: Binance | B36: BTC | C36: 45277 | D36: CERRADA | F36: =if(B36=0,"...", IF(E36=0,today()-C36,E36-C36)) -> 840 | G36: 0.00122 | H36: 40983.61 | I36: =IF(B36=0,"...",IF(D36="CERRADA","-",VLOOKUP(B36,$AC$2:$AD$27,2,FALSE))) -> - | J36: =IF(B36=0,"...",IF(D36="CERRADA","Valor Venta",I36*(1-VLOOKUP(A36,Config!$B$3:$C$22,2,FALSE)))) -> Valor Venta | K36: =if(B36=0,"...",G36*H36) -> 50.000004 | L36: =IF(B36=0,"...",G36*J36) -> #VALUE! | M36: =if(B36=0,"...",L36/K36-1) -> #VALUE! | N36: =if(B36=0,"...",L36-K36) -> #VALUE! | P36: XRP | Q36: =if(P36=0,"...",sumifs($G$2:$G$124,$B$2:$B$124,P36,$D$2:$D$124,"ABIERTA")) -> 32 | R36: =if(P36=0,"",T36/$Y$18) -> #ERROR! | S36: =if(Q36=0,"...",if(P36=0,"...",sumifs($K$2:$K$124,$B$2:$B$124,P36,$D$2:$D$124,"ABIERTA")/Q36)) -> 3.2356 | T36: =if(P36=0,"...",sumifs($L$2:$L$124,$B$2:$B$124,P36,$D$2:$D$124,"ABIERTA")) -> 41.297984 | U36: =if(Q36=0,"...",if(P36=0,"...",V36/(T36-V36))) -> -0.60113673 | V36: =if(Q36=0,"...",if(P36=0,"...",sumifs($N$2:$N$124,$B$2:$B$124,P36,$D$2:$D$124,"ABIERTA"))) -> -62.241216
A37: Binance | B37: SOL | C37: 45278 | D37: CERRADA | E37: 45282 | F37: =if(B37=0,"...", IF(E37=0,today()-C37,E37-C37)) -> 4 | G37: 1.46 | H37: 68.49 | I37: =IF(B37=0,"...",IF(D37="CERRADA","-",VLOOKUP(B37,$AC$2:$AD$27,2,FALSE))) -> - | J37: 97 | K37: =if(B37=0,"...",G37*H37) -> 99.9954 | L37: =IF(B37=0,"...",G37*J37) -> 141.62 | M37: =if(B37=0,"...",L37/K37-1) -> 0.41626515 | N37: =if(B37=0,"...",L37-K37) -> 41.6246 | Q37: =if(P37=0,"...",sumifs($G$2:$G$124,$B$2:$B$124,P37,$D$2:$D$124,"ABIERTA")) -> ... | R37: =if(P37=0,"",T37/$Y$18) | S37: =if(Q37=0,"...",if(P37=0,"...",sumifs($K$2:$K$124,$B$2:$B$124,P37,$D$2:$D$124,"ABIERTA")/Q37)) -> ... | T37: =if(P37=0,"...",sumifs($L$2:$L$124,$B$2:$B$124,P37,$D$2:$D$124,"ABIERTA")) -> ... | U37: =if(Q37=0,"...",if(P37=0,"...",V37/(T37-V37))) -> ... | V37: =if(Q37=0,"...",if(P37=0,"...",sumifs($N$2:$N$124,$B$2:$B$124,P37,$D$2:$D$124,"ABIERTA"))) -> ...
A38: Binance | B38: BTC | C38: 45277 | D38: CERRADA | F38: =if(B38=0,"...", IF(E38=0,today()-C38,E38-C38)) -> 840 | G38: 0.0012 | H38: 41666.67 | I38: =IF(B38=0,"...",IF(D38="CERRADA","-",VLOOKUP(B38,$AC$2:$AD$27,2,FALSE))) -> - | J38: =IF(B38=0,"...",IF(D38="CERRADA","Valor Venta",I38*(1-VLOOKUP(A38,Config!$B$3:$C$22,2,FALSE)))) -> Valor Venta | K38: =if(B38=0,"...",G38*H38) -> 50.000004 | L38: =IF(B38=0,"...",G38*J38) -> #VALUE! | M38: =if(B38=0,"...",L38/K38-1) -> #VALUE! | N38: =if(B38=0,"...",L38-K38) -> #VALUE! | P38: SOL | Q38: =if(P38=0,"...",sumifs($G$2:$G$124,$B$2:$B$124,P38,$D$2:$D$124,"ABIERTA")) -> 9.646 | R38: =if(P38=0,"",T38/$Y$18) -> #ERROR! | S38: =if(Q38=0,"...",if(P38=0,"...",sumifs($K$2:$K$124,$B$2:$B$124,P38,$D$2:$D$124,"ABIERTA")/Q38)) -> 154.17525 | T38: =if(P38=0,"...",sumifs($L$2:$L$124,$B$2:$B$124,P38,$D$2:$D$124,"ABIERTA")) -> 764.22082 | U38: =if(Q38=0,"...",if(P38=0,"...",V38/(T38-V38))) -> -0.48612563 | V38: =if(Q38=0,"...",if(P38=0,"...",sumifs($N$2:$N$124,$B$2:$B$124,P38,$D$2:$D$124,"ABIERTA"))) -> -722.95361
A39: Binance | B39: MATIC | C39: 45279 | D39: CERRADA | F39: =if(B39=0,"...", IF(E39=0,today()-C39,E39-C39)) -> 838 | G39: 149.2 | H39: 0.79 | I39: =IF(B39=0,"...",IF(D39="CERRADA","-",VLOOKUP(B39,$AC$2:$AD$27,2,FALSE))) -> - | J39: 0.9 | K39: =if(B39=0,"...",G39*H39) -> 117.868 | L39: =IF(B39=0,"...",G39*J39) -> 134.28 | M39: =if(B39=0,"...",L39/K39-1) -> 0.13924051 | N39: =if(B39=0,"...",L39-K39) -> 16.412 | Q39: =if(P39=0,"...",sumifs($G$2:$G$124,$B$2:$B$124,P39,$D$2:$D$124,"ABIERTA")) -> ... | R39: =if(P39=0,"",T39/$Y$18) | S39: =if(Q39=0,"...",if(P39=0,"...",sumifs($K$2:$K$124,$B$2:$B$124,P39,$D$2:$D$124,"ABIERTA")/Q39)) -> ... | T39: =if(P39=0,"...",sumifs($L$2:$L$124,$B$2:$B$124,P39,$D$2:$D$124,"ABIERTA")) -> ... | U39: =if(Q39=0,"...",if(P39=0,"...",V39/(T39-V39))) -> ... | V39: =if(Q39=0,"...",if(P39=0,"...",sumifs($N$2:$N$124,$B$2:$B$124,P39,$D$2:$D$124,"ABIERTA"))) -> ...
A40: Binance | B40: SOL | C40: 45271 | D40: CERRADA | E40: 45282 | F40: =if(B40=0,"...", IF(E40=0,today()-C40,E40-C40)) -> 11 | G40: 0.28 | H40: 69.39 | I40: =IF(B40=0,"...",IF(D40="CERRADA","-",VLOOKUP(B40,$AC$2:$AD$27,2,FALSE))) -> - | J40: 97 | K40: =if(B40=0,"...",G40*H40) -> 19.4292 | L40: =IF(B40=0,"...",G40*J40) -> 27.16 | M40: =if(B40=0,"...",L40/K40-1) -> 0.39789595 | N40: =if(B40=0,"...",L40-K40) -> 7.7308 | Q40: =if(P40=0,"...",sumifs($G$2:$G$124,$B$2:$B$124,P40,$D$2:$D$124,"ABIERTA")) -> ... | R40: =if(P40=0,"",T40/$Y$18) | S40: =if(Q40=0,"...",if(P40=0,"...",sumifs($K$2:$K$124,$B$2:$B$124,P40,$D$2:$D$124,"ABIERTA")/Q40)) -> ... | T40: =if(P40=0,"...",sumifs($L$2:$L$124,$B$2:$B$124,P40,$D$2:$D$124,"ABIERTA")) -> ... | U40: =if(Q40=0,"...",if(P40=0,"...",V40/(T40-V40))) -> ... | V40: =if(Q40=0,"...",if(P40=0,"...",sumifs($N$2:$N$124,$B$2:$B$124,P40,$D$2:$D$124,"ABIERTA"))) -> ...
A41: Binance | B41: BTC | C41: 45287 | D41: CERRADA | F41: =if(B41=0,"...", IF(E41=0,today()-C41,E41-C41)) -> 830 | G41: 0.00116 | H41: 42818.97 | I41: =IF(B41=0,"...",IF(D41="CERRADA","-",VLOOKUP(B41,$AC$2:$AD$27,2,FALSE))) -> - | J41: =IF(B41=0,"...",IF(D41="CERRADA","Valor Venta",I41*(1-VLOOKUP(A41,Config!$B$3:$C$22,2,FALSE)))) -> Valor Venta | K41: =if(B41=0,"...",G41*H41) -> 49.670005 | L41: =IF(B41=0,"...",G41*J41) -> #VALUE! | M41: =if(B41=0,"...",L41/K41-1) -> #VALUE! | N41: =if(B41=0,"...",L41-K41) -> #VALUE! | Q41: =if(P41=0,"...",sumifs($G$2:$G$124,$B$2:$B$124,P41,$D$2:$D$124,"ABIERTA")) -> ... | R41: =if(P41=0,"",T41/$Y$18) | S41: =if(Q41=0,"...",if(P41=0,"...",sumifs($K$2:$K$124,$B$2:$B$124,P41,$D$2:$D$124,"ABIERTA")/Q41)) -> ... | T41: =if(P41=0,"...",sumifs($L$2:$L$124,$B$2:$B$124,P41,$D$2:$D$124,"ABIERTA")) -> ... | U41: =if(Q41=0,"...",if(P41=0,"...",V41/(T41-V41))) -> ... | V41: =if(Q41=0,"...",if(P41=0,"...",sumifs($N$2:$N$124,$B$2:$B$124,P41,$D$2:$D$124,"ABIERTA"))) -> ...
A42: Binance | B42: BTC | C42: 45288 | D42: CERRADA | F42: =if(B42=0,"...", IF(E42=0,today()-C42,E42-C42)) -> 829 | G42: 0.00117 | H42: 42641.03 | I42: =IF(B42=0,"...",IF(D42="CERRADA","-",VLOOKUP(B42,$AC$2:$AD$27,2,FALSE))) -> - | J42: =IF(B42=0,"...",IF(D42="CERRADA","Valor Venta",I42*(1-VLOOKUP(A42,Config!$B$3:$C$22,2,FALSE)))) -> Valor Venta | K42: =if(B42=0,"...",G42*H42) -> 49.890005 | L42: =IF(B42=0,"...",G42*J42) -> #VALUE! | M42: =if(B42=0,"...",L42/K42-1) -> #VALUE! | N42: =if(B42=0,"...",L42-K42) -> #VALUE! | Q42: =if(P42=0,"...",sumifs($G$2:$G$124,$B$2:$B$124,P42,$D$2:$D$124,"ABIERTA")) -> ... | R42: =if(P42=0,"",T42/$Y$18) | S42: =if(Q42=0,"...",if(P42=0,"...",sumifs($K$2:$K$124,$B$2:$B$124,P42,$D$2:$D$124,"ABIERTA")/Q42)) -> ... | T42: =if(P42=0,"...",sumifs($L$2:$L$124,$B$2:$B$124,P42,$D$2:$D$124,"ABIERTA")) -> ... | U42: =if(Q42=0,"...",if(P42=0,"...",V42/(T42-V42))) -> ... | V42: =if(Q42=0,"...",if(P42=0,"...",sumifs($N$2:$N$124,$B$2:$B$124,P42,$D$2:$D$124,"ABIERTA"))) -> ...
A43: Binance | B43: BTC | C43: 45288 | D43: CERRADA | F43: =if(B43=0,"...", IF(E43=0,today()-C43,E43-C43)) -> 829 | G43: 0.00117 | H43: 42470.09 | I43: =IF(B43=0,"...",IF(D43="CERRADA","-",VLOOKUP(B43,$AC$2:$AD$27,2,FALSE))) -> - | J43: =IF(B43=0,"...",IF(D43="CERRADA","Valor Venta",I43*(1-VLOOKUP(A43,Config!$B$3:$C$22,2,FALSE)))) -> Valor Venta | K43: =if(B43=0,"...",G43*H43) -> 49.690005 | L43: =IF(B43=0,"...",G43*J43) -> #VALUE! | M43: =if(B43=0,"...",L43/K43-1) -> #VALUE! | N43: =if(B43=0,"...",L43-K43) -> #VALUE! | Q43: =if(P43=0,"...",sumifs($G$2:$G$124,$B$2:$B$124,P43,$D$2:$D$124,"ABIERTA")) -> ... | R43: =if(P43=0,"",T43/$Y$18) | S43: =if(Q43=0,"...",if(P43=0,"...",sumifs($K$2:$K$124,$B$2:$B$124,P43,$D$2:$D$124,"ABIERTA")/Q43)) -> ... | T43: =if(P43=0,"...",sumifs($L$2:$L$124,$B$2:$B$124,P43,$D$2:$D$124,"ABIERTA")) -> ... | U43: =if(Q43=0,"...",if(P43=0,"...",V43/(T43-V43))) -> ... | V43: =if(Q43=0,"...",if(P43=0,"...",sumifs($N$2:$N$124,$B$2:$B$124,P43,$D$2:$D$124,"ABIERTA"))) -> ...
A44: Binance | B44: SOL | C44: 45297 | D44: CERRADA | F44: =if(B44=0,"...", IF(E44=0,today()-C44,E44-C44)) -> 820 | G44: 1.06 | H44: 94.13 | I44: =IF(B44=0,"...",IF(D44="CERRADA","-",VLOOKUP(B44,$AC$2:$AD$27,2,FALSE))) -> - | J44: 109.8 | K44: =if(B44=0,"...",G44*H44) -> 99.7778 | L44: =IF(B44=0,"...",G44*J44) -> 116.388 | M44: =if(B44=0,"...",L44/K44-1) -> 0.1664719 | N44: =if(B44=0,"...",L44-K44) -> 16.6102 | Q44: =if(P44=0,"...",sumifs($G$2:$G$124,$B$2:$B$124,P44,$D$2:$D$124,"ABIERTA")) -> ... | R44: =if(P44=0,"",T44/$Y$18) | S44: =if(Q44=0,"...",if(P44=0,"...",sumifs($K$2:$K$124,$B$2:$B$124,P44,$D$2:$D$124,"ABIERTA")/Q44)) -> ... | T44: =if(P44=0,"...",sumifs($L$2:$L$124,$B$2:$B$124,P44,$D$2:$D$124,"ABIERTA")) -> ... | U44: =if(Q44=0,"...",if(P44=0,"...",V44/(T44-V44))) -> ... | V44: =if(Q44=0,"...",if(P44=0,"...",sumifs($N$2:$N$124,$B$2:$B$124,P44,$D$2:$D$124,"ABIERTA"))) -> ...
A45: Binance | B45: BTC | C45: 45303 | D45: CERRADA | F45: =if(B45=0,"...", IF(E45=0,today()-C45,E45-C45)) -> 814 | G45: 0.00117 | H45: 43589.74 | I45: =IF(B45=0,"...",IF(D45="CERRADA","-",VLOOKUP(B45,$AC$2:$AD$27,2,FALSE))) -> - | J45: =IF(B45=0,"...",IF(D45="CERRADA","Valor Venta",I45*(1-VLOOKUP(A45,Config!$B$3:$C$22,2,FALSE)))) -> Valor Venta | K45: =if(B45=0,"...",G45*H45) -> 50.999996 | L45: =IF(B45=0,"...",G45*J45) -> #VALUE! | M45: =if(B45=0,"...",L45/K45-1) -> #VALUE! | N45: =if(B45=0,"...",L45-K45) -> #VALUE! | Q45: =if(P45=0,"...",sumifs($G$2:$G$124,$B$2:$B$124,P45,$D$2:$D$124,"ABIERTA")) -> ... | R45: =if(P45=0,"",T45/$Y$18) | S45: =if(Q45=0,"...",if(P45=0,"...",sumifs($K$2:$K$124,$B$2:$B$124,P45,$D$2:$D$124,"ABIERTA")/Q45)) -> ... | T45: =if(P45=0,"...",sumifs($L$2:$L$124,$B$2:$B$124,P45,$D$2:$D$124,"ABIERTA")) -> ... | U45: =if(Q45=0,"...",if(P45=0,"...",V45/(T45-V45))) -> ... | V45: =if(Q45=0,"...",if(P45=0,"...",sumifs($N$2:$N$124,$B$2:$B$124,P45,$D$2:$D$124,"ABIERTA"))) -> ...
A46: Binance | B46: BTC | C46: 45303 | D46: CERRADA | F46: =if(B46=0,"...", IF(E46=0,today()-C46,E46-C46)) -> 814 | G46: 0.00232 | H46: 43534.48 | I46: =IF(B46=0,"...",IF(D46="CERRADA","-",VLOOKUP(B46,$AC$2:$AD$27,2,FALSE))) -> - | J46: =IF(B46=0,"...",IF(D46="CERRADA","Valor Venta",I46*(1-VLOOKUP(A46,Config!$B$3:$C$22,2,FALSE)))) -> Valor Venta | K46: =if(B46=0,"...",G46*H46) -> 100.99999 | L46: =IF(B46=0,"...",G46*J46) -> #VALUE! | M46: =if(B46=0,"...",L46/K46-1) -> #VALUE! | N46: =if(B46=0,"...",L46-K46) -> #VALUE! | Q46: =if(P46=0,"...",sumifs($G$2:$G$124,$B$2:$B$124,P46,$D$2:$D$124,"ABIERTA")) -> ... | R46: =if(P46=0,"",T46/$Y$18) | S46: =if(Q46=0,"...",if(P46=0,"...",sumifs($K$2:$K$124,$B$2:$B$124,P46,$D$2:$D$124,"ABIERTA")/Q46)) -> ... | T46: =if(P46=0,"...",sumifs($L$2:$L$124,$B$2:$B$124,P46,$D$2:$D$124,"ABIERTA")) -> ... | U46: =if(Q46=0,"...",if(P46=0,"...",V46/(T46-V46))) -> ... | V46: =if(Q46=0,"...",if(P46=0,"...",sumifs($N$2:$N$124,$B$2:$B$124,P46,$D$2:$D$124,"ABIERTA"))) -> ...
A47: Binance | B47: XTZ | C47: 45305 | D47: CERRADA | F47: =if(B47=0,"...", IF(E47=0,today()-C47,E47-C47)) -> 812 | G47: 43.1 | H47: 1.16 | I47: =IF(B47=0,"...",IF(D47="CERRADA","-",VLOOKUP(B47,$AC$2:$AD$27,2,FALSE))) -> - | J47: 1.19 | K47: =if(B47=0,"...",G47*H47) -> 49.996 | L47: =IF(B47=0,"...",G47*J47) -> 51.289 | M47: =if(B47=0,"...",L47/K47-1) -> 0.025862069 | N47: =if(B47=0,"...",L47-K47) -> 1.293 | Q47: =if(P47=0,"...",sumifs($G$2:$G$124,$B$2:$B$124,P47,$D$2:$D$124,"ABIERTA")) -> ... | R47: =if(P47=0,"",T47/$Y$18) | S47: =if(Q47=0,"...",if(P47=0,"...",sumifs($K$2:$K$124,$B$2:$B$124,P47,$D$2:$D$124,"ABIERTA")/Q47)) -> ... | T47: =if(P47=0,"...",sumifs($L$2:$L$124,$B$2:$B$124,P47,$D$2:$D$124,"ABIERTA")) -> ... | U47: =if(Q47=0,"...",if(P47=0,"...",V47/(T47-V47))) -> ... | V47: =if(Q47=0,"...",if(P47=0,"...",sumifs($N$2:$N$124,$B$2:$B$124,P47,$D$2:$D$124,"ABIERTA"))) -> ...
A48: Binance | B48: BTC | C48: 45305 | D48: CERRADA | F48: =if(B48=0,"...", IF(E48=0,today()-C48,E48-C48)) -> 812 | G48: 0.00093 | H48: 42860.22 | I48: =IF(B48=0,"...",IF(D48="CERRADA","-",VLOOKUP(B48,$AC$2:$AD$27,2,FALSE))) -> - | J48: 42649.15 | K48: =if(B48=0,"...",G48*H48) -> 39.860005 | L48: =IF(B48=0,"...",G48*J48) -> 39.66371 | M48: =if(B48=0,"...",L48/K48-1) -> -0.0049246131 | N48: =if(B48=0,"...",L48-K48) -> -0.1962951 | Q48: =if(P48=0,"...",sumifs($G$2:$G$124,$B$2:$B$124,P48,$D$2:$D$124,"ABIERTA")) -> ... | R48: =if(P48=0,"",T48/$Y$18) | S48: =if(Q48=0,"...",if(P48=0,"...",sumifs($K$2:$K$124,$B$2:$B$124,P48,$D$2:$D$124,"ABIERTA")/Q48)) -> ... | T48: =if(P48=0,"...",sumifs($L$2:$L$124,$B$2:$B$124,P48,$D$2:$D$124,"ABIERTA")) -> ... | U48: =if(Q48=0,"...",if(P48=0,"...",V48/(T48-V48))) -> ... | V48: =if(Q48=0,"...",if(P48=0,"...",sumifs($N$2:$N$124,$B$2:$B$124,P48,$D$2:$D$124,"ABIERTA"))) -> ...
A49: Binance | B49: SAND | C49: 45305 | D49: CERRADA | F49: =if(B49=0,"...", IF(E49=0,today()-C49,E49-C49)) -> 812 | G49: 110 | H49: 0.51 | I49: =IF(B49=0,"...",IF(D49="CERRADA","-",VLOOKUP(B49,$AC$2:$AD$27,2,FALSE))) -> - | J49: 0.51 | K49: =if(B49=0,"...",G49*H49) -> 56.1 | L49: =IF(B49=0,"...",G49*J49) -> 56.1 | M49: =if(B49=0,"...",L49/K49-1) -> 0 | N49: =if(B49=0,"...",L49-K49) -> 0 | Q49: =if(P49=0,"...",sumifs($G$2:$G$124,$B$2:$B$124,P49,$D$2:$D$124,"ABIERTA")) -> ... | R49: =if(P49=0,"",T49/$Y$18) | S49: =if(Q49=0,"...",if(P49=0,"...",sumifs($K$2:$K$124,$B$2:$B$124,P49,$D$2:$D$124,"ABIERTA")/Q49)) -> ... | T49: =if(P49=0,"...",sumifs($L$2:$L$124,$B$2:$B$124,P49,$D$2:$D$124,"ABIERTA")) -> ... | U49: =if(Q49=0,"...",if(P49=0,"...",V49/(T49-V49))) -> ... | V49: =if(Q49=0,"...",if(P49=0,"...",sumifs($N$2:$N$124,$B$2:$B$124,P49,$D$2:$D$124,"ABIERTA"))) -> ...
A50: Binance | B50: CRV | C50: 45306 | D50: CERRADA | F50: =if(B50=0,"...", IF(E50=0,today()-C50,E50-C50)) -> 811 | G50: 94.9 | H50: 0.54 | I50: =IF(B50=0,"...",IF(D50="CERRADA","-",VLOOKUP(B50,$AC$2:$AD$27,2,FALSE))) -> - | J50: 0.55 | K50: =if(B50=0,"...",G50*H50) -> 51.246 | L50: =IF(B50=0,"...",G50*J50) -> 52.195 | M50: =if(B50=0,"...",L50/K50-1) -> 0.018518519 | N50: =if(B50=0,"...",L50-K50) -> 0.949 | Q50: =if(P50=0,"...",sumifs($G$2:$G$124,$B$2:$B$124,P50,$D$2:$D$124,"ABIERTA")) -> ... | R50: =if(P50=0,"",T50/$Y$18) | S50: =if(Q50=0,"...",if(P50=0,"...",sumifs($K$2:$K$124,$B$2:$B$124,P50,$D$2:$D$124,"ABIERTA")/Q50)) -> ... | T50: =if(P50=0,"...",sumifs($L$2:$L$124,$B$2:$B$124,P50,$D$2:$D$124,"ABIERTA")) -> ... | U50: =if(Q50=0,"...",if(P50=0,"...",V50/(T50-V50))) -> ... | V50: =if(Q50=0,"...",if(P50=0,"...",sumifs($N$2:$N$124,$B$2:$B$124,P50,$D$2:$D$124,"ABIERTA"))) -> ...
A51: Binance | B51: BTC | C51: 45309 | D51: CERRADA | F51: =if(B51=0,"...", IF(E51=0,today()-C51,E51-C51)) -> 808 | G51: 0.00121 | H51: 41132.23 | I51: =IF(B51=0,"...",IF(D51="CERRADA","-",VLOOKUP(B51,$AC$2:$AD$27,2,FALSE))) -> - | J51: 43500 | K51: =if(B51=0,"...",G51*H51) -> 49.769998 | L51: =IF(B51=0,"...",G51*J51) -> 52.635 | M51: =if(B51=0,"...",L51/K51-1) -> 0.057564834 | N51: =if(B51=0,"...",L51-K51) -> 2.8650017 | Q51: =if(P51=0,"...",sumifs($G$2:$G$124,$B$2:$B$124,P51,$D$2:$D$124,"ABIERTA")) -> ... | R51: =if(P51=0,"",T51/$Y$18) | S51: =if(Q51=0,"...",if(P51=0,"...",sumifs($K$2:$K$124,$B$2:$B$124,P51,$D$2:$D$124,"ABIERTA")/Q51)) -> ... | T51: =if(P51=0,"...",sumifs($L$2:$L$124,$B$2:$B$124,P51,$D$2:$D$124,"ABIERTA")) -> ... | U51: =if(Q51=0,"...",if(P51=0,"...",V51/(T51-V51))) -> ... | V51: =if(Q51=0,"...",if(P51=0,"...",sumifs($N$2:$N$124,$B$2:$B$124,P51,$D$2:$D$124,"ABIERTA"))) -> ...
A52: Binance | B52: MANA | C52: 45309 | D52: CERRADA | F52: =if(B52=0,"...", IF(E52=0,today()-C52,E52-C52)) -> 808 | G52: 114 | H52: 0.44 | I52: =IF(B52=0,"...",IF(D52="CERRADA","-",VLOOKUP(B52,$AC$2:$AD$27,2,FALSE))) -> - | J52: 0.48 | K52: =if(B52=0,"...",G52*H52) -> 50.16 | L52: =IF(B52=0,"...",G52*J52) -> 54.72 | M52: =if(B52=0,"...",L52/K52-1) -> 0.090909091 | N52: =if(B52=0,"...",L52-K52) -> 4.56 | Q52: =if(P52=0,"...",sumifs($G$2:$G$124,$B$2:$B$124,P52,$D$2:$D$124,"ABIERTA")) -> ... | R52: =if(P52=0,"",T52/$Y$18) | S52: =if(Q52=0,"...",if(P52=0,"...",sumifs($K$2:$K$124,$B$2:$B$124,P52,$D$2:$D$124,"ABIERTA")/Q52)) -> ... | T52: =if(P52=0,"...",sumifs($L$2:$L$124,$B$2:$B$124,P52,$D$2:$D$124,"ABIERTA")) -> ... | U52: =if(Q52=0,"...",if(P52=0,"...",V52/(T52-V52))) -> ... | V52: =if(Q52=0,"...",if(P52=0,"...",sumifs($N$2:$N$124,$B$2:$B$124,P52,$D$2:$D$124,"ABIERTA"))) -> ...
A53: Binance | B53: 1INCH | C53: 45309 | D53: CERRADA | F53: =if(B53=0,"...", IF(E53=0,today()-C53,E53-C53)) -> 808 | G53: 114.3 | H53: 0.42 | I53: =IF(B53=0,"...",IF(D53="CERRADA","-",VLOOKUP(B53,$AC$2:$AD$27,2,FALSE))) -> - | J53: 0.41 | K53: =if(B53=0,"...",G53*H53) -> 48.006 | L53: =IF(B53=0,"...",G53*J53) -> 46.863 | M53: =if(B53=0,"...",L53/K53-1) -> -0.023809524 | N53: =if(B53=0,"...",L53-K53) -> -1.143 | Q53: =if(P53=0,"...",sumifs($G$2:$G$124,$B$2:$B$124,P53,$D$2:$D$124,"ABIERTA")) -> ... | R53: =if(P53=0,"",T53/$Y$18) | S53: =if(Q53=0,"...",if(P53=0,"...",sumifs($K$2:$K$124,$B$2:$B$124,P53,$D$2:$D$124,"ABIERTA")/Q53)) -> ... | T53: =if(P53=0,"...",sumifs($L$2:$L$124,$B$2:$B$124,P53,$D$2:$D$124,"ABIERTA")) -> ... | U53: =if(Q53=0,"...",if(P53=0,"...",V53/(T53-V53))) -> ... | V53: =if(Q53=0,"...",if(P53=0,"...",sumifs($N$2:$N$124,$B$2:$B$124,P53,$D$2:$D$124,"ABIERTA"))) -> ...
A54: Binance | B54: SOL | C54: 6692725 | D54: CERRADA | F54: =if(B54=0,"...", IF(E54=0,today()-C54,E54-C54)) -> -6646608 | G54: 0.59 | H54: 92.46 | I54: =IF(B54=0,"...",IF(D54="CERRADA","-",VLOOKUP(B54,$AC$2:$AD$27,2,FALSE))) -> - | J54: 109.8 | K54: =if(B54=0,"...",G54*H54) -> 54.5514 | L54: =IF(B54=0,"...",G54*J54) -> 64.782 | M54: =if(B54=0,"...",L54/K54-1) -> 0.18754056 | N54: =if(B54=0,"...",L54-K54) -> 10.2306 | Q54: =if(P54=0,"...",sumifs($G$2:$G$124,$B$2:$B$124,P54,$D$2:$D$124,"ABIERTA")) -> ... | R54: =if(P54=0,"",T54/$Y$18) | S54: =if(Q54=0,"...",if(P54=0,"...",sumifs($K$2:$K$124,$B$2:$B$124,P54,$D$2:$D$124,"ABIERTA")/Q54)) -> ... | T54: =if(P54=0,"...",sumifs($L$2:$L$124,$B$2:$B$124,P54,$D$2:$D$124,"ABIERTA")) -> ... | U54: =if(Q54=0,"...",if(P54=0,"...",V54/(T54-V54))) -> ... | V54: =if(Q54=0,"...",if(P54=0,"...",sumifs($N$2:$N$124,$B$2:$B$124,P54,$D$2:$D$124,"ABIERTA"))) -> ...
A55: Binance | B55: MATIC | C55: 45317 | D55: CERRADA | F55: =if(B55=0,"...", IF(E55=0,today()-C55,E55-C55)) -> 800 | G55: 66.3 | H55: 0.75 | I55: =IF(B55=0,"...",IF(D55="CERRADA","-",VLOOKUP(B55,$AC$2:$AD$27,2,FALSE))) -> - | J55: 0.9 | K55: =if(B55=0,"...",G55*H55) -> 49.725 | L55: =IF(B55=0,"...",G55*J55) -> 59.67 | M55: =if(B55=0,"...",L55/K55-1) -> 0.2 | N55: =if(B55=0,"...",L55-K55) -> 9.945 | Q55: =if(P55=0,"...",sumifs($G$2:$G$124,$B$2:$B$124,P55,$D$2:$D$124,"ABIERTA")) -> ... | R55: =if(P55=0,"",T55/$Y$18) | S55: =if(Q55=0,"...",if(P55=0,"...",sumifs($K$2:$K$124,$B$2:$B$124,P55,$D$2:$D$124,"ABIERTA")/Q55)) -> ... | T55: =if(P55=0,"...",sumifs($L$2:$L$124,$B$2:$B$124,P55,$D$2:$D$124,"ABIERTA")) -> ... | U55: =if(Q55=0,"...",if(P55=0,"...",V55/(T55-V55))) -> ... | V55: =if(Q55=0,"...",if(P55=0,"...",sumifs($N$2:$N$124,$B$2:$B$124,P55,$D$2:$D$124,"ABIERTA"))) -> ...
A56: Binance | B56: SOL | C56: 6692730 | D56: CERRADA | F56: =if(B56=0,"...", IF(E56=0,today()-C56,E56-C56)) -> -6646613 | G56: 0.56 | H56: 92.8 | I56: =IF(B56=0,"...",IF(D56="CERRADA","-",VLOOKUP(B56,$AC$2:$AD$27,2,FALSE))) -> - | J56: 109.8 | K56: =if(B56=0,"...",G56*H56) -> 51.968 | L56: =IF(B56=0,"...",G56*J56) -> 61.488 | M56: =if(B56=0,"...",L56/K56-1) -> 0.18318966 | N56: =if(B56=0,"...",L56-K56) -> 9.52 | Q56: =if(P56=0,"...",sumifs($G$2:$G$124,$B$2:$B$124,P56,$D$2:$D$124,"ABIERTA")) -> ... | R56: =if(P56=0,"",T56/$Y$18) | S56: =if(Q56=0,"...",if(P56=0,"...",sumifs($K$2:$K$124,$B$2:$B$124,P56,$D$2:$D$124,"ABIERTA")/Q56)) -> ... | T56: =if(P56=0,"...",sumifs($L$2:$L$124,$B$2:$B$124,P56,$D$2:$D$124,"ABIERTA")) -> ... | U56: =if(Q56=0,"...",if(P56=0,"...",V56/(T56-V56))) -> ... | V56: =if(Q56=0,"...",if(P56=0,"...",sumifs($N$2:$N$124,$B$2:$B$124,P56,$D$2:$D$124,"ABIERTA"))) -> ...
A57: Binance | B57: SOL | C57: 45320 | D57: CERRADA | F57: =if(B57=0,"...", IF(E57=0,today()-C57,E57-C57)) -> 797 | G57: 2.95 | H57: 91.91 | I57: =IF(B57=0,"...",IF(D57="CERRADA","-",VLOOKUP(B57,$AC$2:$AD$27,2,FALSE))) -> - | J57: 109.8 | K57: =if(B57=0,"...",G57*H57) -> 271.1345 | L57: =IF(B57=0,"...",G57*J57) -> 323.91 | M57: =if(B57=0,"...",L57/K57-1) -> 0.19464694 | N57: =if(B57=0,"...",L57-K57) -> 52.7755 | Q57: =if(P57=0,"...",sumifs($G$2:$G$124,$B$2:$B$124,P57,$D$2:$D$124,"ABIERTA")) -> ... | R57: =if(P57=0,"",T57/$Y$18) | S57: =if(Q57=0,"...",if(P57=0,"...",sumifs($K$2:$K$124,$B$2:$B$124,P57,$D$2:$D$124,"ABIERTA")/Q57)) -> ... | T57: =if(P57=0,"...",sumifs($L$2:$L$124,$B$2:$B$124,P57,$D$2:$D$124,"ABIERTA")) -> ... | U57: =if(Q57=0,"...",if(P57=0,"...",V57/(T57-V57))) -> ... | V57: =if(Q57=0,"...",if(P57=0,"...",sumifs($N$2:$N$124,$B$2:$B$124,P57,$D$2:$D$124,"ABIERTA"))) -> ...
A58: Binance | B58: NEAR | C58: 45322 | D58: CERRADA | F58: =if(B58=0,"...", IF(E58=0,today()-C58,E58-C58)) -> 795 | G58: 17.3 | H58: 2.88 | I58: =IF(B58=0,"...",IF(D58="CERRADA","-",VLOOKUP(B58,$AC$2:$AD$27,2,FALSE))) -> - | J58: 2.93 | K58: =if(B58=0,"...",G58*H58) -> 49.824 | L58: =IF(B58=0,"...",G58*J58) -> 50.689 | M58: =if(B58=0,"...",L58/K58-1) -> 0.017361111 | N58: =if(B58=0,"...",L58-K58) -> 0.865 | Q58: =if(P58=0,"...",sumifs($G$2:$G$124,$B$2:$B$124,P58,$D$2:$D$124,"ABIERTA")) -> ... | R58: =if(P58=0,"",T58/$Y$18) | S58: =if(Q58=0,"...",if(P58=0,"...",sumifs($K$2:$K$124,$B$2:$B$124,P58,$D$2:$D$124,"ABIERTA")/Q58)) -> ... | T58: =if(P58=0,"...",sumifs($L$2:$L$124,$B$2:$B$124,P58,$D$2:$D$124,"ABIERTA")) -> ... | U58: =if(Q58=0,"...",if(P58=0,"...",V58/(T58-V58))) -> ... | V58: =if(Q58=0,"...",if(P58=0,"...",sumifs($N$2:$N$124,$B$2:$B$124,P58,$D$2:$D$124,"ABIERTA"))) -> ...
... A68: Binance | B68: SOL | C68: 45343 | D68: CERRADA | F68: =if(B68=0,"...", IF(E68=0,today()-C68,E68-C68)) -> 774 | G68: 1.9 | H68: 102.55 | I68: =IF(B68=0,"...",IF(D68="CERRADA","-",VLOOKUP(B68,$AC$2:$AD$27,2,FALSE))) -> - | J68: 131.68 | K68: =if(B68=0,"...",G68*H68) -> 194.845 | L68: =IF(B68=0,"...",G68*J68) -> 250.192 | M68: =if(B68=0,"...",L68/K68-1) -> 0.28405656 | N68: =if(B68=0,"...",L68-K68) -> 55.347 | Q68: =if(P68=0,"...",sumifs($G$2:$G$124,$B$2:$B$124,P68,$D$2:$D$124,"ABIERTA")) -> ... | R68: =if(P68=0,"",T68/$Y$18) | S68: =if(Q68=0,"...",if(P68=0,"...",sumifs($K$2:$K$124,$B$2:$B$124,P68,$D$2:$D$124,"ABIERTA")/Q68)) -> ... | T68: =if(P68=0,"...",sumifs($L$2:$L$124,$B$2:$B$124,P68,$D$2:$D$124,"ABIERTA")) -> ... | U68: =if(Q68=0,"...",if(P68=0,"...",V68/(T68-V68))) -> ... | V68: =if(Q68=0,"...",if(P68=0,"...",sumifs($N$2:$N$124,$B$2:$B$124,P68,$D$2:$D$124,"ABIERTA"))) -> ...
A69: Binance | B69: SHIB | C69: 45362 | D69: CERRADA | F69: =if(B69=0,"...", IF(E69=0,today()-C69,E69-C69)) -> 755 | G69: 2898559 | H69: 3.45e-05 | I69: =IF(B69=0,"...",IF(D69="CERRADA","-",VLOOKUP(B69,$AC$2:$AD$27,2,FALSE))) -> - | J69: =IF(B69=0,"...",IF(D69="CERRADA","Valor Venta",I69*(1-VLOOKUP(A69,Config!$B$3:$C$22,2,FALSE)))) -> Valor Venta | K69: =if(B69=0,"...",G69*H69) -> 100.00029 | L69: =IF(B69=0,"...",G69*J69) -> #VALUE! | M69: =if(B69=0,"...",L69/K69-1) -> #VALUE! | N69: =if(B69=0,"...",L69-K69) -> #VALUE! | Q69: =if(P69=0,"...",sumifs($G$2:$G$124,$B$2:$B$124,P69,$D$2:$D$124,"ABIERTA")) -> ... | R69: =if(P69=0,"",T69/$Y$18) | S69: =if(Q69=0,"...",if(P69=0,"...",sumifs($K$2:$K$124,$B$2:$B$124,P69,$D$2:$D$124,"ABIERTA")/Q69)) -> ... | T69: =if(P69=0,"...",sumifs($L$2:$L$124,$B$2:$B$124,P69,$D$2:$D$124,"ABIERTA")) -> ... | U69: =if(Q69=0,"...",if(P69=0,"...",V69/(T69-V69))) -> ... | V69: =if(Q69=0,"...",if(P69=0,"...",sumifs($N$2:$N$124,$B$2:$B$124,P69,$D$2:$D$124,"ABIERTA"))) -> ...
A70: Binance | B70: RNDR | C70: 45362 | D70: CERRADA | F70: =if(B70=0,"...", IF(E70=0,today()-C70,E70-C70)) -> 755 | G70: 8.1 | H70: 12.342 | I70: =IF(B70=0,"...",IF(D70="CERRADA","-",VLOOKUP(B70,$AC$2:$AD$27,2,FALSE))) -> - | J70: 10.092 | K70: =if(B70=0,"...",G70*H70) -> 99.9702 | L70: =IF(B70=0,"...",G70*J70) -> 81.7452 | M70: =if(B70=0,"...",L70/K70-1) -> -0.18230433 | N70: =if(B70=0,"...",L70-K70) -> -18.225 | Q70: =if(P70=0,"...",sumifs($G$2:$G$124,$B$2:$B$124,P70,$D$2:$D$124,"ABIERTA")) -> ... | R70: =if(P70=0,"",T70/$Y$18) | S70: =if(Q70=0,"...",if(P70=0,"...",sumifs($K$2:$K$124,$B$2:$B$124,P70,$D$2:$D$124,"ABIERTA")/Q70)) -> ... | T70: =if(P70=0,"...",sumifs($L$2:$L$124,$B$2:$B$124,P70,$D$2:$D$124,"ABIERTA")) -> ... | U70: =if(Q70=0,"...",if(P70=0,"...",V70/(T70-V70))) -> ... | V70: =if(Q70=0,"...",if(P70=0,"...",sumifs($N$2:$N$124,$B$2:$B$124,P70,$D$2:$D$124,"ABIERTA"))) -> ...
A71: Binance | B71: SAND | C71: 45362 | D71: CERRADA | F71: =if(B71=0,"...", IF(E71=0,today()-C71,E71-C71)) -> 755 | G71: 128 | H71: 0.7795 | I71: =IF(B71=0,"...",IF(D71="CERRADA","-",VLOOKUP(B71,$AC$2:$AD$27,2,FALSE))) -> - | J71: 0.3532 | K71: =if(B71=0,"...",G71*H71) -> 99.776 | L71: =IF(B71=0,"...",G71*J71) -> 45.2096 | M71: =if(B71=0,"...",L71/K71-1) -> -0.54688903 | N71: =if(B71=0,"...",L71-K71) -> -54.5664 | Q71: =if(P71=0,"...",sumifs($G$2:$G$124,$B$2:$B$124,P71,$D$2:$D$124,"ABIERTA")) -> ... | R71: =if(P71=0,"",T71/$Y$18) | S71: =if(Q71=0,"...",if(P71=0,"...",sumifs($K$2:$K$124,$B$2:$B$124,P71,$D$2:$D$124,"ABIERTA")/Q71)) -> ... | T71: =if(P71=0,"...",sumifs($L$2:$L$124,$B$2:$B$124,P71,$D$2:$D$124,"ABIERTA")) -> ... | U71: =if(Q71=0,"...",if(P71=0,"...",V71/(T71-V71))) -> ... | V71: =if(Q71=0,"...",if(P71=0,"...",sumifs($N$2:$N$124,$B$2:$B$124,P71,$D$2:$D$124,"ABIERTA"))) -> ...
A72: Binance | B72: AAVE | C72: 45362 | D72: CERRADA | E72: 45547 | F72: =if(B72=0,"...", IF(E72=0,today()-C72,E72-C72)) -> 185 | G72: 0.733 | H72: 136.37 | I72: =IF(B72=0,"...",IF(D72="CERRADA","-",VLOOKUP(B72,$AC$2:$AD$27,2,FALSE))) -> - | J72: 145.38 | K72: =if(B72=0,"...",G72*H72) -> 99.95921 | L72: =IF(B72=0,"...",G72*J72) -> 106.56354 | M72: =if(B72=0,"...",L72/K72-1) -> 0.06607025 | N72: =if(B72=0,"...",L72-K72) -> 6.60433 | Q72: =if(P72=0,"...",sumifs($G$2:$G$124,$B$2:$B$124,P72,$D$2:$D$124,"ABIERTA")) -> ... | R72: =if(P72=0,"",T72/$Y$18) | S72: =if(Q72=0,"...",if(P72=0,"...",sumifs($K$2:$K$124,$B$2:$B$124,P72,$D$2:$D$124,"ABIERTA")/Q72)) -> ... | T72: =if(P72=0,"...",sumifs($L$2:$L$124,$B$2:$B$124,P72,$D$2:$D$124,"ABIERTA")) -> ... | U72: =if(Q72=0,"...",if(P72=0,"...",V72/(T72-V72))) -> ... | V72: =if(Q72=0,"...",if(P72=0,"...",sumifs($N$2:$N$124,$B$2:$B$124,P72,$D$2:$D$124,"ABIERTA"))) -> ...
A73: Binance | B73: BTC | C73: 45362 | D73: CERRADA | F73: =if(B73=0,"...", IF(E73=0,today()-C73,E73-C73)) -> 755 | G73: 0.0034 | H73: 72294.42 | I73: =IF(B73=0,"...",IF(D73="CERRADA","-",VLOOKUP(B73,$AC$2:$AD$27,2,FALSE))) -> - | J73: =IF(B73=0,"...",IF(D73="CERRADA","Valor Venta",I73*(1-VLOOKUP(A73,Config!$B$3:$C$22,2,FALSE)))) -> Valor Venta | K73: =if(B73=0,"...",G73*H73) -> 245.80103 | L73: =IF(B73=0,"...",G73*J73) -> #VALUE! | M73: =if(B73=0,"...",L73/K73-1) -> #VALUE! | N73: =if(B73=0,"...",L73-K73) -> #VALUE! | Q73: =if(P73=0,"...",sumifs($G$2:$G$124,$B$2:$B$124,P73,$D$2:$D$124,"ABIERTA")) -> ... | R73: =if(P73=0,"",T73/$Y$18) | S73: =if(Q73=0,"...",if(P73=0,"...",sumifs($K$2:$K$124,$B$2:$B$124,P73,$D$2:$D$124,"ABIERTA")/Q73)) -> ... | T73: =if(P73=0,"...",sumifs($L$2:$L$124,$B$2:$B$124,P73,$D$2:$D$124,"ABIERTA")) -> ... | U73: =if(Q73=0,"...",if(P73=0,"...",V73/(T73-V73))) -> ... | V73: =if(Q73=0,"...",if(P73=0,"...",sumifs($N$2:$N$124,$B$2:$B$124,P73,$D$2:$D$124,"ABIERTA"))) -> ...
A74: Binance | B74: TRX | C74: 45364 | D74: CERRADA | E74: 45547 | F74: =if(B74=0,"...", IF(E74=0,today()-C74,E74-C74)) -> 183 | G74: 758 | H74: 0.13191 | I74: =IF(B74=0,"...",IF(D74="CERRADA","-",VLOOKUP(B74,$AC$2:$AD$27,2,FALSE))) -> - | J74: 0.152 | K74: =if(B74=0,"...",G74*H74) -> 99.98778 | L74: =IF(B74=0,"...",G74*J74) -> 115.216 | M74: =if(B74=0,"...",L74/K74-1) -> 0.15230081 | N74: =if(B74=0,"...",L74-K74) -> 15.22822 | Q74: =if(P74=0,"...",sumifs($G$2:$G$124,$B$2:$B$124,P74,$D$2:$D$124,"ABIERTA")) -> ... | R74: =if(P74=0,"",T74/$Y$18) | S74: =if(Q74=0,"...",if(P74=0,"...",sumifs($K$2:$K$124,$B$2:$B$124,P74,$D$2:$D$124,"ABIERTA")/Q74)) -> ... | T74: =if(P74=0,"...",sumifs($L$2:$L$124,$B$2:$B$124,P74,$D$2:$D$124,"ABIERTA")) -> ... | U74: =if(Q74=0,"...",if(P74=0,"...",V74/(T74-V74))) -> ... | V74: =if(Q74=0,"...",if(P74=0,"...",sumifs($N$2:$N$124,$B$2:$B$124,P74,$D$2:$D$124,"ABIERTA"))) -> ...
A75: Binance | B75: UNI | C75: 45364 | D75: CERRADA | F75: =if(B75=0,"...", IF(E75=0,today()-C75,E75-C75)) -> 753 | G75: 7.05 | H75: 14.172 | I75: =IF(B75=0,"...",IF(D75="CERRADA","-",VLOOKUP(B75,$AC$2:$AD$27,2,FALSE))) -> - | J75: =IF(B75=0,"...",IF(D75="CERRADA","Valor Venta",I75*(1-VLOOKUP(A75,Config!$B$3:$C$22,2,FALSE)))) -> Valor Venta | K75: =if(B75=0,"...",G75*H75) -> 99.9126 | L75: =IF(B75=0,"...",G75*J75) -> #VALUE! | M75: =if(B75=0,"...",L75/K75-1) -> #VALUE! | N75: =if(B75=0,"...",L75-K75) -> #VALUE! | Q75: =if(P75=0,"...",sumifs($G$2:$G$124,$B$2:$B$124,P75,$D$2:$D$124,"ABIERTA")) -> ... | R75: =if(P75=0,"",T75/$Y$18) | S75: =if(Q75=0,"...",if(P75=0,"...",sumifs($K$2:$K$124,$B$2:$B$124,P75,$D$2:$D$124,"ABIERTA")/Q75)) -> ... | T75: =if(P75=0,"...",sumifs($L$2:$L$124,$B$2:$B$124,P75,$D$2:$D$124,"ABIERTA")) -> ... | U75: =if(Q75=0,"...",if(P75=0,"...",V75/(T75-V75))) -> ... | V75: =if(Q75=0,"...",if(P75=0,"...",sumifs($N$2:$N$124,$B$2:$B$124,P75,$D$2:$D$124,"ABIERTA"))) -> ...
A76: Binance | B76: BTC | C76: 45365 | D76: ABIERTA | F76: =if(B76=0,"...", IF(E76=0,today()-C76,E76-C76)) -> 752 | G76: 0.00137 | H76: 72733.39 | I76: =IF(B76=0,"...",IF(D76="CERRADA","-",VLOOKUP(B76,$AC$2:$AD$27,2,FALSE))) -> 66948.35 | J76: =IF(B76=0,"...",IF(D76="CERRADA","Valor Venta",I76*(1-VLOOKUP(A76,Config!$B$3:$C$22,2,FALSE)))) -> 66462.305 | K76: =if(B76=0,"...",G76*H76) -> 99.644744 | L76: =IF(B76=0,"...",G76*J76) -> 91.053358 | M76: =if(B76=0,"...",L76/K76-1) -> -0.086220167 | N76: =if(B76=0,"...",L76-K76) -> -8.5913865 | Q76: =if(P76=0,"...",sumifs($G$2:$G$124,$B$2:$B$124,P76,$D$2:$D$124,"ABIERTA")) -> ... | R76: =if(P76=0,"",T76/$Y$18) | S76: =if(Q76=0,"...",if(P76=0,"...",sumifs($K$2:$K$124,$B$2:$B$124,P76,$D$2:$D$124,"ABIERTA")/Q76)) -> ... | T76: =if(P76=0,"...",sumifs($L$2:$L$124,$B$2:$B$124,P76,$D$2:$D$124,"ABIERTA")) -> ... | U76: =if(Q76=0,"...",if(P76=0,"...",V76/(T76-V76))) -> ... | V76: =if(Q76=0,"...",if(P76=0,"...",sumifs($N$2:$N$124,$B$2:$B$124,P76,$D$2:$D$124,"ABIERTA"))) -> ...
A77: Binance | B77: BTC | C77: 45365 | D77: ABIERTA | F77: =if(B77=0,"...", IF(E77=0,today()-C77,E77-C77)) -> 752 | G77: 0.00139 | H77: 71761.1 | I77: =IF(B77=0,"...",IF(D77="CERRADA","-",VLOOKUP(B77,$AC$2:$AD$27,2,FALSE))) -> 66948.35 | J77: =IF(B77=0,"...",IF(D77="CERRADA","Valor Venta",I77*(1-VLOOKUP(A77,Config!$B$3:$C$22,2,FALSE)))) -> 66462.305 | K77: =if(B77=0,"...",G77*H77) -> 99.747929 | L77: =IF(B77=0,"...",G77*J77) -> 92.382604 | M77: =if(B77=0,"...",L77/K77-1) -> -0.073839378 | N77: =if(B77=0,"...",L77-K77) -> -7.3653251 | Q77: =if(P77=0,"...",sumifs($G$2:$G$124,$B$2:$B$124,P77,$D$2:$D$124,"ABIERTA")) -> ... | R77: =if(P77=0,"",T77/$Y$18) | S77: =if(Q77=0,"...",if(P77=0,"...",sumifs($K$2:$K$124,$B$2:$B$124,P77,$D$2:$D$124,"ABIERTA")/Q77)) -> ... | T77: =if(P77=0,"...",sumifs($L$2:$L$124,$B$2:$B$124,P77,$D$2:$D$124,"ABIERTA")) -> ... | U77: =if(Q77=0,"...",if(P77=0,"...",V77/(T77-V77))) -> ... | V77: =if(Q77=0,"...",if(P77=0,"...",sumifs($N$2:$N$124,$B$2:$B$124,P77,$D$2:$D$124,"ABIERTA"))) -> ...
A78: Binance | B78: DOGE | C78: 45365 | D78: CERRADA | F78: =if(B78=0,"...", IF(E78=0,today()-C78,E78-C78)) -> 752 | G78: 552 | H78: 0.18106 | I78: =IF(B78=0,"...",IF(D78="CERRADA","-",VLOOKUP(B78,$AC$2:$AD$27,2,FALSE))) -> - | J78: 0.11956 | K78: =if(B78=0,"...",G78*H78) -> 99.94512 | L78: =IF(B78=0,"...",G78*J78) -> 65.99712 | M78: =if(B78=0,"...",L78/K78-1) -> -0.33966641 | N78: =if(B78=0,"...",L78-K78) -> -33.948 | Q78: =if(P78=0,"...",sumifs($G$2:$G$124,$B$2:$B$124,P78,$D$2:$D$124,"ABIERTA")) -> ... | R78: =if(P78=0,"",T78/$Y$18) | S78: =if(Q78=0,"...",if(P78=0,"...",sumifs($K$2:$K$124,$B$2:$B$124,P78,$D$2:$D$124,"ABIERTA")/Q78)) -> ... | T78: =if(P78=0,"...",sumifs($L$2:$L$124,$B$2:$B$124,P78,$D$2:$D$124,"ABIERTA")) -> ... | U78: =if(Q78=0,"...",if(P78=0,"...",V78/(T78-V78))) -> ... | V78: =if(Q78=0,"...",if(P78=0,"...",sumifs($N$2:$N$124,$B$2:$B$124,P78,$D$2:$D$124,"ABIERTA"))) -> ...
A79: Binance | B79: BTC | C79: 45365 | D79: ABIERTA | F79: =if(B79=0,"...", IF(E79=0,today()-C79,E79-C79)) -> 752 | G79: 0.00141 | H79: 70651.22 | I79: =IF(B79=0,"...",IF(D79="CERRADA","-",VLOOKUP(B79,$AC$2:$AD$27,2,FALSE))) -> 66948.35 | J79: =IF(B79=0,"...",IF(D79="CERRADA","Valor Venta",I79*(1-VLOOKUP(A79,Config!$B$3:$C$22,2,FALSE)))) -> 66462.305 | K79: =if(B79=0,"...",G79*H79) -> 99.61822 | L79: =IF(B79=0,"...",G79*J79) -> 93.71185 | M79: =if(B79=0,"...",L79/K79-1) -> -0.059290059 | N79: =if(B79=0,"...",L79-K79) -> -5.9063702 | Q79: =if(P79=0,"...",sumifs($G$2:$G$124,$B$2:$B$124,P79,$D$2:$D$124,"ABIERTA")) -> ... | R79: =if(P79=0,"",T79/$Y$18) | S79: =if(Q79=0,"...",if(P79=0,"...",sumifs($K$2:$K$124,$B$2:$B$124,P79,$D$2:$D$124,"ABIERTA")/Q79)) -> ... | T79: =if(P79=0,"...",sumifs($L$2:$L$124,$B$2:$B$124,P79,$D$2:$D$124,"ABIERTA")) -> ... | U79: =if(Q79=0,"...",if(P79=0,"...",V79/(T79-V79))) -> ... | V79: =if(Q79=0,"...",if(P79=0,"...",sumifs($N$2:$N$124,$B$2:$B$124,P79,$D$2:$D$124,"ABIERTA"))) -> ...
A80: Binance | B80: BTC | C80: 45366 | D80: ABIERTA | F80: =if(B80=0,"...", IF(E80=0,today()-C80,E80-C80)) -> 751 | G80: 0.00221 | H80: 67870.02 | I80: =IF(B80=0,"...",IF(D80="CERRADA","-",VLOOKUP(B80,$AC$2:$AD$27,2,FALSE))) -> 66948.35 | J80: =IF(B80=0,"...",IF(D80="CERRADA","Valor Venta",I80*(1-VLOOKUP(A80,Config!$B$3:$C$22,2,FALSE)))) -> 66462.305 | K80: =if(B80=0,"...",G80*H80) -> 149.99274 | L80: =IF(B80=0,"...",G80*J80) -> 146.88169 | M80: =if(B80=0,"...",L80/K80-1) -> -0.020741338 | N80: =if(B80=0,"...",L80-K80) -> -3.1110502 | Q80: =if(P80=0,"...",sumifs($G$2:$G$124,$B$2:$B$124,P80,$D$2:$D$124,"ABIERTA")) -> ... | R80: =if(P80=0,"",T80/$Y$18) | S80: =if(Q80=0,"...",if(P80=0,"...",sumifs($K$2:$K$124,$B$2:$B$124,P80,$D$2:$D$124,"ABIERTA")/Q80)) -> ... | T80: =if(P80=0,"...",sumifs($L$2:$L$124,$B$2:$B$124,P80,$D$2:$D$124,"ABIERTA")) -> ... | U80: =if(Q80=0,"...",if(P80=0,"...",V80/(T80-V80))) -> ... | V80: =if(Q80=0,"...",if(P80=0,"...",sumifs($N$2:$N$124,$B$2:$B$124,P80,$D$2:$D$124,"ABIERTA"))) -> ...
A81: Binance | B81: BTC | C81: 45367 | D81: ABIERTA | F81: =if(B81=0,"...", IF(E81=0,today()-C81,E81-C81)) -> 750 | G81: 0.00152 | H81: 65666.01 | I81: =IF(B81=0,"...",IF(D81="CERRADA","-",VLOOKUP(B81,$AC$2:$AD$27,2,FALSE))) -> 66948.35 | J81: =IF(B81=0,"...",IF(D81="CERRADA","Valor Venta",I81*(1-VLOOKUP(A81,Config!$B$3:$C$22,2,FALSE)))) -> 66462.305 | K81: =if(B81=0,"...",G81*H81) -> 99.812335 | L81: =IF(B81=0,"...",G81*J81) -> 101.0227 | M81: =if(B81=0,"...",L81/K81-1) -> 0.012126441 | N81: =if(B81=0,"...",L81-K81) -> 1.2103684 | Q81: =if(P81=0,"...",sumifs($G$2:$G$124,$B$2:$B$124,P81,$D$2:$D$124,"ABIERTA")) -> ... | R81: =if(P81=0,"",T81/$Y$18) | S81: =if(Q81=0,"...",if(P81=0,"...",sumifs($K$2:$K$124,$B$2:$B$124,P81,$D$2:$D$124,"ABIERTA")/Q81)) -> ... | T81: =if(P81=0,"...",sumifs($L$2:$L$124,$B$2:$B$124,P81,$D$2:$D$124,"ABIERTA")) -> ... | U81: =if(Q81=0,"...",if(P81=0,"...",V81/(T81-V81))) -> ... | V81: =if(Q81=0,"...",if(P81=0,"...",sumifs($N$2:$N$124,$B$2:$B$124,P81,$D$2:$D$124,"ABIERTA"))) -> ...
A82: Binance | B82: SOL | C82: 45370 | D82: ABIERTA | F82: =if(B82=0,"...", IF(E82=0,today()-C82,E82-C82)) -> 747 | G82: 0.54 | H82: 182.16 | I82: =IF(B82=0,"...",IF(D82="CERRADA","-",VLOOKUP(B82,$AC$2:$AD$27,2,FALSE))) -> 79.8061 | J82: =IF(B82=0,"...",IF(D82="CERRADA","Valor Venta",I82*(1-VLOOKUP(A82,Config!$B$3:$C$22,2,FALSE)))) -> 79.226708 | K82: =if(B82=0,"...",G82*H82) -> 98.3664 | L82: =IF(B82=0,"...",G82*J82) -> 42.782422 | M82: =if(B82=0,"...",L82/K82-1) -> -0.56507077 | N82: =if(B82=0,"...",L82-K82) -> -55.583978 | Q82: =if(P82=0,"...",sumifs($G$2:$G$124,$B$2:$B$124,P82,$D$2:$D$124,"ABIERTA")) -> ... | R82: =if(P82=0,"",T82/$Y$18) | S82: =if(Q82=0,"...",if(P82=0,"...",sumifs($K$2:$K$124,$B$2:$B$124,P82,$D$2:$D$124,"ABIERTA")/Q82)) -> ... | T82: =if(P82=0,"...",sumifs($L$2:$L$124,$B$2:$B$124,P82,$D$2:$D$124,"ABIERTA")) -> ... | U82: =if(Q82=0,"...",if(P82=0,"...",V82/(T82-V82))) -> ... | V82: =if(Q82=0,"...",if(P82=0,"...",sumifs($N$2:$N$124,$B$2:$B$124,P82,$D$2:$D$124,"ABIERTA"))) -> ...
A83: Binance | B83: SOL | C83: 45370 | D83: ABIERTA | F83: =if(B83=0,"...", IF(E83=0,today()-C83,E83-C83)) -> 747 | G83: 1.84 | H83: 175.2 | I83: =IF(B83=0,"...",IF(D83="CERRADA","-",VLOOKUP(B83,$AC$2:$AD$27,2,FALSE))) -> 79.8061 | J83: =IF(B83=0,"...",IF(D83="CERRADA","Valor Venta",I83*(1-VLOOKUP(A83,Config!$B$3:$C$22,2,FALSE)))) -> 79.226708 | K83: =if(B83=0,"...",G83*H83) -> 322.368 | L83: =IF(B83=0,"...",G83*J83) -> 145.77714 | M83: =if(B83=0,"...",L83/K83-1) -> -0.54779276 | N83: =if(B83=0,"...",L83-K83) -> -176.59086 | Q83: =if(P83=0,"...",sumifs($G$2:$G$124,$B$2:$B$124,P83,$D$2:$D$124,"ABIERTA")) -> ... | R83: =if(P83=0,"",T83/$Y$18) | S83: =if(Q83=0,"...",if(P83=0,"...",sumifs($K$2:$K$124,$B$2:$B$124,P83,$D$2:$D$124,"ABIERTA")/Q83)) -> ... | T83: =if(P83=0,"...",sumifs($L$2:$L$124,$B$2:$B$124,P83,$D$2:$D$124,"ABIERTA")) -> ... | U83: =if(Q83=0,"...",if(P83=0,"...",V83/(T83-V83))) -> ... | V83: =if(Q83=0,"...",if(P83=0,"...",sumifs($N$2:$N$124,$B$2:$B$124,P83,$D$2:$D$124,"ABIERTA"))) -> ...
A84: Binance | B84: UNI | C84: 45370 | D84: CERRADA | F84: =if(B84=0,"...", IF(E84=0,today()-C84,E84-C84)) -> 747 | G84: 18.26 | H84: 10.952 | I84: =IF(B84=0,"...",IF(D84="CERRADA","-",VLOOKUP(B84,$AC$2:$AD$27,2,FALSE))) -> - | J84: =IF(B84=0,"...",IF(D84="CERRADA","Valor Venta",I84*(1-VLOOKUP(A84,Config!$B$3:$C$22,2,FALSE)))) -> Valor Venta | K84: =if(B84=0,"...",G84*H84) -> 199.98352 | L84: =IF(B84=0,"...",G84*J84) -> #VALUE! | M84: =if(B84=0,"...",L84/K84-1) -> #VALUE! | N84: =if(B84=0,"...",L84-K84) -> #VALUE! | Q84: =if(P84=0,"...",sumifs($G$2:$G$124,$B$2:$B$124,P84,$D$2:$D$124,"ABIERTA")) -> ... | R84: =if(P84=0,"",T84/$Y$18) | S84: =if(Q84=0,"...",if(P84=0,"...",sumifs($K$2:$K$124,$B$2:$B$124,P84,$D$2:$D$124,"ABIERTA")/Q84)) -> ... | T84: =if(P84=0,"...",sumifs($L$2:$L$124,$B$2:$B$124,P84,$D$2:$D$124,"ABIERTA")) -> ... | U84: =if(Q84=0,"...",if(P84=0,"...",V84/(T84-V84))) -> ... | V84: =if(Q84=0,"...",if(P84=0,"...",sumifs($N$2:$N$124,$B$2:$B$124,P84,$D$2:$D$124,"ABIERTA"))) -> ...
A85: Binance | B85: MATIC | C85: 45370 | D85: CERRADA | F85: =if(B85=0,"...", IF(E85=0,today()-C85,E85-C85)) -> 747 | G85: 209.9 | H85: 0.9525 | I85: =IF(B85=0,"...",IF(D85="CERRADA","-",VLOOKUP(B85,$AC$2:$AD$27,2,FALSE))) -> - | J85: 0.4442 | K85: =if(B85=0,"...",G85*H85) -> 199.92975 | L85: =IF(B85=0,"...",G85*J85) -> 93.23758 | M85: =if(B85=0,"...",L85/K85-1) -> -0.53364829 | N85: =if(B85=0,"...",L85-K85) -> -106.69217 | Q85: =if(P85=0,"...",sumifs($G$2:$G$124,$B$2:$B$124,P85,$D$2:$D$124,"ABIERTA")) -> ... | R85: =if(P85=0,"",T85/$Y$18) | S85: =if(Q85=0,"...",if(P85=0,"...",sumifs($K$2:$K$124,$B$2:$B$124,P85,$D$2:$D$124,"ABIERTA")/Q85)) -> ... | T85: =if(P85=0,"...",sumifs($L$2:$L$124,$B$2:$B$124,P85,$D$2:$D$124,"ABIERTA")) -> ... | U85: =if(Q85=0,"...",if(P85=0,"...",V85/(T85-V85))) -> ... | V85: =if(Q85=0,"...",if(P85=0,"...",sumifs($N$2:$N$124,$B$2:$B$124,P85,$D$2:$D$124,"ABIERTA"))) -> ...
A86: Binance | B86: FET | C86: 45378 | D86: CERRADA | F86: =if(B86=0,"...", IF(E86=0,today()-C86,E86-C86)) -> 739 | G86: 73 | H86: 3.071 | I86: =IF(B86=0,"...",IF(D86="CERRADA","-",VLOOKUP(B86,$AC$2:$AD$27,2,FALSE))) -> - | J86: 1.328 | K86: =if(B86=0,"...",G86*H86) -> 224.183 | L86: =IF(B86=0,"...",G86*J86) -> 96.944 | M86: =if(B86=0,"...",L86/K86-1) -> -0.56756757 | N86: =if(B86=0,"...",L86-K86) -> -127.239 | Q86: =if(P86=0,"...",sumifs($G$2:$G$124,$B$2:$B$124,P86,$D$2:$D$124,"ABIERTA")) -> ... | R86: =if(P86=0,"",T86/$Y$18) | S86: =if(Q86=0,"...",if(P86=0,"...",sumifs($K$2:$K$124,$B$2:$B$124,P86,$D$2:$D$124,"ABIERTA")/Q86)) -> ... | T86: =if(P86=0,"...",sumifs($L$2:$L$124,$B$2:$B$124,P86,$D$2:$D$124,"ABIERTA")) -> ... | U86: =if(Q86=0,"...",if(P86=0,"...",V86/(T86-V86))) -> ... | V86: =if(Q86=0,"...",if(P86=0,"...",sumifs($N$2:$N$124,$B$2:$B$124,P86,$D$2:$D$124,"ABIERTA"))) -> ...
A87: Binance | B87: BTC | C87: 45384 | D87: ABIERTA | F87: =if(B87=0,"...", IF(E87=0,today()-C87,E87-C87)) -> 733 | G87: 0.00368 | H87: 67737.87 | I87: =IF(B87=0,"...",IF(D87="CERRADA","-",VLOOKUP(B87,$AC$2:$AD$27,2,FALSE))) -> 66948.35 | J87: =IF(B87=0,"...",IF(D87="CERRADA","Valor Venta",I87*(1-VLOOKUP(A87,Config!$B$3:$C$22,2,FALSE)))) -> 66462.305 | K87: =if(B87=0,"...",G87*H87) -> 249.27536 | L87: =IF(B87=0,"...",G87*J87) -> 244.58128 | M87: =if(B87=0,"...",L87/K87-1) -> -0.018830899 | N87: =if(B87=0,"...",L87-K87) -> -4.6940793 | Q87: =if(P87=0,"...",sumifs($G$2:$G$124,$B$2:$B$124,P87,$D$2:$D$124,"ABIERTA")) -> ... | R87: =if(P87=0,"",T87/$Y$18) | S87: =if(Q87=0,"...",if(P87=0,"...",sumifs($K$2:$K$124,$B$2:$B$124,P87,$D$2:$D$124,"ABIERTA")/Q87)) -> ... | T87: =if(P87=0,"...",sumifs($L$2:$L$124,$B$2:$B$124,P87,$D$2:$D$124,"ABIERTA")) -> ... | U87: =if(Q87=0,"...",if(P87=0,"...",V87/(T87-V87))) -> ... | V87: =if(Q87=0,"...",if(P87=0,"...",sumifs($N$2:$N$124,$B$2:$B$124,P87,$D$2:$D$124,"ABIERTA"))) -> ...
A88: Binance | B88: SOL | C88: 45387 | D88: ABIERTA | F88: =if(B88=0,"...", IF(E88=0,today()-C88,E88-C88)) -> 730 | G88: 1.42 | H88: 172.66 | I88: =IF(B88=0,"...",IF(D88="CERRADA","-",VLOOKUP(B88,$AC$2:$AD$27,2,FALSE))) -> 79.8061 | J88: =IF(B88=0,"...",IF(D88="CERRADA","Valor Venta",I88*(1-VLOOKUP(A88,Config!$B$3:$C$22,2,FALSE)))) -> 79.226708 | K88: =if(B88=0,"...",G88*H88) -> 245.1772 | L88: =IF(B88=0,"...",G88*J88) -> 112.50192 | M88: =if(B88=0,"...",L88/K88-1) -> -0.54114035 | N88: =if(B88=0,"...",L88-K88) -> -132.67527 | Q88: =if(P88=0,"...",sumifs($G$2:$G$124,$B$2:$B$124,P88,$D$2:$D$124,"ABIERTA")) -> ... | R88: =if(P88=0,"",T88/$Y$18) | S88: =if(Q88=0,"...",if(P88=0,"...",sumifs($K$2:$K$124,$B$2:$B$124,P88,$D$2:$D$124,"ABIERTA")/Q88)) -> ... | T88: =if(P88=0,"...",sumifs($L$2:$L$124,$B$2:$B$124,P88,$D$2:$D$124,"ABIERTA")) -> ... | U88: =if(Q88=0,"...",if(P88=0,"...",V88/(T88-V88))) -> ... | V88: =if(Q88=0,"...",if(P88=0,"...",sumifs($N$2:$N$124,$B$2:$B$124,P88,$D$2:$D$124,"ABIERTA"))) -> ...
A89: Binance | B89: BTC | C89: 45410 | D89: ABIERTA | F89: =if(B89=0,"...", IF(E89=0,today()-C89,E89-C89)) -> 707 | G89: 0.00159 | H89: 63299.84 | I89: =IF(B89=0,"...",IF(D89="CERRADA","-",VLOOKUP(B89,$AC$2:$AD$27,2,FALSE))) -> 66948.35 | J89: =IF(B89=0,"...",IF(D89="CERRADA","Valor Venta",I89*(1-VLOOKUP(A89,Config!$B$3:$C$22,2,FALSE)))) -> 66462.305 | K89: =if(B89=0,"...",G89*H89) -> 100.64675 | L89: =IF(B89=0,"...",G89*J89) -> 105.67506 | M89: =if(B89=0,"...",L89/K89-1) -> 0.049960079 | N89: =if(B89=0,"...",L89-K89) -> 5.0283193 | Q89: =if(P89=0,"...",sumifs($G$2:$G$124,$B$2:$B$124,P89,$D$2:$D$124,"ABIERTA")) -> ... | R89: =if(P89=0,"",T89/$Y$18) | S89: =if(Q89=0,"...",if(P89=0,"...",sumifs($K$2:$K$124,$B$2:$B$124,P89,$D$2:$D$124,"ABIERTA")/Q89)) -> ... | T89: =if(P89=0,"...",sumifs($L$2:$L$124,$B$2:$B$124,P89,$D$2:$D$124,"ABIERTA")) -> ... | U89: =if(Q89=0,"...",if(P89=0,"...",V89/(T89-V89))) -> ... | V89: =if(Q89=0,"...",if(P89=0,"...",sumifs($N$2:$N$124,$B$2:$B$124,P89,$D$2:$D$124,"ABIERTA"))) -> ...
A90: Binance | B90: SOL | C90: 45410 | D90: ABIERTA | F90: =if(B90=0,"...", IF(E90=0,today()-C90,E90-C90)) -> 707 | G90: 1.07 | H90: 140.18 | I90: =IF(B90=0,"...",IF(D90="CERRADA","-",VLOOKUP(B90,$AC$2:$AD$27,2,FALSE))) -> 79.8061 | J90: =IF(B90=0,"...",IF(D90="CERRADA","Valor Venta",I90*(1-VLOOKUP(A90,Config!$B$3:$C$22,2,FALSE)))) -> 79.226708 | K90: =if(B90=0,"...",G90*H90) -> 149.9926 | L90: =IF(B90=0,"...",G90*J90) -> 84.772577 | M90: =if(B90=0,"...",L90/K90-1) -> -0.4348216 | N90: =if(B90=0,"...",L90-K90) -> -65.220023 | Q90: =if(P90=0,"...",sumifs($G$2:$G$124,$B$2:$B$124,P90,$D$2:$D$124,"ABIERTA")) -> ... | R90: =if(P90=0,"",T90/$Y$18) | S90: =if(Q90=0,"...",if(P90=0,"...",sumifs($K$2:$K$124,$B$2:$B$124,P90,$D$2:$D$124,"ABIERTA")/Q90)) -> ... | T90: =if(P90=0,"...",sumifs($L$2:$L$124,$B$2:$B$124,P90,$D$2:$D$124,"ABIERTA")) -> ... | U90: =if(Q90=0,"...",if(P90=0,"...",V90/(T90-V90))) -> ... | V90: =if(Q90=0,"...",if(P90=0,"...",sumifs($N$2:$N$124,$B$2:$B$124,P90,$D$2:$D$124,"ABIERTA"))) -> ...
A91: Binance | B91: ETH | C91: 45410 | D91: CERRADA | F91: =if(B91=0,"...", IF(E91=0,today()-C91,E91-C91)) -> 707 | G91: 0.0461 | H91: 3251.34 | I91: =IF(B91=0,"...",IF(D91="CERRADA","-",VLOOKUP(B91,$AC$2:$AD$27,2,FALSE))) -> - | J91: 2744 | K91: =if(B91=0,"...",G91*H91) -> 149.88677 | L91: =IF(B91=0,"...",G91*J91) -> 126.4984 | M91: =if(B91=0,"...",L91/K91-1) -> -0.15604028 | N91: =if(B91=0,"...",L91-K91) -> -23.388374 | Q91: =if(P91=0,"...",sumifs($G$2:$G$124,$B$2:$B$124,P91,$D$2:$D$124,"ABIERTA")) -> ... | R91: =if(P91=0,"",T91/$Y$18) | S91: =if(Q91=0,"...",if(P91=0,"...",sumifs($K$2:$K$124,$B$2:$B$124,P91,$D$2:$D$124,"ABIERTA")/Q91)) -> ... | T91: =if(P91=0,"...",sumifs($L$2:$L$124,$B$2:$B$124,P91,$D$2:$D$124,"ABIERTA")) -> ... | U91: =if(Q91=0,"...",if(P91=0,"...",V91/(T91-V91))) -> ... | V91: =if(Q91=0,"...",if(P91=0,"...",sumifs($N$2:$N$124,$B$2:$B$124,P91,$D$2:$D$124,"ABIERTA"))) -> ...
A92: Binance | B92: SOL | C92: 45412 | D92: ABIERTA | F92: =if(B92=0,"...", IF(E92=0,today()-C92,E92-C92)) -> 705 | G92: 1.635 | H92: 124.57 | I92: =IF(B92=0,"...",IF(D92="CERRADA","-",VLOOKUP(B92,$AC$2:$AD$27,2,FALSE))) -> 79.8061 | J92: =IF(B92=0,"...",IF(D92="CERRADA","Valor Venta",I92*(1-VLOOKUP(A92,Config!$B$3:$C$22,2,FALSE)))) -> 79.226708 | K92: =if(B92=0,"...",G92*H92) -> 203.67195 | L92: =IF(B92=0,"...",G92*J92) -> 129.53567 | M92: =if(B92=0,"...",L92/K92-1) -> -0.36399849 | N92: =if(B92=0,"...",L92-K92) -> -74.136283 | Q92: =if(P92=0,"...",sumifs($G$2:$G$124,$B$2:$B$124,P92,$D$2:$D$124,"ABIERTA")) -> ... | R92: =if(P92=0,"",T92/$Y$18) | S92: =if(Q92=0,"...",if(P92=0,"...",sumifs($K$2:$K$124,$B$2:$B$124,P92,$D$2:$D$124,"ABIERTA")/Q92)) -> ... | T92: =if(P92=0,"...",sumifs($L$2:$L$124,$B$2:$B$124,P92,$D$2:$D$124,"ABIERTA")) -> ... | U92: =if(Q92=0,"...",if(P92=0,"...",V92/(T92-V92))) -> ... | V92: =if(Q92=0,"...",if(P92=0,"...",sumifs($N$2:$N$124,$B$2:$B$124,P92,$D$2:$D$124,"ABIERTA"))) -> ...
A93: Binance | B93: SOL | C93: 45436 | D93: ABIERTA | F93: =if(B93=0,"...", IF(E93=0,today()-C93,E93-C93)) -> 681 | G93: 0.998 | H93: 168 | I93: =IF(B93=0,"...",IF(D93="CERRADA","-",VLOOKUP(B93,$AC$2:$AD$27,2,FALSE))) -> 79.8061 | J93: =IF(B93=0,"...",IF(D93="CERRADA","Valor Venta",I93*(1-VLOOKUP(A93,Config!$B$3:$C$22,2,FALSE)))) -> 79.226708 | K93: =if(B93=0,"...",G93*H93) -> 167.664 | L93: =IF(B93=0,"...",G93*J93) -> 79.068254 | M93: =if(B93=0,"...",L93/K93-1) -> -0.52841245 | N93: =if(B93=0,"...",L93-K93) -> -88.595746 | Q93: =if(P93=0,"...",sumifs($G$2:$G$124,$B$2:$B$124,P93,$D$2:$D$124,"ABIERTA")) -> ... | R93: =if(P93=0,"",T93/$Y$18) | S93: =if(Q93=0,"...",if(P93=0,"...",sumifs($K$2:$K$124,$B$2:$B$124,P93,$D$2:$D$124,"ABIERTA")/Q93)) -> ... | T93: =if(P93=0,"...",sumifs($L$2:$L$124,$B$2:$B$124,P93,$D$2:$D$124,"ABIERTA")) -> ... | U93: =if(Q93=0,"...",if(P93=0,"...",V93/(T93-V93))) -> ... | V93: =if(Q93=0,"...",if(P93=0,"...",sumifs($N$2:$N$124,$B$2:$B$124,P93,$D$2:$D$124,"ABIERTA"))) -> ...
A94: Binance | B94: SOL | C94: 45477 | D94: CERRADA | F94: =if(B94=0,"...", IF(E94=0,today()-C94,E94-C94)) -> 640 | G94: 3.889 | H94: 126.73 | I94: =IF(B94=0,"...",IF(D94="CERRADA","-",VLOOKUP(B94,$AC$2:$AD$27,2,FALSE))) -> - | J94: 156 | K94: =if(B94=0,"...",G94*H94) -> 492.85297 | L94: =IF(B94=0,"...",G94*J94) -> 606.684 | M94: =if(B94=0,"...",L94/K94-1) -> 0.23096347 | N94: =if(B94=0,"...",L94-K94) -> 113.83103 | Q94: =if(P94=0,"...",sumifs($G$2:$G$124,$B$2:$B$124,P94,$D$2:$D$124,"ABIERTA")) -> ... | R94: =if(P94=0,"",T94/$Y$18) | S94: =if(Q94=0,"...",if(P94=0,"...",sumifs($K$2:$K$124,$B$2:$B$124,P94,$D$2:$D$124,"ABIERTA")/Q94)) -> ... | T94: =if(P94=0,"...",sumifs($L$2:$L$124,$B$2:$B$124,P94,$D$2:$D$124,"ABIERTA")) -> ... | U94: =if(Q94=0,"...",if(P94=0,"...",V94/(T94-V94))) -> ... | V94: =if(Q94=0,"...",if(P94=0,"...",sumifs($N$2:$N$124,$B$2:$B$124,P94,$D$2:$D$124,"ABIERTA"))) -> ...
A95: Binance | B95: SOL | C95: 45510 | D95: ABIERTA | F95: =if(B95=0,"...", IF(E95=0,today()-C95,E95-C95)) -> 607 | G95: 2.143 | H95: 139.96 | I95: =IF(B95=0,"...",IF(D95="CERRADA","-",VLOOKUP(B95,$AC$2:$AD$27,2,FALSE))) -> 79.8061 | J95: =IF(B95=0,"...",IF(D95="CERRADA","Valor Venta",I95*(1-VLOOKUP(A95,Config!$B$3:$C$22,2,FALSE)))) -> 79.226708 | K95: =if(B95=0,"...",G95*H95) -> 299.93428 | L95: =IF(B95=0,"...",G95*J95) -> 169.78283 | M95: =if(B95=0,"...",L95/K95-1) -> -0.43393321 | N95: =if(B95=0,"...",L95-K95) -> -130.15145 | Q95: =if(P95=0,"...",sumifs($G$2:$G$124,$B$2:$B$124,P95,$D$2:$D$124,"ABIERTA")) -> ... | R95: =if(P95=0,"",T95/$Y$18) | S95: =if(Q95=0,"...",if(P95=0,"...",sumifs($K$2:$K$124,$B$2:$B$124,P95,$D$2:$D$124,"ABIERTA")/Q95)) -> ... | T95: =if(P95=0,"...",sumifs($L$2:$L$124,$B$2:$B$124,P95,$D$2:$D$124,"ABIERTA")) -> ... | U95: =if(Q95=0,"...",if(P95=0,"...",V95/(T95-V95))) -> ... | V95: =if(Q95=0,"...",if(P95=0,"...",sumifs($N$2:$N$124,$B$2:$B$124,P95,$D$2:$D$124,"ABIERTA"))) -> ...
A96: Binance | B96: BNB | C96: 45510 | D96: CERRADA | F96: =if(B96=0,"...", IF(E96=0,today()-C96,E96-C96)) -> 607 | G96: 0.301 | H96: 479.7 | I96: =IF(B96=0,"...",IF(D96="CERRADA","-",VLOOKUP(B96,$AC$2:$AD$27,2,FALSE))) -> - | J96: 539.7 | K96: =if(B96=0,"...",G96*H96) -> 144.3897 | L96: =IF(B96=0,"...",G96*J96) -> 162.4497 | M96: =if(B96=0,"...",L96/K96-1) -> 0.12507817 | N96: =if(B96=0,"...",L96-K96) -> 18.06 | Q96: =if(P96=0,"...",sumifs($G$2:$G$124,$B$2:$B$124,P96,$D$2:$D$124,"ABIERTA")) -> ... | R96: =if(P96=0,"",T96/$Y$18) | S96: =if(Q96=0,"...",if(P96=0,"...",sumifs($K$2:$K$124,$B$2:$B$124,P96,$D$2:$D$124,"ABIERTA")/Q96)) -> ... | T96: =if(P96=0,"...",sumifs($L$2:$L$124,$B$2:$B$124,P96,$D$2:$D$124,"ABIERTA")) -> ... | U96: =if(Q96=0,"...",if(P96=0,"...",V96/(T96-V96))) -> ... | V96: =if(Q96=0,"...",if(P96=0,"...",sumifs($N$2:$N$124,$B$2:$B$124,P96,$D$2:$D$124,"ABIERTA"))) -> ...
A97: Binance | B97: BTC | C97: 45547 | D97: ABIERTA | F97: =if(B97=0,"...", IF(E97=0,today()-C97,E97-C97)) -> 570 | G97: 0.00382 | H97: 58054.25 | I97: =IF(B97=0,"...",IF(D97="CERRADA","-",VLOOKUP(B97,$AC$2:$AD$27,2,FALSE))) -> 66948.35 | J97: =IF(B97=0,"...",IF(D97="CERRADA","Valor Venta",I97*(1-VLOOKUP(A97,Config!$B$3:$C$22,2,FALSE)))) -> 66462.305 | K97: =if(B97=0,"...",G97*H97) -> 221.76723 | L97: =IF(B97=0,"...",G97*J97) -> 253.88601 | M97: =if(B97=0,"...",L97/K97-1) -> 0.144831 | N97: =if(B97=0,"...",L97-K97) -> 32.11877 | Q97: =if(P97=0,"...",sumifs($G$2:$G$124,$B$2:$B$124,P97,$D$2:$D$124,"ABIERTA")) -> ... | R97: =if(P97=0,"",T97/$Y$18) | S97: =if(Q97=0,"...",if(P97=0,"...",sumifs($K$2:$K$124,$B$2:$B$124,P97,$D$2:$D$124,"ABIERTA")/Q97)) -> ... | T97: =if(P97=0,"...",sumifs($L$2:$L$124,$B$2:$B$124,P97,$D$2:$D$124,"ABIERTA")) -> ... | U97: =if(Q97=0,"...",if(P97=0,"...",V97/(T97-V97))) -> ... | V97: =if(Q97=0,"...",if(P97=0,"...",sumifs($N$2:$N$124,$B$2:$B$124,P97,$D$2:$D$124,"ABIERTA"))) -> ...
A98: Binance | B98: ETH | C98: 45569 | D98: CERRADA | F98: =if(B98=0,"...", IF(E98=0,today()-C98,E98-C98)) -> 548 | G98: 0.0604 | H98: 2439.64 | I98: =IF(B98=0,"...",IF(D98="CERRADA","-",VLOOKUP(B98,$AC$2:$AD$27,2,FALSE))) -> - | J98: 2744 | K98: =if(B98=0,"...",G98*H98) -> 147.35426 | L98: =IF(B98=0,"...",G98*J98) -> 165.7376 | M98: =if(B98=0,"...",L98/K98-1) -> 0.12475611 | N98: =if(B98=0,"...",L98-K98) -> 18.383344 | Q98: =if(P98=0,"...",sumifs($G$2:$G$124,$B$2:$B$124,P98,$D$2:$D$124,"ABIERTA")) -> ... | R98: =if(P98=0,"",T98/$Y$18) | S98: =if(Q98=0,"...",if(P98=0,"...",sumifs($K$2:$K$124,$B$2:$B$124,P98,$D$2:$D$124,"ABIERTA")/Q98)) -> ... | T98: =if(P98=0,"...",sumifs($L$2:$L$124,$B$2:$B$124,P98,$D$2:$D$124,"ABIERTA")) -> ... | U98: =if(Q98=0,"...",if(P98=0,"...",V98/(T98-V98))) -> ... | V98: =if(Q98=0,"...",if(P98=0,"...",sumifs($N$2:$N$124,$B$2:$B$124,P98,$D$2:$D$124,"ABIERTA"))) -> ...
A99: Binance | B99: RAY | C99: 45593 | D99: CERRADA | F99: =if(B99=0,"...", IF(E99=0,today()-C99,E99-C99)) -> 524 | G99: 29.5 | H99: 3.375 | I99: =IF(B99=0,"...",IF(D99="CERRADA","-",VLOOKUP(B99,$AC$2:$AD$40,2,FALSE))) -> - | J99: 3.72 | K99: =if(B99=0,"...",G99*H99) -> 99.5625 | L99: =IF(B99=0,"...",G99*J99) -> 109.74 | M99: =if(B99=0,"...",L99/K99-1) -> 0.10222222 | N99: =if(B99=0,"...",L99-K99) -> 10.1775 | Q99: =if(P99=0,"...",sumifs($G$2:$G$124,$B$2:$B$124,P99,$D$2:$D$124,"ABIERTA")) -> ... | R99: =if(P99=0,"",T99/$Y$18) | S99: =if(Q99=0,"...",if(P99=0,"...",sumifs($K$2:$K$124,$B$2:$B$124,P99,$D$2:$D$124,"ABIERTA")/Q99)) -> ... | T99: =if(P99=0,"...",sumifs($L$2:$L$124,$B$2:$B$124,P99,$D$2:$D$124,"ABIERTA")) -> ... | U99: =if(Q99=0,"...",if(P99=0,"...",V99/(T99-V99))) -> ... | V99: =if(Q99=0,"...",if(P99=0,"...",sumifs($N$2:$N$124,$B$2:$B$124,P99,$D$2:$D$124,"ABIERTA"))) -> ...
A100: Binance | B100: ETH | C100: 45596 | D100: CERRADA | F100: =if(B100=0,"...", IF(E100=0,today()-C100,E100-C100)) -> 521 | G100: 0.0393 | H100: 2538.33 | I100: =IF(B100=0,"...",IF(D100="CERRADA","-",VLOOKUP(B100,$AC$2:$AD$27,2,FALSE))) -> - | J100: 2744 | K100: =if(B100=0,"...",G100*H100) -> 99.756369 | L100: =IF(B100=0,"...",G100*J100) -> 107.8392 | M100: =if(B100=0,"...",L100/K100-1) -> 0.081025714 | N100: =if(B100=0,"...",L100-K100) -> 8.082831 | Q100: =if(P100=0,"...",sumifs($G$2:$G$124,$B$2:$B$124,P100,$D$2:$D$124,"ABIERTA")) -> ... | R100: =if(P100=0,"",T100/$Y$18) | S100: =if(Q100=0,"...",if(P100=0,"...",sumifs($K$2:$K$124,$B$2:$B$124,P100,$D$2:$D$124,"ABIERTA")/Q100)) -> ... | T100: =if(P100=0,"...",sumifs($L$2:$L$124,$B$2:$B$124,P100,$D$2:$D$124,"ABIERTA")) -> ... | U100: =if(Q100=0,"...",if(P100=0,"...",V100/(T100-V100))) -> ... | V100: =if(Q100=0,"...",if(P100=0,"...",sumifs($N$2:$N$124,$B$2:$B$124,P100,$D$2:$D$124,"ABIERTA"))) -> ...
A101: Binance | B101: AAVE | C101: 45615 | D101: CERRADA | F101: =if(B101=0,"...", IF(E101=0,today()-C101,E101-C101)) -> 502 | G101: 0.597 | H101: 167.4553 | I101: =IF(B101=0,"...",IF(D101="CERRADA","-",VLOOKUP(B101,$AC$2:$AD$40,2,FALSE))) -> - | J101: 188.79 | K101: =if(B101=0,"...",G101*H101) -> 99.970814 | L101: =IF(B101=0,"...",G101*J101) -> 112.70763 | M101: =if(B101=0,"...",L101/K101-1) -> 0.12740534 | N101: =if(B101=0,"...",L101-K101) -> 12.736816 | Q101: =if(P101=0,"...",sumifs($G$2:$G$124,$B$2:$B$124,P101,$D$2:$D$124,"ABIERTA")) -> ... | R101: =if(P101=0,"",T101/$Y$18) | S101: =if(Q101=0,"...",if(P101=0,"...",sumifs($K$2:$K$124,$B$2:$B$124,P101,$D$2:$D$124,"ABIERTA")/Q101)) -> ... | T101: =if(P101=0,"...",sumifs($L$2:$L$124,$B$2:$B$124,P101,$D$2:$D$124,"ABIERTA")) -> ... | U101: =if(Q101=0,"...",if(P101=0,"...",V101/(T101-V101))) -> ... | V101: =if(Q101=0,"...",if(P101=0,"...",sumifs($N$2:$N$124,$B$2:$B$124,P101,$D$2:$D$124,"ABIERTA"))) -> ...
A102: Binance | B102: RAY | C102: 45615 | D102: ABIERTA | F102: =if(B102=0,"...", IF(E102=0,today()-C102,E102-C102)) -> 502 | G102: 8.6 | H102: 5.769 | I102: =IF(B102=0,"...",IF(D102="CERRADA","-",VLOOKUP(B102,$AC$2:$AD$40,2,FALSE))) -> 0.597927 | J102: =IF(B102=0,"...",IF(D102="CERRADA","Valor Venta",I102*(1-VLOOKUP(A102,Config!$B$3:$C$22,2,FALSE)))) -> 0.59358605 | K102: =if(B102=0,"...",G102*H102) -> 49.6134 | L102: =IF(B102=0,"...",G102*J102) -> 5.10484 | M102: =if(B102=0,"...",L102/K102-1) -> -0.89710764 | N102: =if(B102=0,"...",L102-K102) -> -44.50856 | Q102: =if(P102=0,"...",sumifs($G$2:$G$124,$B$2:$B$124,P102,$D$2:$D$124,"ABIERTA")) -> ... | R102: =if(P102=0,"",T102/$Y$18) | S102: =if(Q102=0,"...",if(P102=0,"...",sumifs($K$2:$K$124,$B$2:$B$124,P102,$D$2:$D$124,"ABIERTA")/Q102)) -> ... | T102: =if(P102=0,"...",sumifs($L$2:$L$124,$B$2:$B$124,P102,$D$2:$D$124,"ABIERTA")) -> ... | U102: =if(Q102=0,"...",if(P102=0,"...",V102/(T102-V102))) -> ... | V102: =if(Q102=0,"...",if(P102=0,"...",sumifs($N$2:$N$124,$B$2:$B$124,P102,$D$2:$D$124,"ABIERTA"))) -> ...
A103: Binance | B103: RONIN | C103: 45631 | D103: CERRADA | F103: =if(B103=0,"...", IF(E103=0,today()-C103,E103-C103)) -> 486 | G103: 2.323 | H103: 43.39 | I103: =IF(B103=0,"...",IF(D103="CERRADA","-",VLOOKUP(B103,$AC$2:$AD$27,2,FALSE))) -> - | J103: 43.34 | K103: =if(B103=0,"...",G103*H103) -> 100.79497 | L103: =IF(B103=0,"...",G103*J103) -> 100.67882 | M103: =if(B103=0,"...",L103/K103-1) -> -0.0011523392 | N103: =if(B103=0,"...",L103-K103) -> -0.11615 | Q103: =if(P103=0,"...",sumifs($G$2:$G$124,$B$2:$B$124,P103,$D$2:$D$124,"ABIERTA")) -> ... | R103: =if(P103=0,"",T103/$Y$18) | S103: =if(Q103=0,"...",if(P103=0,"...",sumifs($K$2:$K$124,$B$2:$B$124,P103,$D$2:$D$124,"ABIERTA")/Q103)) -> ... | T103: =if(P103=0,"...",sumifs($L$2:$L$124,$B$2:$B$124,P103,$D$2:$D$124,"ABIERTA")) -> ... | U103: =if(Q103=0,"...",if(P103=0,"...",V103/(T103-V103))) -> ... | V103: =if(Q103=0,"...",if(P103=0,"...",sumifs($N$2:$N$124,$B$2:$B$124,P103,$D$2:$D$124,"ABIERTA"))) -> ...
A104: Binance | B104: RNDR | C104: 45646 | D104: CERRADA | F104: =if(B104=0,"...", IF(E104=0,today()-C104,E104-C104)) -> 471 | G104: 6.88 | H104: 14.54 | I104: =IF(B104=0,"...",IF(D104="CERRADA","-",VLOOKUP(B104,$AC$2:$AD$27,2,FALSE))) -> - | J104: 14.52 | K104: =if(B104=0,"...",G104*H104) -> 100.0352 | L104: =IF(B104=0,"...",G104*J104) -> 99.8976 | M104: =if(B104=0,"...",L104/K104-1) -> -0.0013755158 | N104: =if(B104=0,"...",L104-K104) -> -0.1376 | Q104: =if(P104=0,"...",sumifs($G$2:$G$124,$B$2:$B$124,P104,$D$2:$D$124,"ABIERTA")) -> ... | R104: =if(P104=0,"",T104/$Y$18) | S104: =if(Q104=0,"...",if(P104=0,"...",sumifs($K$2:$K$124,$B$2:$B$124,P104,$D$2:$D$124,"ABIERTA")/Q104)) -> ... | T104: =if(P104=0,"...",sumifs($L$2:$L$124,$B$2:$B$124,P104,$D$2:$D$124,"ABIERTA")) -> ... | U104: =if(Q104=0,"...",if(P104=0,"...",V104/(T104-V104))) -> ... | V104: =if(Q104=0,"...",if(P104=0,"...",sumifs($N$2:$N$124,$B$2:$B$124,P104,$D$2:$D$124,"ABIERTA"))) -> ...
A105: Binance | B105: ONE | C105: 45646 | D105: CERRADA | F105: =if(B105=0,"...", IF(E105=0,today()-C105,E105-C105)) -> 471 | G105: 0.02 | H105: 4130.5 | I105: =IF(B105=0,"...",IF(D105="CERRADA","-",VLOOKUP(B105,$AC$2:$AD$27,2,FALSE))) -> - | J105: 4126.3 | K105: =if(B105=0,"...",G105*H105) -> 82.61 | L105: =IF(B105=0,"...",G105*J105) -> 82.526 | M105: =if(B105=0,"...",L105/K105-1) -> -0.001016826 | N105: =if(B105=0,"...",L105-K105) -> -0.084 | Q105: =if(P105=0,"...",sumifs($G$2:$G$124,$B$2:$B$124,P105,$D$2:$D$124,"ABIERTA")) -> ... | R105: =if(P105=0,"",T105/$Y$18) | S105: =if(Q105=0,"...",if(P105=0,"...",sumifs($K$2:$K$124,$B$2:$B$124,P105,$D$2:$D$124,"ABIERTA")/Q105)) -> ... | T105: =if(P105=0,"...",sumifs($L$2:$L$124,$B$2:$B$124,P105,$D$2:$D$124,"ABIERTA")) -> ... | U105: =if(Q105=0,"...",if(P105=0,"...",V105/(T105-V105))) -> ... | V105: =if(Q105=0,"...",if(P105=0,"...",sumifs($N$2:$N$124,$B$2:$B$124,P105,$D$2:$D$124,"ABIERTA"))) -> ...
A106: Balance | B106: TRUMP | C106: 45676 | D106: CERRADA | F106: =if(B106=0,"...", IF(E106=0,today()-C106,E106-C106)) -> 441 | G106: 0.67 | H106: 74.55 | I106: 51.8 | J106: =IF(B106=0,"...",IF(D106="CERRADA","Valor Venta",I106*(1-VLOOKUP(A106,Config!$B$3:$C$22,2,FALSE)))) -> Valor Venta | K106: =if(B106=0,"...",G106*H106) -> 49.9485 | L106: =IF(B106=0,"...",G106*J106) -> #VALUE! | M106: =if(B106=0,"...",L106/K106-1) -> #VALUE! | N106: =if(B106=0,"...",L106-K106) -> #VALUE! | Q106: =if(P106=0,"...",sumifs($G$2:$G$124,$B$2:$B$124,P106,$D$2:$D$124,"ABIERTA")) -> ... | R106: =if(P106=0,"",T106/$Y$18) | S106: =if(Q106=0,"...",if(P106=0,"...",sumifs($K$2:$K$124,$B$2:$B$124,P106,$D$2:$D$124,"ABIERTA")/Q106)) -> ... | T106: =if(P106=0,"...",sumifs($L$2:$L$124,$B$2:$B$124,P106,$D$2:$D$124,"ABIERTA")) -> ... | U106: =if(Q106=0,"...",if(P106=0,"...",V106/(T106-V106))) -> ... | V106: =if(Q106=0,"...",if(P106=0,"...",sumifs($N$2:$N$124,$B$2:$B$124,P106,$D$2:$D$124,"ABIERTA"))) -> ...
A107: BingX | B107: ONDO | C107: 45662 | D107: CERRADA | F107: =if(B107=0,"...", IF(E107=0,today()-C107,E107-C107)) -> 455 | G107: 75.10482 | H107: 1.3352 | I107: =IF(B107=0,"...",IF(D107="CERRADA","-",VLOOKUP(B107,$AC$2:$AD$27,2,FALSE))) -> - | J107: =IF(B107=0,"...",IF(D107="CERRADA","Valor Venta",I107*(1-VLOOKUP(A107,Config!$B$3:$C$22,2,FALSE)))) -> Valor Venta | K107: =if(B107=0,"...",G107*H107) -> 100.27996 | L107: =IF(B107=0,"...",G107*J107) -> #VALUE! | M107: =if(B107=0,"...",L107/K107-1) -> #VALUE! | N107: =if(B107=0,"...",L107-K107) -> #VALUE! | Q107: =if(P107=0,"...",sumifs($G$2:$G$124,$B$2:$B$124,P107,$D$2:$D$124,"ABIERTA")) -> ... | R107: =if(P107=0,"",T107/$Y$18) | S107: =if(Q107=0,"...",if(P107=0,"...",sumifs($K$2:$K$124,$B$2:$B$124,P107,$D$2:$D$124,"ABIERTA")/Q107)) -> ... | T107: =if(P107=0,"...",sumifs($L$2:$L$124,$B$2:$B$124,P107,$D$2:$D$124,"ABIERTA")) -> ... | U107: =if(Q107=0,"...",if(P107=0,"...",V107/(T107-V107))) -> ... | V107: =if(Q107=0,"...",if(P107=0,"...",sumifs($N$2:$N$124,$B$2:$B$124,P107,$D$2:$D$124,"ABIERTA"))) -> ...
A108: Binance | B108: XRP | C108: 45775 | D108: CERRADA | F108: =if(B108=0,"...", IF(E108=0,today()-C108,E108-C108)) -> 342 | G108: 43.9 | H108: 2.2816 | I108: =IF(B108=0,"...",IF(D108="CERRADA","-",VLOOKUP(B108,$AC$2:$AD$40,2,FALSE))) -> - | J108: =IF(B108=0,"...",IF(D108="CERRADA","Valor Venta",I108*(1-VLOOKUP(A108,Config!$B$3:$C$22,2,FALSE)))) -> Valor Venta | K108: =if(B108=0,"...",G108*H108) -> 100.16224 | L108: =IF(B108=0,"...",G108*J108) -> #VALUE! | M108: =if(B108=0,"...",L108/K108-1) -> #VALUE! | N108: =if(B108=0,"...",L108-K108) -> #VALUE! | Q108: =if(P108=0,"...",sumifs($G$2:$G$124,$B$2:$B$124,P108,$D$2:$D$124,"ABIERTA")) -> ... | R108: =if(P108=0,"",T108/$Y$18) | S108: =if(Q108=0,"...",if(P108=0,"...",sumifs($K$2:$K$124,$B$2:$B$124,P108,$D$2:$D$124,"ABIERTA")/Q108)) -> ... | T108: =if(P108=0,"...",sumifs($L$2:$L$124,$B$2:$B$124,P108,$D$2:$D$124,"ABIERTA")) -> ... | U108: =if(Q108=0,"...",if(P108=0,"...",V108/(T108-V108))) -> ... | V108: =if(Q108=0,"...",if(P108=0,"...",sumifs($N$2:$N$124,$B$2:$B$124,P108,$D$2:$D$124,"ABIERTA"))) -> ...
A109: Binance | B109: SUI | C109: 45791 | D109: ABIERTA | F109: =if(B109=0,"...", IF(E109=0,today()-C109,E109-C109)) -> 326 | G109: 27.6 | H109: 3.9621 | I109: =IF(B109=0,"...",IF(D109="CERRADA","-",VLOOKUP(B109,$AC$2:$AD$40,2,FALSE))) -> 0.850209 | J109: =IF(B109=0,"...",IF(D109="CERRADA","Valor Venta",I109*(1-VLOOKUP(A109,Config!$B$3:$C$22,2,FALSE)))) -> 0.84403648 | K109: =if(B109=0,"...",G109*H109) -> 109.35396 | L109: =IF(B109=0,"...",G109*J109) -> 23.295407 | M109: =if(B109=0,"...",L109/K109-1) -> -0.78697244 | N109: =if(B109=0,"...",L109-K109) -> -86.058553 | Q109: =if(P109=0,"...",sumifs($G$2:$G$124,$B$2:$B$124,P109,$D$2:$D$124,"ABIERTA")) -> ... | R109: =if(P109=0,"",T109/$Y$18) | S109: =if(Q109=0,"...",if(P109=0,"...",sumifs($K$2:$K$124,$B$2:$B$124,P109,$D$2:$D$124,"ABIERTA")/Q109)) -> ... | T109: =if(P109=0,"...",sumifs($L$2:$L$124,$B$2:$B$124,P109,$D$2:$D$124,"ABIERTA")) -> ... | U109: =if(Q109=0,"...",if(P109=0,"...",V109/(T109-V109))) -> ... | V109: =if(Q109=0,"...",if(P109=0,"...",sumifs($N$2:$N$124,$B$2:$B$124,P109,$D$2:$D$124,"ABIERTA"))) -> ...
...

Sheet Estrategia michel saylor
A1: Fecha | C1: Dólares agregados
A2: 45740 | C2: 31
A3: 45742 | C3: 22
A4: 45744 | C4: 80
A5: 45745 | C5: 20
A6: 45746 | C6: 20
A7: 45747 | C7: 15
A8: Cierre | C8: 324.9 | D8: =SUM(C2:C7) -> 188 | E8: =C8-D8 -> 136.9
A10: 45749 | C10: 60
A11: 45750 | C11: 30
A12: 45750 | C12: 50
A13: 45751 | C13: 30
A14: 45752 | C14: 20
A15: 45753 | C15: 30
A16: 45753 | C16: 60
A17: 45754 | C17: 45
A18: 45755 | C18: 20
A19: 45755 | C19: 40
A20: 45756 | C20: 20
A21: Cierre | C21: 491 | D21: =SUM(C10:C20) -> 405 | E21: =C21-D21 -> 86
A23: 45757 | C23: 40
A24: 45758 | C24: 20
A25: Cierre | C25: 64.8
A27: 45759 | C27: 40
A28: cierre | C28: 41.2
A30: 13/04/0205 | C30: 30
A31: 45761 | C31: 20
A32: 45762 | C32: 20
A33: 45762 | C33: 40
A34: 45763 | C34: 40
A35: 45764 | C35: 30
A36: 45765 | C36: 20
A37: 45766 | C37: 20
A38: 45766 | C38: 20
A39: 45767 | C39: 40
A40: Cierre | C40: 325 | D40: =SUM(C30:C39) -> 280 | E40: =C40-D40 -> 45
A42: 45768 | C42: 30
A43: 45769 | C43: 30
A44: 45770 | C44: 30
A45: 45771 | C45: 20
A46: 45772 | C46: 20
A47: 45773 | C47: 20
A48: Cierre | C48: 167 | D48: =SUM(C42:C47) -> 150 | E48: =C48-D48 -> 17
A50: 45776 | C50: 30
A51: 45777 | C51: 30
A52: cierre | C52: 67
A54: 45780 | C54: 30
A55: 45781 | C55: 20
A56: 45781 | C56: 30
A57: 45782 | C57: 30
A58: 45783 | C58: 20
A59: cierre | C59: 145.7 | D59: =SUM(C54:C58) -> 130 | E59: =C59-D59 -> 15.7
A61: 45785 | C61: 32
A62: 45787 | C62: 30
A63: 45788 | C63: 30
A64: 45789 | C64: 20
A65: 45789 | C65: 60
A66: 45790 | C66: 30
A67: 45790 | C67: 20
A68: 45791 | C68: 20
A69: 45791 | C69: 20
A70: 45792 | C70: 20
A71: 45792 | C71: 60
A72: 45793 | C72: =20+15 -> 35
A73: 45794 | C73: 20
A74: Cierre | C74: 449 | D74: =SUM(C61:C73) -> 397 | E74: =C74-D74 -> 52
A76: 45795 | C76: 50
A77: 45796 | C77: 30
A78: 45796 | C78: 60
A79: 45797 | C79: 35
A80: Cierre | C80: 202 | D80: =SUM(C76:C79) -> 175 | E80: =C80-D80 -> 27
A82: 45797 | C82: 20
A83: 45798 | C83: 30
A84: 45798 | C84: 20
A85: 45799 | C85: 30
A86: Cierre | C86: 122
A88: 45800 | C88: 80
A89: 45800 | C89: 60
A90: 45801 | C90: 30
A91: 45801 | C91: 50
A92: 45803 | C92: 50
A93: 45803 | C93: 30
A94: 45805 | C94: 60
A95: 45806 | C95: 60
A96: 45806 | C96: 30
A97: 45806 | C97: 60
A98: 45809 | C98: 44
A99: 45813 | C99: 124
A100: Cierre | C100: 891 | D100: =SUM(C88:C99) -> 678 | E100: =C100-D100 -> 213
A102: 45819 | C102: 100
A103: 45820 | C103: 50
A104: 45820 | C104: 50
A105: 45820 | C105: 50
A106: 45821 | C106: 50
A107: 45822 | C107: 50
A108: 45822 | C108: 50
A109: 45823 | C109: 50
A110: Cierre | C110: 521 | D110: =SUM(C102:C109) -> 450 | E110: =C110-D110 -> 71
A112: 45824 | C112: 50
A113: 45825 | C113: 100
...

Sheet Acciones ARG
A1: ID | B1: Ticker | C1: Gráfica | D1: Apertura | E1: Estado | F1: Cierre | G1: Dias | H1: Unidades | I1: Valor Compra | J1: Valor Actual | K1: Total Compra | L1: Total compra USD | M1: Valor Venta | N1: Total Venta | O1: Total Venta USD | P1: Gan Dia (%) | Q1: Gan Dia | R1: Ganancias (%) | S1: Ganancias Bruta (USD) | U1: Ticker | V1: Unidades | W1: % Cartera | X1: PPC | Y1: Total (Abierto) | Z1: Ganancias (%) | AA1: Ganancias Tot
A2: IOL | B2: GGAL | C2: =IFERROR(__xludf.DUMMYFUNCTION("if(B2=0,""..."", sparkline(query(GOOGLEFINANCE(B2,""price"",today()-$AE$27,today()),""select Col2"",0),{""charttype"",$AE$26}))"),"") | D2: 45569 | E2: CERRADA | G2: =if(B2=0,"...", IF(F2=0,today()-D2,F2-D2)) -> 548 | H2: 18 | I2: 5380 | J2: =IFERROR(__xludf.DUMMYFUNCTION("IF(B2=0,""..."",IF(E2=""CERRADA"",""-"",GOOGLEFINANCE(""BCBA:"" & B2)))"),"-") -> - | K2: =IF(B2=0,"...",$H$2*I2) -> 96840 | L2: =IF(B2=0,"...",K2/VLOOKUP($D2,CCL!$A$12:$B$828,2,0)) -> 78.992447 | M2: 6230 | N2: =IF(B2=0,"...",H2*M2) -> 112140 | O2: {=IF(B2=0,"...",IF(E2="ABIERTA",N2/CCL!$E$2,N2/ VLOOKUP(F2,{CCL!M:N;CCL!$P:$Q},2,FALSE)))} -> #N/A | P2: =IFERROR(__xludf.DUMMYFUNCTION("IF(B2=0,""..."",IF(E2=""CERRADA"",""-"",GOOGLEFINANCE(B2,""changepct"")/100))"),"-") -> - | Q2: =IFERROR(__xludf.DUMMYFUNCTION("IF(B2=0,""..."",IF(E2=""CERRADA"",""-"",GOOGLEFINANCE(B2,""change"")*H2))"),"-") -> - | R2: =IF(B2=0,"...",O2/L2-1) -> #N/A | S2: =IF(B2=0,"...",O2-L2) -> #N/A | U2: =IFERROR(__xludf.DUMMYFUNCTION("Unique(Filter(B2:B28,E2:E28=""ABIERTA""))"),"YPFD") -> YPFD | V2: =if(U2=0,"...",sumifs($H$2:$H$28,$B$2:$B$28,U2,$E$2:$E$28,"ABIERTA")) -> 13 | W2: =if(U2=0,"",Y2/$AD$18) -> 0.67300771 | X2: =if(V2=0,"...",if(U2=0,"...",sumifs($M$2:$M$28,$B$2:$B$28,U2,$E$2:$E$28,"ABIERTA")/V2)) -> 9998.7462 | Y2: =if(U2=0,"...",sumifs($N$2:$N$28,$B$2:$B$28,U2,$E$2:$E$28,"ABIERTA")) -> 844894.05 | Z2: =if(V2=0,"...",if(U2=0,"...",AA2/(Y2-AA2))) -> 0.00013330133 | AA2: =if(V2=0,"...",if(U2=0,"...",sumifs($S$2:$S$28,$B$2:$B$28,U2,$E$2:$E$28,"ABIERTA"))) -> 112.61049
A3: IOL | B3: PAMP | C3: =IFERROR(__xludf.DUMMYFUNCTION("if(B3=0,""..."", sparkline(query(GOOGLEFINANCE(B3,""price"",today()-$AE$27,today()),""select Col2"",0),{""charttype"",$AE$26}))"),"") | D3: 45595 | E3: CERRADA | G3: =if(B3=0,"...", IF(F3=0,today()-D3,F3-D3)) -> 522 | H3: 31 | I3: 3090 | J3: =IFERROR(__xludf.DUMMYFUNCTION("IF(B3=0,""..."",IF(E3=""CERRADA"",""-"",GOOGLEFINANCE(""BCBA:"" & B3)))"),"-") -> - | K3: =IF(B3=0,"...",H3*I3) -> 95790 | L3: =IF(B3=0,"...",K3/VLOOKUP($D3,CCL!$A$12:$B$828,2,0)) -> 82.677369 | M3: 3740 | N3: =IF(B3=0,"...",H3*M3) -> 115940 | O3: {=IF(B3=0,"...",IF(E3="ABIERTA",N3/CCL!$E$2,N3/ VLOOKUP(F3,{CCL!M:N;CCL!$P:$Q},2,FALSE)))} -> #N/A | P3: =IFERROR(__xludf.DUMMYFUNCTION("IF(B3=0,""..."",IF(E3=""CERRADA"",""-"",GOOGLEFINANCE(B3,""changepct"")/100))"),"-") -> - | Q3: =IFERROR(__xludf.DUMMYFUNCTION("IF(B3=0,""..."",IF(E3=""CERRADA"",""-"",GOOGLEFINANCE(B3,""change"")*H3))"),"-") -> - | R3: =IF(B3=0,"...",O3/L3-1) -> #N/A | S3: =IF(B3=0,"...",O3-L3) -> #N/A | U3: =IFERROR(__xludf.DUMMYFUNCTION("""COMPUTED_VALUE"""),"BCBA:GGAL") -> BCBA:GGAL | V3: =if(U3=0,"...",sumifs($H$2:$H$28,$B$2:$B$28,U3,$E$2:$E$28,"ABIERTA")) -> 60 | W3: =if(U3=0,"",Y3/$AD$18) -> 0.32699229 | X3: =if(V3=0,"...",if(U3=0,"...",sumifs($M$2:$M$28,$B$2:$B$28,U3,$E$2:$E$28,"ABIERTA")/V3)) -> 114.0295 | Y3: =if(U3=0,"...",sumifs($N$2:$N$28,$B$2:$B$28,U3,$E$2:$E$28,"ABIERTA")) -> 410506.2 | Z3: =if(V3=0,"...",if(U3=0,"...",AA3/(Y3-AA3))) -> -0.00011815538 | AA3: =if(V3=0,"...",if(U3=0,"...",sumifs($S$2:$S$28,$B$2:$B$28,U3,$E$2:$E$28,"ABIERTA"))) -> -48.509249
A4: IOL | B4: ALUA | C4: =IFERROR(__xludf.DUMMYFUNCTION("if(B4=0,""..."", sparkline(query(GOOGLEFINANCE(B4,""price"",today()-$AE$27,today()),""select Col2"",0),{""charttype"",$AE$26}))"),"") | D4: 45621 | E4: CERRADA | F4: 45714 | G4: =if(B4=0,"...", IF(F4=0,today()-D4,F4-D4)) -> 93 | H4: 159 | I4: 951 | J4: =IFERROR(__xludf.DUMMYFUNCTION("IF(B4=0,""..."",IF(E4=""CERRADA"",""-"",GOOGLEFINANCE(B4)))"),"-") -> - | K4: =IF(B4=0,"...",H4*I4) -> 151209 | L4: =IF(B4=0,"...",K4/VLOOKUP($D4,CCL!$A$12:$B$828,2,0)) -> 136.21083 | M4: 793 | N4: =IF(B4=0,"...",H4*M4) -> 126087 | O4: {=IF(B4=0,"...",IF(E4="ABIERTA",N4/CCL!$E$2,N4/ VLOOKUP(F4,{CCL!M:N;CCL!$P:$Q},2,FALSE)))} -> 103.35085 | P4: =IFERROR(__xludf.DUMMYFUNCTION("IF(B4=0,""..."",IF(E4=""CERRADA"",""-"",GOOGLEFINANCE(B4,""changepct"")/100))"),"-") -> - | Q4: =IFERROR(__xludf.DUMMYFUNCTION("IF(B4=0,""..."",IF(E4=""CERRADA"",""-"",GOOGLEFINANCE(B4,""change"")*H4))"),"-") -> - | R4: =IF(B4=0,"...",O4/L4-1) -> -0.24124352 | S4: =IF(B4=0,"...",O4-L4) -> -32.859979 | V4: =if(U4=0,"...",sumifs($H$2:$H$28,$B$2:$B$28,U4,$E$2:$E$28,"ABIERTA")) -> ... | W4: =if(U4=0,"",Y4/$AD$18) | X4: =if(V4=0,"...",if(U4=0,"...",sumifs($M$2:$M$28,$B$2:$B$28,U4,$E$2:$E$28,"ABIERTA")/V4)) -> ... | Y4: =if(U4=0,"...",sumifs($N$2:$N$28,$B$2:$B$28,U4,$E$2:$E$28,"ABIERTA")) -> ... | Z4: =if(V4=0,"...",if(U4=0,"...",AA4/(Y4-AA4))) -> ... | AA4: =if(V4=0,"...",if(U4=0,"...",sumifs($S$2:$S$28,$B$2:$B$28,U4,$E$2:$E$28,"ABIERTA"))) -> ...
A5: IOL | B5: BCBA:SUPV | C5: =IFERROR(__xludf.DUMMYFUNCTION("if(B5=0,""..."", sparkline(query(GOOGLEFINANCE(B5,""price"",today()-$AE$27,today()),""select Col2"",0),{""charttype"",$AE$26}))"),"") | D5: 45625 | E5: CERRADA | H5: 42 | I5: 2620 | J5: =IFERROR(__xludf.DUMMYFUNCTION("IF(B5=0,""..."",IF(E5=""CERRADA"",""-"",GOOGLEFINANCE(B5)))"),"-") -> - | K5: =IF(B5=0,"...",H5*I5) -> 110040 | L5: =IF(B5=0,"...",K5/VLOOKUP($D5,CCL!$A$12:$B$828,2,0)) -> 99.19501 | M5: 3420 | N5: =IF(B5=0,"...",H5*M5) -> 143640 | O5: {=IF(B5=0,"...",IF(E5="ABIERTA",N5/CCL!$E$2,N5/ VLOOKUP(F5,{CCL!M:N;CCL!$P:$Q},2,FALSE)))} -> #N/A | P5: =IFERROR(__xludf.DUMMYFUNCTION("IF(B5=0,""..."",IF(E5=""CERRADA"",""-"",GOOGLEFINANCE(B5,""changepct"")/100))"),"-") -> - | Q5: =IFERROR(__xludf.DUMMYFUNCTION("IF(B5=0,""..."",IF(E5=""CERRADA"",""-"",GOOGLEFINANCE(B5,""change"")*H5))"),"-") -> - | R5: =IF(B5=0,"...",O5/L5-1) -> #N/A | S5: =IF(B5=0,"...",O5-L5) -> #N/A | V5: =if(U5=0,"...",sumifs($H$2:$H$28,$B$2:$B$28,U5,$E$2:$E$28,"ABIERTA")) -> ... | W5: =if(U5=0,"",Y5/$AD$18) | X5: =if(V5=0,"...",if(U5=0,"...",sumifs($M$2:$M$28,$B$2:$B$28,U5,$E$2:$E$28,"ABIERTA")/V5)) -> ... | Y5: =if(U5=0,"...",sumifs($N$2:$N$28,$B$2:$B$28,U5,$E$2:$E$28,"ABIERTA")) -> ... | Z5: =if(V5=0,"...",if(U5=0,"...",AA5/(Y5-AA5))) -> ... | AA5: =if(V5=0,"...",if(U5=0,"...",sumifs($S$2:$S$28,$B$2:$B$28,U5,$E$2:$E$28,"ABIERTA"))) -> ...
A6: IOL | B6: BCBA:LOMA | C6: =IFERROR(__xludf.DUMMYFUNCTION("if(B6=0,""..."", sparkline(query(GOOGLEFINANCE(B6,""price"",today()-$AE$27,today()),""select Col2"",0),{""charttype"",$AE$26}))"),"") | D6: 45645 | E6: CERRADA | F6: 45695 | G6: =if(B6=0,"...", IF(F6=0,today()-D6,F6-D6)) -> 50 | H6: 50 | I6: 2795 | J6: =IFERROR(__xludf.DUMMYFUNCTION("IF(B6=0,""..."",IF(E6=""CERRADA"",""-"",GOOGLEFINANCE(B6)))"),"-") -> - | K6: =IF(B6=0,"...",H6*I6) -> 139750 | L6: =IF(B6=0,"...",K6/VLOOKUP($D6,CCL!$A$12:$B$828,2,0)) -> 120.72495 | M6: 2960 | N6: =IF(B6=0,"...",H6*M6) -> 148000 | O6: {=IF(B6=0,"...",IF(E6="ABIERTA",N6/CCL!$E$2,N6/ VLOOKUP(F6,{CCL!M:N;CCL!$P:$Q},2,FALSE)))} -> 123.00839 | P6: =IFERROR(__xludf.DUMMYFUNCTION("IF(B6=0,""..."",IF(E6=""CERRADA"",""-"",GOOGLEFINANCE(B6,""changepct"")/100))"),"-") -> - | Q6: =IFERROR(__xludf.DUMMYFUNCTION("IF(B6=0,""..."",IF(E6=""CERRADA"",""-"",GOOGLEFINANCE(B6,""change"")*H6))"),"-") -> - | R6: =IF(B6=0,"...",O6/L6-1) -> 0.018914331 | S6: =IF(B6=0,"...",O6-L6) -> 2.2834317 | V6: =if(U6=0,"...",sumifs($H$2:$H$28,$B$2:$B$28,U6,$E$2:$E$28,"ABIERTA")) -> ... | W6: =if(U6=0,"",Y6/$AD$18) | X6: =if(V6=0,"...",if(U6=0,"...",sumifs($M$2:$M$28,$B$2:$B$28,U6,$E$2:$E$28,"ABIERTA")/V6)) -> ... | Y6: =if(U6=0,"...",sumifs($N$2:$N$28,$B$2:$B$28,U6,$E$2:$E$28,"ABIERTA")) -> ... | Z6: =if(V6=0,"...",if(U6=0,"...",AA6/(Y6-AA6))) -> ... | AA6: =if(V6=0,"...",if(U6=0,"...",sumifs($S$2:$S$28,$B$2:$B$28,U6,$E$2:$E$28,"ABIERTA"))) -> ...
A7: IOL | B7: PAMP | C7: =IFERROR(__xludf.DUMMYFUNCTION("if(B7=0,""..."", sparkline(query(GOOGLEFINANCE(B7,""price"",today()-$AE$27,today()),""select Col2"",0),{""charttype"",$AE$26}))"),"") | D7: 45868 | E7: CERRADA | F7: 45961 | G7: =if(B7=0,"...", IF(F7=0,today()-D7,F7-D7)) -> 93 | H7: 41 | I7: 4070 | J7: =IFERROR(__xludf.DUMMYFUNCTION("IF(B7=0,""..."",IF(E7=""CERRADA"",""-"",GOOGLEFINANCE(B7)))"),"-") -> - | K7: =IF(B7=0,"...",H7*I7) -> 166870 | L7: {=IF($D7=0,"...",K7/VLOOKUP($D7,{CCL!M:N;CCL!$P:$Q},2,FALSE))} -> 126.41667 | M7: 5120 | N7: =IF(B7=0,"...",H7*M7) -> 209920 | O7: {=IF(B7=0,"...",IF(E7="ABIERTA",N7/CCL!$E$2,N7/ VLOOKUP(F7,{CCL!M:N;CCL!$P:$Q},2,FALSE)))} -> 139.34007 | P7: =IFERROR(__xludf.DUMMYFUNCTION("IF(B7=0,""..."",IF(E7=""CERRADA"",""-"",GOOGLEFINANCE(B7,""changepct"")/100))"),"-") -> - | Q7: =IFERROR(__xludf.DUMMYFUNCTION("IF(B7=0,""..."",IF(E7=""CERRADA"",""-"",GOOGLEFINANCE(B7,""change"")*H7))"),"-") -> - | R7: =IF(B7=0,"...",O7/L7-1) -> 0.10222866 | S7: =IF(B7=0,"...",O7-L7) -> 12.923406 | V7: =if(U7=0,"...",sumifs($H$2:$H$28,$B$2:$B$28,U7,$E$2:$E$28,"ABIERTA")) -> ... | W7: =if(U7=0,"",Y7/$AD$18) | X7: =if(V7=0,"...",if(U7=0,"...",sumifs($M$2:$M$28,$B$2:$B$28,U7,$E$2:$E$28,"ABIERTA")/V7)) -> ... | Y7: =if(U7=0,"...",sumifs($N$2:$N$28,$B$2:$B$28,U7,$E$2:$E$28,"ABIERTA")) -> ... | Z7: =if(V7=0,"...",if(U7=0,"...",AA7/(Y7-AA7))) -> ... | AA7: =if(V7=0,"...",if(U7=0,"...",sumifs($S$2:$S$28,$B$2:$B$28,U7,$E$2:$E$28,"ABIERTA"))) -> ...
A8: IOL | B8: YPFD | C8: =IFERROR(__xludf.DUMMYFUNCTION("if(B8=0,""..."", sparkline(query(GOOGLEFINANCE(B8,""price"",today()-$AE$27,today()),""select Col2"",0),{""charttype"",$AE$26}))"),"") | D8: 45868 | E8: ABIERTA | G8: =if(B8=0,"...", IF(F8=0,today()-D8,F8-D8)) -> 249 | H8: 4 | I8: 44375 | J8: =IFERROR(__xludf.DUMMYFUNCTION("IF(B8=0,""..."",IF(E8=""CERRADA"",""-"",GOOGLEFINANCE(B8)))"),65450.0) -> 65450 | K8: =IF(B8=0,"...",H8*I8) -> 177500 | L8: {=IF($D8=0,"...",K8/VLOOKUP($D8,{CCL!M:N;CCL!$P:$Q},2,FALSE))} -> 134.4697 | M8: =IF(B8=0,"...",IF(E8="CERRADA","Valor Venta",J8*(1-VLOOKUP(A8,Config!$B$3:$C$22,2,FALSE)))) -> 64991.85 | N8: =IF(B8=0,"...",H8*M8) -> 259967.4 | O8: {=IF(B8=0,"...",IF(E8="ABIERTA",N8/CCL!$E$2,N8/ VLOOKUP(F8,{CCL!M:N;CCL!$P:$Q},2,FALSE)))} -> 175.95682 | P8: =IFERROR(__xludf.DUMMYFUNCTION("IF(B8=0,""..."",IF(E8=""CERRADA"",""-"",GOOGLEFINANCE(B8,""changepct"")/100))"),-0.0304) -> -0.0304 | Q8: =IFERROR(__xludf.DUMMYFUNCTION("IF(B8=0,""..."",IF(E8=""CERRADA"",""-"",GOOGLEFINANCE(B8,""change"")*H8))"),-8200.0) -> -8200 | R8: =IF(B8=0,"...",O8/L8-1) -> 0.30852394 | S8: =IF(B8=0,"...",O8-L8) -> 41.487121 | V8: =if(U8=0,"...",sumifs($H$2:$H$28,$B$2:$B$28,U8,$E$2:$E$28,"ABIERTA")) -> ... | W8: =if(U8=0,"",Y8/$AD$18) | X8: =if(V8=0,"...",if(U8=0,"...",sumifs($M$2:$M$28,$B$2:$B$28,U8,$E$2:$E$28,"ABIERTA")/V8)) -> ... | Y8: =if(U8=0,"...",sumifs($N$2:$N$28,$B$2:$B$28,U8,$E$2:$E$28,"ABIERTA")) -> ... | Z8: =if(V8=0,"...",if(U8=0,"...",AA8/(Y8-AA8))) -> ... | AA8: =if(V8=0,"...",if(U8=0,"...",sumifs($S$2:$S$28,$B$2:$B$28,U8,$E$2:$E$28,"ABIERTA"))) -> ...
A9: IOL | B9: YPFD | C9: =IFERROR(__xludf.DUMMYFUNCTION("if(B9=0,""..."", sparkline(query(GOOGLEFINANCE(B9,""price"",today()-$AE$27,today()),""select Col2"",0),{""charttype"",$AE$26}))"),"") | D9: 46021 | E9: ABIERTA | G9: =if(B9=0,"...", IF(F9=0,today()-D9,F9-D9)) -> 96 | H9: 9 | I9: 54900 | J9: =IFERROR(__xludf.DUMMYFUNCTION("IF(B9=0,""..."",IF(E9=""CERRADA"",""-"",GOOGLEFINANCE(B9)))"),65450.0) -> 65450 | K9: =IF(B9=0,"...",H9*I9) -> 494100 | L9: {=IF($D9=0,"...",K9/VLOOKUP($D9,{CCL!M:N;CCL!$P:$Q},2,FALSE))} -> 324.77947 | M9: =IF(B9=0,"...",IF(E9="CERRADA","Valor Venta",J9*(1-VLOOKUP(A9,Config!$B$3:$C$22,2,FALSE)))) -> 64991.85 | N9: =IF(B9=0,"...",H9*M9) -> 584926.65 | O9: {=IF(B9=0,"...",IF(E9="ABIERTA",N9/CCL!$E$2,N9/ VLOOKUP(F9,{CCL!M:N;CCL!$P:$Q},2,FALSE)))} -> 395.90284 | P9: =IFERROR(__xludf.DUMMYFUNCTION("IF(B9=0,""..."",IF(E9=""CERRADA"",""-"",GOOGLEFINANCE(B9,""changepct"")/100))"),-0.0304) -> -0.0304 | Q9: =IFERROR(__xludf.DUMMYFUNCTION("IF(B9=0,""..."",IF(E9=""CERRADA"",""-"",GOOGLEFINANCE(B9,""change"")*H9))"),-18450.0) -> -18450 | R9: =IF(B9=0,"...",O9/L9-1) -> 0.21898973 | S9: =IF(B9=0,"...",O9-L9) -> 71.123369 | V9: =if(U9=0,"...",sumifs($H$2:$H$28,$B$2:$B$28,U9,$E$2:$E$28,"ABIERTA")) -> ... | W9: =if(U9=0,"",Y9/$AD$18) | X9: =if(V9=0,"...",if(U9=0,"...",sumifs($M$2:$M$28,$B$2:$B$28,U9,$E$2:$E$28,"ABIERTA")/V9)) -> ... | Y9: =if(U9=0,"...",sumifs($N$2:$N$28,$B$2:$B$28,U9,$E$2:$E$28,"ABIERTA")) -> ... | Z9: =if(V9=0,"...",if(U9=0,"...",AA9/(Y9-AA9))) -> ... | AA9: =if(V9=0,"...",if(U9=0,"...",sumifs($S$2:$S$28,$B$2:$B$28,U9,$E$2:$E$28,"ABIERTA"))) -> ...
A10: IOL | B10: BCBA:GGAL | C10: =IFERROR(__xludf.DUMMYFUNCTION("if(B10=0,""..."", sparkline(query(GOOGLEFINANCE(B10,""price"",today()-$AE$27,today()),""select Col2"",0),{""charttype"",$AE$26}))"),"") | D10: 46021 | E10: ABIERTA | G10: =IF(B10=0,"...", IF(F10=0,TODAY()-D10,F10-D10)) -> 96 | H10: 60 | I10: 8275 | J10: =IFERROR(__xludf.DUMMYFUNCTION("IF(B10=0,""..."",IF(E10=""CERRADA"",""-"",GOOGLEFINANCE(B10)))"),6890.0) -> 6890 | K10: =IF(B10=0,"...",H10*I10) -> 496500 | L10: {=IF($D10=0,"...",K10/VLOOKUP($D10,{CCL!M:N;CCL!$P:$Q},2,FALSE))} -> 326.35703 | M10: =IF(B10=0,"...",IF(E10="CERRADA","Valor Venta",J10*(1-VLOOKUP(A10,Config!$B$3:$C$22,2,FALSE)))) -> 6841.77 | N10: =IF(B10=0,"...",H10*M10) -> 410506.2 | O10: {=IF(B10=0,"...",IF(E10="ABIERTA",N10/CCL!$E$2,N10/ VLOOKUP(F10,{CCL!M:N;CCL!$P:$Q},2,FALSE)))} -> 277.84778 | P10: =IFERROR(__xludf.DUMMYFUNCTION("IF(B10=0,""..."",IF(E10=""CERRADA"",""-"",GOOGLEFINANCE(B10,""changepct"")/100))"),0.0) -> 0 | Q10: =IFERROR(__xludf.DUMMYFUNCTION("IF(B10=0,""..."",IF(E10=""CERRADA"",""-"",GOOGLEFINANCE(B10,""change"")*H10))"),0.0) -> 0 | R10: =IF(B10=0,"...",O10/L10-1) -> -0.14863859 | S10: =IF(B10=0,"...",O10-L10) -> -48.509249 | V10: =if(U10=0,"...",sumifs($H$2:$H$28,$B$2:$B$28,U10,$E$2:$E$28,"ABIERTA")) -> ... | W10: =if(U10=0,"",Y10/$AD$18) | X10: =if(V10=0,"...",if(U10=0,"...",sumifs($M$2:$M$28,$B$2:$B$28,U10,$E$2:$E$28,"ABIERTA")/V10)) -> ... | Y10: =if(U10=0,"...",sumifs($N$2:$N$28,$B$2:$B$28,U10,$E$2:$E$28,"ABIERTA")) -> ... | Z10: =if(V10=0,"...",if(U10=0,"...",AA10/(Y10-AA10))) -> ... | AA10: =if(V10=0,"...",if(U10=0,"...",sumifs($S$2:$S$28,$B$2:$B$28,U10,$E$2:$E$28,"ABIERTA"))) -> ...
C11: =IFERROR(__xludf.DUMMYFUNCTION("if(B11=0,""..."", sparkline(query(GOOGLEFINANCE(B11,""price"",today()-$AE$27,today()),""select Col2"",0),{""charttype"",$AE$26}))"),"...") -> ... | G11: =if(B11=0,"...", IF(F11=0,today()-D11,F11-D11)) -> ... | J11: =IFERROR(__xludf.DUMMYFUNCTION("IF(B11=0,""..."",IF(E11=""CERRADA"",""-"",GOOGLEFINANCE(B11)*100))"),"...") -> ... | K11: =IF(B11=0,"...",H11*I11) -> ... | L11: =IF(B11=0,"...",K11/VLOOKUP($D11,CCL!$A$12:$B$828,2,0)) -> ... | M11: =IF(B11=0,"...",IF(E11="CERRADA","Valor Venta",J11*(1-VLOOKUP($A$2,Config!$B$3:$C$22,2,FALSE)))) -> ... | N11: =IF(B11=0,"...",H11*M11) -> ... | O11: {=IF(B11=0,"...",IF(E11="ABIERTA",K11/CCL!$E$2,N11/ VLOOKUP(F11,{CCL!M:N;CCL!$P:$Q},2,FALSE)))} -> ... | P11: =IFERROR(__xludf.DUMMYFUNCTION("if(B11=0,""..."",GOOGLEFINANCE(B11,""changepct"")/100)"),"...") -> ... | Q11: =IFERROR(__xludf.DUMMYFUNCTION("IF(B11=0,""..."",IF(E11=""CERRADA"",""-"",GOOGLEFINANCE(B11,""change"")*H11))"),"...") -> ... | R11: =IF(B11=0,"...",O11/L11-1) -> ... | S11: =IF(B11=0,"...",N11-K11) -> ... | V11: =if(U11=0,"...",sumifs($H$2:$H$28,$B$2:$B$28,U11,$E$2:$E$28,"ABIERTA")) -> ... | W11: =if(U11=0,"",Y11/$AD$18) | X11: =if(V11=0,"...",if(U11=0,"...",sumifs($M$2:$M$28,$B$2:$B$28,U11,$E$2:$E$28,"ABIERTA")/V11)) -> ... | Y11: =if(U11=0,"...",sumifs($N$2:$N$28,$B$2:$B$28,U11,$E$2:$E$28,"ABIERTA")) -> ... | Z11: =if(V11=0,"...",if(U11=0,"...",AA11/(Y11-AA11))) -> ... | AA11: =if(V11=0,"...",if(U11=0,"...",sumifs($S$2:$S$28,$B$2:$B$28,U11,$E$2:$E$28,"ABIERTA"))) -> ...
C12: =IFERROR(__xludf.DUMMYFUNCTION("if(B12=0,""..."", sparkline(query(GOOGLEFINANCE(B12,""price"",today()-$AE$27,today()),""select Col2"",0),{""charttype"",$AE$26}))"),"...") -> ... | G12: =if(B12=0,"...", IF(F12=0,today()-D12,F12-D12)) -> ... | J12: =IFERROR(__xludf.DUMMYFUNCTION("IF(B12=0,""..."",IF(E12=""CERRADA"",""-"",GOOGLEFINANCE(B12)))"),"...") -> ... | K12: =IF(B12=0,"...",H12*I12) -> ... | L12: =IF(B12=0,"...",K12/VLOOKUP($D12,CCL!$A$12:$B$828,2,0)) -> ... | M12: =IF(B12=0,"...",IF(E12="CERRADA","Valor Venta",J12*(1-VLOOKUP($A$2,Config!$B$3:$C$22,2,FALSE)))) -> ... | N12: =IF(B12=0,"...",H12*M12) -> ... | O12: {=IF(B12=0,"...",IF(E12="ABIERTA",K12/CCL!$E$2,N12/ VLOOKUP(F12,{CCL!M:N;CCL!$P:$Q},2,FALSE)))} -> ... | P12: =IFERROR(__xludf.DUMMYFUNCTION("if(B12=0,""..."",GOOGLEFINANCE(B12,""changepct"")/100)"),"...") -> ... | Q12: =IFERROR(__xludf.DUMMYFUNCTION("IF(B12=0,""..."",IF(E12=""CERRADA"",""-"",GOOGLEFINANCE(B12,""change"")*H12))"),"...") -> ... | R12: =IF(B12=0,"...",O12/L12-1) -> ... | S12: =IF(B12=0,"...",N12-K12) -> ... | V12: =if(U12=0,"...",sumifs($H$2:$H$28,$B$2:$B$28,U12,$E$2:$E$28,"ABIERTA")) -> ... | W12: =if(U12=0,"",Y12/$AD$18) | X12: =if(V12=0,"...",if(U12=0,"...",sumifs($M$2:$M$28,$B$2:$B$28,U12,$E$2:$E$28,"ABIERTA")/V12)) -> ... | Y12: =if(U12=0,"...",sumifs($N$2:$N$28,$B$2:$B$28,U12,$E$2:$E$28,"ABIERTA")) -> ... | Z12: =if(V12=0,"...",if(U12=0,"...",AA12/(Y12-AA12))) -> ... | AA12: =if(V12=0,"...",if(U12=0,"...",sumifs($S$2:$S$28,$B$2:$B$28,U12,$E$2:$E$28,"ABIERTA"))) -> ...
C13: =IFERROR(__xludf.DUMMYFUNCTION("if(B13=0,""..."", sparkline(query(GOOGLEFINANCE(B13,""price"",today()-$AE$27,today()),""select Col2"",0),{""charttype"",$AE$26}))"),"...") -> ... | G13: =if(B13=0,"...", IF(F13=0,today()-D13,F13-D13)) -> ... | J13: =IFERROR(__xludf.DUMMYFUNCTION("IF(B13=0,""..."",IF(E13=""CERRADA"",""-"",GOOGLEFINANCE(B13)))"),"...") -> ... | K13: =IF(B13=0,"...",H13*I13) -> ... | L13: =IF(B13=0,"...",K13/VLOOKUP($D13,CCL!$A$12:$B$828,2,0)) -> ... | M13: =IF(B13=0,"...",IF(E13="CERRADA","Valor Venta",J13*(1-VLOOKUP($A$2,Config!$B$3:$C$22,2,FALSE)))) -> ... | N13: =IF(B13=0,"...",H13*M13) -> ... | O13: {=IF(B13=0,"...",IF(E13="ABIERTA",K13/CCL!$E$2,N13/ VLOOKUP(F13,{CCL!M:N;CCL!$P:$Q},2,FALSE)))} -> ... | P13: =IFERROR(__xludf.DUMMYFUNCTION("if(B13=0,""..."",GOOGLEFINANCE(B13,""changepct"")/100)"),"...") -> ... | Q13: =IFERROR(__xludf.DUMMYFUNCTION("IF(B13=0,""..."",IF(E13=""CERRADA"",""-"",GOOGLEFINANCE(B13,""change"")*H13))"),"...") -> ... | R13: =IF(B13=0,"...",O13/L13-1) -> ... | S13: =IF(B13=0,"...",N13-K13) -> ... | V13: =if(U13=0,"...",sumifs($H$2:$H$28,$B$2:$B$28,U13,$E$2:$E$28,"ABIERTA")) -> ... | W13: =if(U13=0,"",Y13/$AD$18) | X13: =if(V13=0,"...",if(U13=0,"...",sumifs($M$2:$M$28,$B$2:$B$28,U13,$E$2:$E$28,"ABIERTA")/V13)) -> ... | Y13: =if(U13=0,"...",sumifs($N$2:$N$28,$B$2:$B$28,U13,$E$2:$E$28,"ABIERTA")) -> ... | Z13: =if(V13=0,"...",if(U13=0,"...",AA13/(Y13-AA13))) -> ... | AA13: =if(V13=0,"...",if(U13=0,"...",sumifs($S$2:$S$28,$B$2:$B$28,U13,$E$2:$E$28,"ABIERTA"))) -> ...
C14: =IFERROR(__xludf.DUMMYFUNCTION("if(B14=0,""..."", sparkline(query(GOOGLEFINANCE(B14,""price"",today()-$AE$27,today()),""select Col2"",0),{""charttype"",$AE$26}))"),"...") -> ... | G14: =if(B14=0,"...", IF(F14=0,today()-D14,F14-D14)) -> ... | J14: =IFERROR(__xludf.DUMMYFUNCTION("IF(B14=0,""..."",IF(E14=""CERRADA"",""-"",GOOGLEFINANCE(B14)))"),"...") -> ... | K14: =IF(B14=0,"...",H14*I14) -> ... | L14: =IF(B14=0,"...",K14/VLOOKUP($D14,CCL!$A$12:$B$828,2,0)) -> ... | M14: =IF(B14=0,"...",IF(E14="CERRADA","Valor Venta",J14*(1-VLOOKUP($A$2,Config!$B$3:$C$22,2,FALSE)))) -> ... | N14: =IF(B14=0,"...",H14*M14) -> ... | O14: {=IF(B14=0,"...",IF(E14="ABIERTA",K14/CCL!$E$2,N14/ VLOOKUP(F14,{CCL!M:N;CCL!$P:$Q},2,FALSE)))} -> ... | P14: =IFERROR(__xludf.DUMMYFUNCTION("if(B14=0,""..."",GOOGLEFINANCE(B14,""changepct"")/100)"),"...") -> ... | Q14: =IFERROR(__xludf.DUMMYFUNCTION("IF(B14=0,""..."",IF(E14=""CERRADA"",""-"",GOOGLEFINANCE(B14,""change"")*H14))"),"...") -> ... | R14: =IF(B14=0,"...",O14/L14-1) -> ... | S14: =IF(B14=0,"...",N14-K14) -> ... | V14: =if(U14=0,"...",sumifs($H$2:$H$28,$B$2:$B$28,U14,$E$2:$E$28,"ABIERTA")) -> ... | W14: =if(U14=0,"",Y14/$AD$18) | X14: =if(V14=0,"...",if(U14=0,"...",sumifs($M$2:$M$28,$B$2:$B$28,U14,$E$2:$E$28,"ABIERTA")/V14)) -> ... | Y14: =if(U14=0,"...",sumifs($N$2:$N$28,$B$2:$B$28,U14,$E$2:$E$28,"ABIERTA")) -> ... | Z14: =if(V14=0,"...",if(U14=0,"...",AA14/(Y14-AA14))) -> ... | AA14: =if(V14=0,"...",if(U14=0,"...",sumifs($S$2:$S$28,$B$2:$B$28,U14,$E$2:$E$28,"ABIERTA"))) -> ...
C15: =IFERROR(__xludf.DUMMYFUNCTION("if(B15=0,""..."", sparkline(query(GOOGLEFINANCE(B15,""price"",today()-$AE$27,today()),""select Col2"",0),{""charttype"",$AE$26}))"),"...") -> ... | G15: =if(B15=0,"...", IF(F15=0,today()-D15,F15-D15)) -> ... | J15: =IFERROR(__xludf.DUMMYFUNCTION("IF(B15=0,""..."",IF(E15=""CERRADA"",""-"",GOOGLEFINANCE(""BCBA:"" & B15)))"),"...") -> ... | K15: =IF(B15=0,"...",H15*I15) -> ... | L15: =IF(B15=0,"...",K15/VLOOKUP($D15,CCL!$A$12:$B$828,2,0)) -> ... | M15: =IF(B15=0,"...",IF(E15="CERRADA","Valor Venta",J15*(1-VLOOKUP($A$2,Config!$B$3:$C$22,2,FALSE)))) -> ... | N15: =IF(B15=0,"...",H15*M15) -> ... | O15: {=IF(B15=0,"...",IF(E15="ABIERTA",K15/CCL!$E$2,N15/ VLOOKUP(F15,{CCL!M:N;CCL!$P:$Q},2,FALSE)))} -> ... | P15: =IFERROR(__xludf.DUMMYFUNCTION("if(B15=0,""..."",GOOGLEFINANCE(B15,""changepct"")/100)"),"...") -> ... | Q15: =IFERROR(__xludf.DUMMYFUNCTION("IF(B15=0,""..."",IF(E15=""CERRADA"",""-"",GOOGLEFINANCE(B15,""change"")*H15))"),"...") -> ... | R15: =IF(B15=0,"...",O15/L15-1) -> ... | S15: =IF(B15=0,"...",N15-K15) -> ... | V15: =if(U15=0,"...",sumifs($H$2:$H$28,$B$2:$B$28,U15,$E$2:$E$28,"ABIERTA")) -> ... | W15: =if(U15=0,"",Y15/$AD$18) | X15: =if(V15=0,"...",if(U15=0,"...",sumifs($M$2:$M$28,$B$2:$B$28,U15,$E$2:$E$28,"ABIERTA")/V15)) -> ... | Y15: =if(U15=0,"...",sumifs($N$2:$N$28,$B$2:$B$28,U15,$E$2:$E$28,"ABIERTA")) -> ... | Z15: =if(V15=0,"...",if(U15=0,"...",AA15/(Y15-AA15))) -> ... | AA15: =if(V15=0,"...",if(U15=0,"...",sumifs($S$2:$S$28,$B$2:$B$28,U15,$E$2:$E$28,"ABIERTA"))) -> ...
C16: =IFERROR(__xludf.DUMMYFUNCTION("if(B16=0,""..."", sparkline(query(GOOGLEFINANCE(B16,""price"",today()-$AE$27,today()),""select Col2"",0),{""charttype"",$AE$26}))"),"...") -> ... | G16: =if(B16=0,"...", IF(F16=0,today()-D16,F16-D16)) -> ... | J16: =IFERROR(__xludf.DUMMYFUNCTION("IF(B16=0,""..."",IF(E16=""CERRADA"",""-"",GOOGLEFINANCE(""BCBA:"" & B16)))"),"...") -> ... | K16: =IF(B16=0,"...",H16*I16) -> ... | L16: =IF(B16=0,"...",K16/VLOOKUP($D16,CCL!$A$12:$B$828,2,0)) -> ... | M16: =IF(B16=0,"...",IF(E16="CERRADA","Valor Venta",J16*(1-VLOOKUP($A$2,Config!$B$3:$C$22,2,FALSE)))) -> ... | N16: =IF(B16=0,"...",H16*M16) -> ... | O16: {=IF(B16=0,"...",IF(E16="ABIERTA",K16/CCL!$E$2,N16/ VLOOKUP(F16,{CCL!M:N;CCL!$P:$Q},2,FALSE)))} -> ... | P16: =IFERROR(__xludf.DUMMYFUNCTION("if(B16=0,""..."",GOOGLEFINANCE(B16,""changepct"")/100)"),"...") -> ... | Q16: =IFERROR(__xludf.DUMMYFUNCTION("IF(B16=0,""..."",IF(E16=""CERRADA"",""-"",GOOGLEFINANCE(B16,""change"")*H16))"),"...") -> ... | R16: =IF(B16=0,"...",O16/L16-1) -> ... | S16: =IF(B16=0,"...",N16-K16) -> ... | V16: =if(U16=0,"...",sumifs($H$2:$H$28,$B$2:$B$28,U16,$E$2:$E$28,"ABIERTA")) -> ... | W16: =if(U16=0,"",Y16/$AD$18) | X16: =if(V16=0,"...",if(U16=0,"...",sumifs($M$2:$M$28,$B$2:$B$28,U16,$E$2:$E$28,"ABIERTA")/V16)) -> ... | Y16: =if(U16=0,"...",sumifs($N$2:$N$28,$B$2:$B$28,U16,$E$2:$E$28,"ABIERTA")) -> ... | Z16: =if(V16=0,"...",if(U16=0,"...",AA16/(Y16-AA16))) -> ... | AA16: =if(V16=0,"...",if(U16=0,"...",sumifs($S$2:$S$28,$B$2:$B$28,U16,$E$2:$E$28,"ABIERTA"))) -> ...
C17: =IFERROR(__xludf.DUMMYFUNCTION("if(B17=0,""..."", sparkline(query(GOOGLEFINANCE(B17,""price"",today()-$AE$27,today()),""select Col2"",0),{""charttype"",$AE$26}))"),"...") -> ... | G17: =if(B17=0,"...", IF(F17=0,today()-D17,F17-D17)) -> ... | J17: =IFERROR(__xludf.DUMMYFUNCTION("IF(B17=0,""..."",IF(E17=""CERRADA"",""-"",GOOGLEFINANCE(""BCBA:"" & B17)))"),"...") -> ... | K17: =IF(B17=0,"...",H17*I17) -> ... | L17: =IF(B17=0,"...",K17/VLOOKUP($D17,CCL!$A$12:$B$828,2,0)) -> ... | M17: =IF(B17=0,"...",IF(E17="CERRADA","Valor Venta",J17*(1-VLOOKUP($A$2,Config!$B$3:$C$22,2,FALSE)))) -> ... | N17: =IF(B17=0,"...",H17*M17) -> ... | O17: {=IF(B17=0,"...",IF(E17="ABIERTA",K17/CCL!$E$2,N17/ VLOOKUP(F17,{CCL!M:N;CCL!$P:$Q},2,FALSE)))} -> ... | P17: =IFERROR(__xludf.DUMMYFUNCTION("if(B17=0,""..."",GOOGLEFINANCE(B17,""changepct"")/100)"),"...") -> ... | Q17: =IFERROR(__xludf.DUMMYFUNCTION("IF(B17=0,""..."",IF(E17=""CERRADA"",""-"",GOOGLEFINANCE(B17,""change"")*H17))"),"...") -> ... | R17: =IF(B17=0,"...",O17/L17-1) -> ... | S17: =IF(B17=0,"...",N17-K17) -> ... | V17: =if(U17=0,"...",sumifs($H$2:$H$28,$B$2:$B$28,U17,$E$2:$E$28,"ABIERTA")) -> ... | W17: =if(U17=0,"",Y17/$AD$18) | X17: =if(V17=0,"...",if(U17=0,"...",sumifs($M$2:$M$28,$B$2:$B$28,U17,$E$2:$E$28,"ABIERTA")/V17)) -> ... | Y17: =if(U17=0,"...",sumifs($N$2:$N$28,$B$2:$B$28,U17,$E$2:$E$28,"ABIERTA")) -> ... | Z17: =if(V17=0,"...",if(U17=0,"...",AA17/(Y17-AA17))) -> ... | AA17: =if(V17=0,"...",if(U17=0,"...",sumifs($S$2:$S$28,$B$2:$B$28,U17,$E$2:$E$28,"ABIERTA"))) -> ...
C18: =IFERROR(__xludf.DUMMYFUNCTION("if(B18=0,""..."", sparkline(query(GOOGLEFINANCE(B18,""price"",today()-$AE$27,today()),""select Col2"",0),{""charttype"",$AE$26}))"),"...") -> ... | G18: =if(B18=0,"...", IF(F18=0,today()-D18,F18-D18)) -> ... | J18: =IFERROR(__xludf.DUMMYFUNCTION("IF(B18=0,""..."",IF(E18=""CERRADA"",""-"",GOOGLEFINANCE(B18)))"),"...") -> ... | K18: =IF(B18=0,"...",H18*I18) -> ... | L18: =IF(B18=0,"...",K18/VLOOKUP($D18,CCL!$A$12:$B$828,2,0)) -> ... | M18: =IF(B18=0,"...",IF(E18="CERRADA","Valor Venta",J18*(1-VLOOKUP($A$2,Config!$B$3:$C$22,2,FALSE)))) -> ... | N18: =IF(B18=0,"...",H18*M18) -> ... | O18: {=IF(B18=0,"...",IF(E18="ABIERTA",K18/CCL!$E$2,N18/ VLOOKUP(F18,{CCL!M:N;CCL!$P:$Q},2,FALSE)))} -> ... | P18: =IFERROR(__xludf.DUMMYFUNCTION("if(B18=0,""..."",GOOGLEFINANCE(B18,""changepct"")/100)"),"...") -> ... | Q18: =IFERROR(__xludf.DUMMYFUNCTION("IF(B18=0,""..."",IF(E18=""CERRADA"",""-"",GOOGLEFINANCE(B18,""change"")*H18))"),"...") -> ... | R18: =IF(B18=0,"...",O18/L18-1) -> ... | S18: =IF(B18=0,"...",N18-K18) -> ... | V18: =if(U18=0,"...",sumifs($H$2:$H$28,$B$2:$B$28,U18,$E$2:$E$28,"ABIERTA")) -> ... | W18: =if(U18=0,"",Y18/$AD$18) | X18: =if(V18=0,"...",if(U18=0,"...",sumifs($M$2:$M$28,$B$2:$B$28,U18,$E$2:$E$28,"ABIERTA")/V18)) -> ... | Y18: =if(U18=0,"...",sumifs($N$2:$N$28,$B$2:$B$28,U18,$E$2:$E$28,"ABIERTA")) -> ... | Z18: =if(V18=0,"...",if(U18=0,"...",AA18/(Y18-AA18))) -> ... | AA18: =if(V18=0,"...",if(U18=0,"...",sumifs($S$2:$S$28,$B$2:$B$28,U18,$E$2:$E$28,"ABIERTA"))) -> ... | AC18: Total Abierto | AD18: =sumifs(N2:N27,E2:E27,"ABIERTA") -> 1255400.2 | AE18: Total Acumulado | AF18: =sum(N2:N27) -> 2111127.2
C19: =IFERROR(__xludf.DUMMYFUNCTION("if(B19=0,""..."", sparkline(query(GOOGLEFINANCE(B19,""price"",today()-$AE$27,today()),""select Col2"",0),{""charttype"",$AE$26}))"),"...") -> ... | G19: =if(B19=0,"...", IF(F19=0,today()-D19,F19-D19)) -> ... | J19: =IFERROR(__xludf.DUMMYFUNCTION("IF(B19=0,""..."",IF(E19=""CERRADA"",""-"",GOOGLEFINANCE(B19)))"),"...") -> ... | K19: =IF(B19=0,"...",H19*I19) -> ... | L19: =IF(B19=0,"...",K19/VLOOKUP($D19,CCL!$A$12:$B$828,2,0)) -> ... | M19: =IF(B19=0,"...",IF(E19="CERRADA","Valor Venta",J19*(1-VLOOKUP($A$2,Config!$B$3:$C$22,2,FALSE)))) -> ... | N19: =IF(B19=0,"...",H19*M19) -> ... | O19: {=IF(B19=0,"...",IF(E19="ABIERTA",K19/CCL!$E$2,N19/ VLOOKUP(F19,{CCL!M:N;CCL!$P:$Q},2,FALSE)))} -> ... | P19: =IFERROR(__xludf.DUMMYFUNCTION("if(B19=0,""..."",GOOGLEFINANCE(B19,""changepct"")/100)"),"...") -> ... | Q19: =IFERROR(__xludf.DUMMYFUNCTION("IF(B19=0,""..."",IF(E19=""CERRADA"",""-"",GOOGLEFINANCE(B19,""change"")*H19))"),"...") -> ... | R19: =IF(B19=0,"...",O19/L19-1) -> ... | S19: =IF(B19=0,"...",N19-K19) -> ... | V19: =if(U19=0,"...",sumifs($H$2:$H$28,$B$2:$B$28,U19,$E$2:$E$28,"ABIERTA")) -> ... | W19: =if(U19=0,"",Y19/$AD$18) | X19: =if(V19=0,"...",if(U19=0,"...",sumifs($M$2:$M$28,$B$2:$B$28,U19,$E$2:$E$28,"ABIERTA")/V19)) -> ... | Y19: =if(U19=0,"...",sumifs($N$2:$N$28,$B$2:$B$28,U19,$E$2:$E$28,"ABIERTA")) -> ... | Z19: =if(V19=0,"...",if(U19=0,"...",AA19/(Y19-AA19))) -> ... | AA19: =if(V19=0,"...",if(U19=0,"...",sumifs($S$2:$S$28,$B$2:$B$28,U19,$E$2:$E$28,"ABIERTA"))) -> ...
C20: =IFERROR(__xludf.DUMMYFUNCTION("if(B20=0,""..."", sparkline(query(GOOGLEFINANCE(B20,""price"",today()-$AE$27,today()),""select Col2"",0),{""charttype"",$AE$26}))"),"...") -> ... | G20: =if(B20=0,"...", IF(F20=0,today()-D20,F20-D20)) -> ... | J20: =IFERROR(__xludf.DUMMYFUNCTION("IF(B20=0,""..."",IF(E20=""CERRADA"",""-"",GOOGLEFINANCE(""BCBA:"" & B20)))"),"...") -> ... | K20: =IF(B20=0,"...",H20*I20) -> ... | L20: =IF(B20=0,"...",K20/VLOOKUP($D20,CCL!$A$12:$B$828,2,0)) -> ... | M20: =IF(B20=0,"...",IF(E20="CERRADA","Valor Venta",J20*(1-VLOOKUP($A$2,Config!$B$3:$C$22,2,FALSE)))) -> ... | N20: =IF(B20=0,"...",H20*M20) -> ... | O20: {=IF(B20=0,"...",IF(E20="ABIERTA",K20/CCL!$E$2,N20/ VLOOKUP(F20,{CCL!M:N;CCL!$P:$Q},2,FALSE)))} -> ... | P20: =IFERROR(__xludf.DUMMYFUNCTION("if(B20=0,""..."",GOOGLEFINANCE(B20,""changepct"")/100)"),"...") -> ... | Q20: =IFERROR(__xludf.DUMMYFUNCTION("IF(B20=0,""..."",IF(E20=""CERRADA"",""-"",GOOGLEFINANCE(B20,""change"")*H20))"),"...") -> ... | R20: =IF(B20=0,"...",O20/L20-1) -> ... | S20: =IF(B20=0,"...",N20-K20) -> ... | V20: =if(U20=0,"...",sumifs($H$2:$H$28,$B$2:$B$28,U20,$E$2:$E$28,"ABIERTA")) -> ... | W20: =if(U20=0,"",Y20/$AD$18) | X20: =if(V20=0,"...",if(U20=0,"...",sumifs($M$2:$M$28,$B$2:$B$28,U20,$E$2:$E$28,"ABIERTA")/V20)) -> ... | Y20: =if(U20=0,"...",sumifs($N$2:$N$28,$B$2:$B$28,U20,$E$2:$E$28,"ABIERTA")) -> ... | Z20: =if(V20=0,"...",if(U20=0,"...",AA20/(Y20-AA20))) -> ... | AA20: =if(V20=0,"...",if(U20=0,"...",sumifs($S$2:$S$28,$B$2:$B$28,U20,$E$2:$E$28,"ABIERTA"))) -> ... | AC20: Ganancia Abierto | AD20: =sumifs(S2:S27,E2:E27,"ABIERTA") -> 64.10124 | AE20: Ganancia Acumulada | AF20: =sum(S2:S27) -> #N/A
C21: =IFERROR(__xludf.DUMMYFUNCTION("if(B21=0,""..."", sparkline(query(GOOGLEFINANCE(B21,""price"",today()-$AE$27,today()),""select Col2"",0),{""charttype"",$AE$26}))"),"...") -> ... | G21: =if(B21=0,"...", IF(F21=0,today()-D21,F21-D21)) -> ... | J21: =IFERROR(__xludf.DUMMYFUNCTION("IF(B21=0,""..."",IF(E21=""CERRADA"",""-"",GOOGLEFINANCE(B21)))"),"...") -> ... | K21: =IF(B21=0,"...",H21*I21) -> ... | L21: =IF(B21=0,"...",K21/VLOOKUP($D21,CCL!$A$12:$B$828,2,0)) -> ... | M21: =IF(B21=0,"...",IF(E21="CERRADA","Valor Venta",J21*(1-VLOOKUP($A$2,Config!$B$3:$C$22,2,FALSE)))) -> ... | N21: =IF(B21=0,"...",H21*M21) -> ... | O21: {=IF(B21=0,"...",IF(E21="ABIERTA",K21/CCL!$E$2,N21/ VLOOKUP(F21,{CCL!M:N;CCL!$P:$Q},2,FALSE)))} -> ... | P21: =IFERROR(__xludf.DUMMYFUNCTION("if(B21=0,""..."",GOOGLEFINANCE(B21,""changepct"")/100)"),"...") -> ... | Q21: =IFERROR(__xludf.DUMMYFUNCTION("IF(B21=0,""..."",IF(E21=""CERRADA"",""-"",GOOGLEFINANCE(B21,""change"")*H21))"),"...") -> ... | R21: =IF(B21=0,"...",O21/L21-1) -> ... | S21: =IF(B21=0,"...",N21-K21) -> ... | V21: =if(U21=0,"...",sumifs($H$2:$H$28,$B$2:$B$28,U21,$E$2:$E$28,"ABIERTA")) -> ... | W21: =if(U21=0,"",Y21/$AD$18) | X21: =if(V21=0,"...",if(U21=0,"...",sumifs($M$2:$M$28,$B$2:$B$28,U21,$E$2:$E$28,"ABIERTA")/V21)) -> ... | Y21: =if(U21=0,"...",sumifs($N$2:$N$28,$B$2:$B$28,U21,$E$2:$E$28,"ABIERTA")) -> ... | Z21: =if(V21=0,"...",if(U21=0,"...",AA21/(Y21-AA21))) -> ... | AA21: =if(V21=0,"...",if(U21=0,"...",sumifs($S$2:$S$28,$B$2:$B$28,U21,$E$2:$E$28,"ABIERTA"))) -> ...
C22: =IFERROR(__xludf.DUMMYFUNCTION("if(B22=0,""..."", sparkline(query(GOOGLEFINANCE(B22,""price"",today()-$AE$27,today()),""select Col2"",0),{""charttype"",$AE$26}))"),"...") -> ... | G22: =if(B22=0,"...", IF(F22=0,today()-D22,F22-D22)) -> ... | J22: =IFERROR(__xludf.DUMMYFUNCTION("IF(B22=0,""..."",IF(E22=""CERRADA"",""-"",GOOGLEFINANCE(B22)))"),"...") -> ... | K22: =IF(B22=0,"...",H22*I22) -> ... | L22: =IF(B22=0,"...",K22/VLOOKUP($D22,CCL!$A$12:$B$828,2,0)) -> ... | M22: =IF(B22=0,"...",IF(E22="CERRADA","Valor Venta",J22*(1-VLOOKUP($A$2,Config!$B$3:$C$22,2,FALSE)))) -> ... | N22: =IF(B22=0,"...",H22*M22) -> ... | O22: {=IF(B22=0,"...",IF(E22="ABIERTA",K22/CCL!$E$2,N22/ VLOOKUP(F22,{CCL!M:N;CCL!$P:$Q},2,FALSE)))} -> ... | P22: =IFERROR(__xludf.DUMMYFUNCTION("if(B22=0,""..."",GOOGLEFINANCE(B22,""changepct"")/100)"),"...") -> ... | Q22: =IFERROR(__xludf.DUMMYFUNCTION("IF(B22=0,""..."",IF(E22=""CERRADA"",""-"",GOOGLEFINANCE(B22,""change"")*H22))"),"...") -> ... | R22: =IF(B22=0,"...",O22/L22-1) -> ... | S22: =IF(B22=0,"...",N22-K22) -> ... | V22: =if(U22=0,"...",sumifs($H$2:$H$28,$B$2:$B$28,U22,$E$2:$E$28,"ABIERTA")) -> ... | W22: =if(U22=0,"",Y22/$AD$18) | X22: =if(V22=0,"...",if(U22=0,"...",sumifs($M$2:$M$28,$B$2:$B$28,U22,$E$2:$E$28,"ABIERTA")/V22)) -> ... | Y22: =if(U22=0,"...",sumifs($N$2:$N$28,$B$2:$B$28,U22,$E$2:$E$28,"ABIERTA")) -> ... | Z22: =if(V22=0,"...",if(U22=0,"...",AA22/(Y22-AA22))) -> ... | AA22: =if(V22=0,"...",if(U22=0,"...",sumifs($S$2:$S$28,$B$2:$B$28,U22,$E$2:$E$28,"ABIERTA"))) -> ... | AC22: (%) | AD22: =AD20/(AD18-AD20) -> 5.1063008e-05 | AE22: (%) | AF22: =AF20/(AF18-AF20) -> #N/A
C23: =IFERROR(__xludf.DUMMYFUNCTION("if(B23=0,""..."", sparkline(query(GOOGLEFINANCE(B23,""price"",today()-$AE$27,today()),""select Col2"",0),{""charttype"",$AE$26}))"),"...") -> ... | G23: =if(B23=0,"...", IF(F23=0,today()-D23,F23-D23)) -> ... | J23: =IFERROR(__xludf.DUMMYFUNCTION("IF(B23=0,""..."",IF(E23=""CERRADA"",""-"",GOOGLEFINANCE(""BCBA:"" & B23)))"),"...") -> ... | K23: =IF(B23=0,"...",H23*I23) -> ... | L23: =IF(B23=0,"...",K23/VLOOKUP($D23,CCL!$A$12:$B$828,2,0)) -> ... | M23: =IF(B23=0,"...",IF(E23="CERRADA","Valor Venta",J23*(1-VLOOKUP($A$2,Config!$B$3:$C$22,2,FALSE)))) -> ... | N23: =IF(B23=0,"...",H23*M23) -> ... | O23: {=IF(B23=0,"...",IF(E23="ABIERTA",K23/CCL!$E$2,N23/ VLOOKUP(F23,{CCL!M:N;CCL!$P:$Q},2,FALSE)))} -> ... | P23: =IFERROR(__xludf.DUMMYFUNCTION("if(B23=0,""..."",GOOGLEFINANCE(B23,""changepct"")/100)"),"...") -> ... | Q23: =IFERROR(__xludf.DUMMYFUNCTION("IF(B23=0,""..."",IF(E23=""CERRADA"",""-"",GOOGLEFINANCE(B23,""change"")*H23))"),"...") -> ... | R23: =IF(B23=0,"...",O23/L23-1) -> ... | S23: =IF(B23=0,"...",N23-K23) -> ... | V23: =if(U23=0,"...",sumifs($H$2:$H$28,$B$2:$B$28,U23,$E$2:$E$28,"ABIERTA")) -> ... | W23: =if(U23=0,"",Y23/$AD$18) | X23: =if(V23=0,"...",if(U23=0,"...",sumifs($M$2:$M$28,$B$2:$B$28,U23,$E$2:$E$28,"ABIERTA")/V23)) -> ... | Y23: =if(U23=0,"...",sumifs($N$2:$N$28,$B$2:$B$28,U23,$E$2:$E$28,"ABIERTA")) -> ... | Z23: =if(V23=0,"...",if(U23=0,"...",AA23/(Y23-AA23))) -> ... | AA23: =if(V23=0,"...",if(U23=0,"...",sumifs($S$2:$S$28,$B$2:$B$28,U23,$E$2:$E$28,"ABIERTA"))) -> ...
C24: =IFERROR(__xludf.DUMMYFUNCTION("if(B24=0,""..."", sparkline(query(GOOGLEFINANCE(B24,""price"",today()-$AE$27,today()),""select Col2"",0),{""charttype"",$AE$26}))"),"...") -> ... | G24: =if(B24=0,"...", IF(F24=0,today()-D24,F24-D24)) -> ... | J24: =IFERROR(__xludf.DUMMYFUNCTION("IF(B24=0,""..."",IF(E24=""CERRADA"",""-"",GOOGLEFINANCE(B24)))"),"...") -> ... | K24: =IF(B24=0,"...",H24*I24) -> ... | L24: =IF(B24=0,"...",K24/VLOOKUP($D24,CCL!$A$12:$B$828,2,0)) -> ... | M24: =IF(B24=0,"...",IF(E24="CERRADA","Valor Venta",J24*(1-VLOOKUP($A$2,Config!$B$3:$C$22,2,FALSE)))) -> ... | N24: =IF(B24=0,"...",H24*M24) -> ... | O24: {=IF(B24=0,"...",IF(E24="ABIERTA",K24/CCL!$E$2,N24/ VLOOKUP(F24,{CCL!M:N;CCL!$P:$Q},2,FALSE)))} -> ... | P24: =IFERROR(__xludf.DUMMYFUNCTION("if(B24=0,""..."",GOOGLEFINANCE(B24,""changepct"")/100)"),"...") -> ... | Q24: =IFERROR(__xludf.DUMMYFUNCTION("IF(B24=0,""..."",IF(E24=""CERRADA"",""-"",GOOGLEFINANCE(B24,""change"")*H24))"),"...") -> ... | R24: =IF(B24=0,"...",O24/L24-1) -> ... | S24: =IF(B24=0,"...",N24-K24) -> ... | V24: =if(U24=0,"...",sumifs($H$2:$H$28,$B$2:$B$28,U24,$E$2:$E$28,"ABIERTA")) -> ... | W24: =if(U24=0,"",Y24/$AD$18) | X24: =if(V24=0,"...",if(U24=0,"...",sumifs($M$2:$M$28,$B$2:$B$28,U24,$E$2:$E$28,"ABIERTA")/V24)) -> ... | Y24: =if(U24=0,"...",sumifs($N$2:$N$28,$B$2:$B$28,U24,$E$2:$E$28,"ABIERTA")) -> ... | Z24: =if(V24=0,"...",if(U24=0,"...",AA24/(Y24-AA24))) -> ... | AA24: =if(V24=0,"...",if(U24=0,"...",sumifs($S$2:$S$28,$B$2:$B$28,U24,$E$2:$E$28,"ABIERTA"))) -> ...
C25: =IFERROR(__xludf.DUMMYFUNCTION("if(B25=0,""..."", sparkline(query(GOOGLEFINANCE(B25,""price"",today()-$AE$27,today()),""select Col2"",0),{""charttype"",$AE$26}))"),"...") -> ... | G25: =if(B25=0,"...", IF(F25=0,today()-D25,F25-D25)) -> ... | J25: =IFERROR(__xludf.DUMMYFUNCTION("IF(B25=0,""..."",IF(E25=""CERRADA"",""-"",GOOGLEFINANCE(""BCBA:"" & B25)))"),"...") -> ... | K25: =IF(B25=0,"...",H25*I25) -> ... | L25: =IF(B25=0,"...",K25/VLOOKUP($D25,CCL!$A$12:$B$828,2,0)) -> ... | M25: =IF(B25=0,"...",IF(E25="CERRADA","Valor Venta",J25*(1-VLOOKUP($A$2,Config!$B$3:$C$22,2,FALSE)))) -> ... | N25: =IF(B25=0,"...",H25*M25) -> ... | O25: {=IF(B25=0,"...",IF(E25="ABIERTA",K25/CCL!$E$2,N25/ VLOOKUP(F25,{CCL!M:N;CCL!$P:$Q},2,FALSE)))} -> ... | P25: =IFERROR(__xludf.DUMMYFUNCTION("if(B25=0,""..."",GOOGLEFINANCE(B25,""changepct"")/100)"),"...") -> ... | Q25: =IFERROR(__xludf.DUMMYFUNCTION("IF(B25=0,""..."",IF(E25=""CERRADA"",""-"",GOOGLEFINANCE(B25,""change"")*H25))"),"...") -> ... | R25: =IF(B25=0,"...",O25/L25-1) -> ... | S25: =IF(B25=0,"...",N25-K25) -> ... | V25: =if(U25=0,"...",sumifs($H$2:$H$28,$B$2:$B$28,U25,$E$2:$E$28,"ABIERTA")) -> ... | W25: =if(U25=0,"",Y25/$AD$18) | X25: =if(V25=0,"...",if(U25=0,"...",sumifs($M$2:$M$28,$B$2:$B$28,U25,$E$2:$E$28,"ABIERTA")/V25)) -> ... | Y25: =if(U25=0,"...",sumifs($N$2:$N$28,$B$2:$B$28,U25,$E$2:$E$28,"ABIERTA")) -> ... | Z25: =if(V25=0,"...",if(U25=0,"...",AA25/(Y25-AA25))) -> ... | AA25: =if(V25=0,"...",if(U25=0,"...",sumifs($S$2:$S$28,$B$2:$B$28,U25,$E$2:$E$28,"ABIERTA"))) -> ...
C26: =IFERROR(__xludf.DUMMYFUNCTION("if(B26=0,""..."", sparkline(query(GOOGLEFINANCE(B26,""price"",today()-$AE$27,today()),""select Col2"",0),{""charttype"",$AE$26}))"),"...") -> ... | G26: =if(B26=0,"...", IF(F26=0,today()-D26,F26-D26)) -> ... | J26: =IFERROR(__xludf.DUMMYFUNCTION("IF(B26=0,""..."",IF(E26=""CERRADA"",""-"",GOOGLEFINANCE(B26)))"),"...") -> ... | K26: =IF(B26=0,"...",H26*I26) -> ... | L26: =IF(B26=0,"...",K26/VLOOKUP($D26,CCL!$A$12:$B$828,2,0)) -> ... | M26: =IF(B26=0,"...",IF(E26="CERRADA","Valor Venta",J26*(1-VLOOKUP($A$2,Config!$B$3:$C$22,2,FALSE)))) -> ... | N26: =IF(B26=0,"...",H26*M26) -> ... | O26: {=IF(B26=0,"...",IF(E26="ABIERTA",K26/CCL!$E$2,N26/ VLOOKUP(F26,{CCL!M:N;CCL!$P:$Q},2,FALSE)))} -> ... | P26: =IFERROR(__xludf.DUMMYFUNCTION("if(B26=0,""..."",GOOGLEFINANCE(B26,""changepct"")/100)"),"...") -> ... | Q26: =IFERROR(__xludf.DUMMYFUNCTION("IF(B26=0,""..."",IF(E26=""CERRADA"",""-"",GOOGLEFINANCE(B26,""change"")*H26))"),"...") -> ... | R26: =IF(B26=0,"...",O26/L26-1) -> ... | S26: =IF(B26=0,"...",N26-K26) -> ... | V26: =if(U26=0,"...",sumifs($H$2:$H$28,$B$2:$B$28,U26,$E$2:$E$28,"ABIERTA")) -> ... | W26: =if(U26=0,"",Y26/$AD$18) | X26: =if(V26=0,"...",if(U26=0,"...",sumifs($M$2:$M$28,$B$2:$B$28,U26,$E$2:$E$28,"ABIERTA")/V26)) -> ... | Y26: =if(U26=0,"...",sumifs($N$2:$N$28,$B$2:$B$28,U26,$E$2:$E$28,"ABIERTA")) -> ... | Z26: =if(V26=0,"...",if(U26=0,"...",AA26/(Y26-AA26))) -> ... | AA26: =if(V26=0,"...",if(U26=0,"...",sumifs($S$2:$S$28,$B$2:$B$28,U26,$E$2:$E$28,"ABIERTA"))) -> ... | AC26: Config Gráficas | AD26: Tipo | AE26: column
C27: =IFERROR(__xludf.DUMMYFUNCTION("if(B27=0,""..."", sparkline(query(GOOGLEFINANCE(B27,""price"",today()-$AE$27,today()),""select Col2"",0),{""charttype"",$AE$26}))"),"...") -> ... | G27: =if(B27=0,"...", IF(F27=0,today()-D27,F27-D27)) -> ... | J27: =IFERROR(__xludf.DUMMYFUNCTION("IF(B27=0,""..."",IF(E27=""CERRADA"",""-"",GOOGLEFINANCE(B27)))"),"...") -> ... | K27: =IF(B27=0,"...",H27*I27) -> ... | L27: =IF(B27=0,"...",K27/VLOOKUP($D27,CCL!$A$12:$B$828,2,0)) -> ... | M27: =IF(B27=0,"...",IF(E27="CERRADA","Valor Venta",J27*(1-VLOOKUP($A$2,Config!$B$3:$C$22,2,FALSE)))) -> ... | N27: =IF(B27=0,"...",H27*M27) -> ... | O27: {=IF(B27=0,"...",IF(E27="ABIERTA",K27/CCL!$E$2,N27/ VLOOKUP(F27,{CCL!M:N;CCL!$P:$Q},2,FALSE)))} -> ... | P27: =IFERROR(__xludf.DUMMYFUNCTION("if(B27=0,""..."",GOOGLEFINANCE(B27,""changepct"")/100)"),"...") -> ... | Q27: =IFERROR(__xludf.DUMMYFUNCTION("IF(B27=0,""..."",IF(E27=""CERRADA"",""-"",GOOGLEFINANCE(B27,""change"")*H27))"),"...") -> ... | R27: =IF(B27=0,"...",O27/L27-1) -> ... | S27: =IF(B27=0,"...",N27-K27) -> ... | V27: =if(U27=0,"...",sumifs($H$2:$H$28,$B$2:$B$28,U27,$E$2:$E$28,"ABIERTA")) -> ... | W27: =if(U27=0,"",Y27/$AD$18) | X27: =if(V27=0,"...",if(U27=0,"...",sumifs($M$2:$M$28,$B$2:$B$28,U27,$E$2:$E$28,"ABIERTA")/V27)) -> ... | Y27: =if(U27=0,"...",sumifs($N$2:$N$28,$B$2:$B$28,U27,$E$2:$E$28,"ABIERTA")) -> ... | Z27: =if(V27=0,"...",if(U27=0,"...",AA27/(Y27-AA27))) -> ... | AA27: =if(V27=0,"...",if(U27=0,"...",sumifs($S$2:$S$28,$B$2:$B$28,U27,$E$2:$E$28,"ABIERTA"))) -> ... | AD27: Días | AE27: 30

Sheet Cartera corto plazo
A1: ID | B1: Ticker | C1: Gráfica | D1: Apertura | E1: Estado | F1: Cierre | G1: Dias | H1: Unidades | I1: Valor Compra ARS | J1: Total Compra | K1: Valor Compra USD | L1: Valor Actual ARS | M1: Valor Venta ARS | N1: Total Venta ARS | O1: Gan Dia (%) | P1: Gan Dia | Q1: Ganancias ARS (%) | R1: Ganancias Bruta | S1: Ganancia USD CCL (%) | T1: Ganancia USD CCL | V1: Ticker | W1: Unidades | X1: % Cartera | Y1: PPC | Z1: Total (Abierto) | AA1: Gan ARS (%) | AB1: Gana Tot Ars | AC1: Tot Invertido USD | AD1: Gan USD (%) | AE1: Gana Tot USD
A2: IOL | B2: MSFT | C2: =IFERROR(__xludf.DUMMYFUNCTION("if(B2=0,""..."", sparkline(query(GOOGLEFINANCE(""BCBA:""&B2,""price"",today()-$AI$36,today()),""select Col2"",0),{""charttype"",$AI$35}))"),"") | D2: 45663 | E2: ABIERTA | G2: =if(B2=0,"...", IF(F2=0,today()-D2,F2-D2)) -> 454 | H2: 15 | I2: 17000 | J2: =if(B2=0,"...",H2*I2) -> 255000 | K2: {=IF(B2=0,"...",J2/VLOOKUP(D2,{CCL!M:N;CCL!$P:$Q},2,FALSE))} -> 214.81825 | L2: =IFERROR(__xludf.DUMMYFUNCTION("if(B2=0,""..."",if(E2=""CERRADA"",""Valor Venta"", GOOGLEFINANCE(""BCBA:""&B2)))"),18330.0) -> 18330 | M2: =if(B2=0,"...",L2*(1-VLOOKUP(A2,Config!$B$3:$C$22,2,FALSE))) -> 18201.69 | N2: =IF(B2=0,"...",H2*M2) -> 273025.35 | O2: =IFERROR(__xludf.DUMMYFUNCTION("if(B2=0,""..."",GOOGLEFINANCE(B2,""changepct"")/100)"),0.0111) -> 0.0111 | P2: =IFERROR(__xludf.DUMMYFUNCTION("if(B2=0,""..."",GOOGLEFINANCE(B2,""change"")*H2)"),61.349999999999994) -> 61.35 | Q2: =if(B2=0,"...",N2/J2-1) -> 0.070687647 | R2: =if(B2=0,"...",N2-J2) -> 18025.35 | S2: {=IF(B2=0,"...",(N2/IF(E2="ABIERTA",CCL!$E$2,VLOOKUP(F2,{CCL!M:N;CCL!$P:$Q},2,FALSE))/(J2/VLOOKUP(D2,{CCL!M:N;CCL!$P:$Q},2,FALSE))-1))} -> -0.13976123 | T2: {=IF(B2=0,"...",(N2/IF(E2="ABIERTA",CCL!$E$2,VLOOKUP(F2,{CCL!M:N;CCL!$P:$Q},2,FALSE))-K2))} -> -30.023262 | V2: =IFERROR(__xludf.DUMMYFUNCTION("Unique(Filter(B2:B37,E2:E37=""ABIERTA""))"),"MSFT") -> MSFT | W2: =if(V2=0,"...",sumifs($H$2:$H$37,$B$2:$B$37,V2,$E$2:$E$37,"ABIERTA")) -> 15 | X2: =if(V2=0,"",Z2/$AH$19) -> 0.054914752 | Y2: =if(W2=0,"...",if(V2=0,"...",sumifs($J$2:$J$37,$B$2:$B$37,V2,$E$2:$E$37,"ABIERTA")/W2)) -> 17000 | Z2: =if(V2=0,"...",sumifs($N$2:$N$37,$B$2:$B$37,V2,$E$2:$E$37,"ABIERTA")) -> 273025.35 | AA2: =if(W2=0,"...",if(V2=0,"...",AB2/(Z2-AB2))) -> 0.070687647 | AB2: =if(W2=0,"...",if(V2=0,"...",sumifs($R$2:$R$37,$B$2:$B$37,V2,$E$2:$E$37,"ABIERTA"))) -> 18025.35 | AC2: =IF(W2=0,"...",IF(V2=0,"...",SUMIFS($K$2:$K$37,$B$2:$B$37,V2,$E$2:$E$37,"ABIERTA"))) -> 214.81825 | AD2: =IF(V2=0,"...",AE2/(AC2+AE2)) -> -0.16246795 | AE2: =IF(W2=0,"...",if(V2=0,"...",sumifs($T$2:$T$37,$B$2:$B$37,V2,$E$2:$E$37,"ABIERTA"))) -> -30.023262
A3: IOL | B3: EWZ | C3: =IFERROR(__xludf.DUMMYFUNCTION("if(B3=0,""..."", sparkline(query(GOOGLEFINANCE(""BCBA:""&B3,""price"",today()-$AI$36,today()),""select Col2"",0),{""charttype"",$AI$35}))"),"") | D3: 45734 | E3: ABIERTA | G3: =if(B3=0,"...", IF(F3=0,today()-D3,F3-D3)) -> 383 | H3: 7 | I3: 16825 | J3: =if(B3=0,"...",H3*I3) -> 117775 | K3: {=IF(B3=0,"...",J3/VLOOKUP(D3,{CCL!M:N;CCL!$P:$Q},2,FALSE))} -> 90.665199 | L3: =IFERROR(__xludf.DUMMYFUNCTION("if(B3=0,""..."",if(E3=""CERRADA"",""Valor Venta"", GOOGLEFINANCE(""BCBA:""&B3)))"),28620.0) -> 28620 | M3: =if(B3=0,"...",L3*(1-VLOOKUP(A3,Config!$B$3:$C$22,2,FALSE))) -> 28419.66 | N3: =IF(B3=0,"...",H3*M3) -> 198937.62 | O3: =IFERROR(__xludf.DUMMYFUNCTION("if(B3=0,""..."",GOOGLEFINANCE(B3,""changepct"")/100)"),-5.0E-4) -> -0.0005 | P3: =IFERROR(__xludf.DUMMYFUNCTION("if(B3=0,""..."",GOOGLEFINANCE(B3,""change"")*H3)"),-0.14) -> -0.14 | Q3: =if(B3=0,"...",N3/J3-1) -> 0.68913284 | R3: =if(B3=0,"...",N3-J3) -> 81162.62 | S3: {=IF(B3=0,"...",(N3/IF(E3="ABIERTA",CCL!$E$2,VLOOKUP(F3,{CCL!M:N;CCL!$P:$Q},2,FALSE))/(J3/VLOOKUP(D3,{CCL!M:N;CCL!$P:$Q},2,FALSE))-1))} -> 0.4851267 | T3: {=IF(B3=0,"...",(N3/IF(E3="ABIERTA",CCL!$E$2,VLOOKUP(F3,{CCL!M:N;CCL!$P:$Q},2,FALSE))-K3))} -> 43.984109 | V3: =IFERROR(__xludf.DUMMYFUNCTION("""COMPUTED_VALUE"""),"EWZ") -> EWZ | W3: =if(V3=0,"...",sumifs($H$2:$H$37,$B$2:$B$37,V3,$E$2:$E$37,"ABIERTA")) -> 7 | X3: =if(V3=0,"",Z3/$AH$19) -> 0.040013171 | Y3: =if(W3=0,"...",if(V3=0,"...",sumifs($J$2:$J$37,$B$2:$B$37,V3,$E$2:$E$37,"ABIERTA")/W3)) -> 16825 | Z3: =if(V3=0,"...",sumifs($N$2:$N$37,$B$2:$B$37,V3,$E$2:$E$37,"ABIERTA")) -> 198937.62 | AA3: =if(W3=0,"...",if(V3=0,"...",AB3/(Z3-AB3))) -> 0.68913284 | AB3: =if(W3=0,"...",if(V3=0,"...",sumifs($R$2:$R$37,$B$2:$B$37,V3,$E$2:$E$37,"ABIERTA"))) -> 81162.62 | AC3: =IF(W3=0,"...",IF(V3=0,"...",SUMIFS($K$2:$K$37,$B$2:$B$37,V3,$E$2:$E$37,"ABIERTA"))) -> 90.665199 | AD3: =IF(V3=0,"...",AE3/(AC3+AE3)) -> 0.32665678 | AE3: =IF(W3=0,"...",if(V3=0,"...",sumifs($T$2:$T$37,$B$2:$B$37,V3,$E$2:$E$37,"ABIERTA"))) -> 43.984109
A4: IOL | B4: SPY | C4: =IFERROR(__xludf.DUMMYFUNCTION("if(B4=0,""..."", sparkline(query(GOOGLEFINANCE(""BCBA:""&B4,""price"",today()-$AI$36,today()),""select Col2"",0),{""charttype"",$AI$35}))"),"") | D4: 45734 | E4: CERRADA | F4: 45735 | G4: =if(B4=0,"...", IF(F4=0,today()-D4,F4-D4)) -> 1 | H4: 3 | I4: 33575 | J4: =if(B4=0,"...",H4*I4) -> 100725 | K4: {=IF(B4=0,"...",J4/VLOOKUP(D4,{CCL!M:N;CCL!$P:$Q},2,FALSE))} -> 77.539819 | L4: 36375 | M4: =if(B4=0,"...",L4*(1-VLOOKUP(A4,Config!$B$3:$C$22,2,FALSE))) -> 36120.375 | N4: =IF(B4=0,"...",H4*M4) -> 108361.12 | O4: =IFERROR(__xludf.DUMMYFUNCTION("if(B4=0,""..."",GOOGLEFINANCE(B4,""changepct"")/100)"),9.0E-4) -> 0.0009 | P4: =IFERROR(__xludf.DUMMYFUNCTION("if(B4=0,""..."",GOOGLEFINANCE(B4,""change"")*H4)"),1.77) -> 1.77 | Q4: =if(B4=0,"...",N4/J4-1) -> 0.075811616 | R4: =if(B4=0,"...",N4-J4) -> 7636.125 | S4: {=IF(B4=0,"...",(N4/IF(E4="ABIERTA",CCL!$E$2,VLOOKUP(F4,{CCL!M:N;CCL!$P:$Q},2,FALSE))/(J4/VLOOKUP(D4,{CCL!M:N;CCL!$P:$Q},2,FALSE))-1))} -> 0.081765862 | T4: {=IF(B4=0,"...",(N4/IF(E4="ABIERTA",CCL!$E$2,VLOOKUP(F4,{CCL!M:N;CCL!$P:$Q},2,FALSE))-K4))} -> 6.3401102 | V4: =IFERROR(__xludf.DUMMYFUNCTION("""COMPUTED_VALUE"""),"JPM") -> JPM | W4: =if(V4=0,"...",sumifs($H$2:$H$37,$B$2:$B$37,V4,$E$2:$E$37,"ABIERTA")) -> 18 | X4: =if(V4=0,"",Z4/$AH$19) -> 0.10497615 | Y4: =if(W4=0,"...",if(V4=0,"...",sumifs($J$2:$J$37,$B$2:$B$37,V4,$E$2:$E$37,"ABIERTA")/W4)) -> 24083.333 | Z4: =if(V4=0,"...",sumifs($N$2:$N$37,$B$2:$B$37,V4,$E$2:$E$37,"ABIERTA")) -> 521920.8 | AA4: =if(W4=0,"...",if(V4=0,"...",AB4/(Z4-AB4))) -> 0.20396955 | AB4: =if(W4=0,"...",if(V4=0,"...",sumifs($R$2:$R$37,$B$2:$B$37,V4,$E$2:$E$37,"ABIERTA"))) -> 88420.8 | AC4: =IF(W4=0,"...",IF(V4=0,"...",SUMIFS($K$2:$K$37,$B$2:$B$37,V4,$E$2:$E$37,"ABIERTA"))) -> 336.63758 | AD4: =IF(V4=0,"...",AE4/(AC4+AE4)) -> 0.047048527 | AE4: =IF(W4=0,"...",if(V4=0,"...",sumifs($T$2:$T$37,$B$2:$B$37,V4,$E$2:$E$37,"ABIERTA"))) -> 16.620261
A5: IOL | B5: AMD | C5: =IFERROR(__xludf.DUMMYFUNCTION("if(B5=0,""..."", sparkline(query(GOOGLEFINANCE(""BCBA:""&B5,""price"",today()-$AI$36,today()),""select Col2"",0),{""charttype"",$AI$35}))"),"") | D5: 45805 | E5: CERRADA | F5: 45867 | G5: =if(B5=0,"...", IF(F5=0,today()-D5,F5-D5)) -> 62 | H5: 15 | I5: 13275 | J5: =if(B5=0,"...",H5*I5) -> 199125 | K5: {=IF(B5=0,"...",J5/VLOOKUP(D5,{CCL!M:N;CCL!$P:$Q},2,FALSE))} -> 169.4205 | L5: 23050 | M5: =if(B5=0,"...",L5*(1-VLOOKUP(A5,Config!$B$3:$C$22,2,FALSE))) -> 22888.65 | N5: =IF(B5=0,"...",H5*M5) -> 343329.75 | O5: =IFERROR(__xludf.DUMMYFUNCTION("if(B5=0,""..."",GOOGLEFINANCE(B5,""changepct"")/100)"),0.0347) -> 0.0347 | P5: =IFERROR(__xludf.DUMMYFUNCTION("if(B5=0,""..."",GOOGLEFINANCE(B5,""change"")*H5)"),109.35) -> 109.35 | Q5: =if(B5=0,"...",N5/J5-1) -> 0.72419209 | R5: =if(B5=0,"...",N5-J5) -> 144204.75 | S5: {=IF(B5=0,"...",(N5/IF(E5="ABIERTA",CCL!$E$2,VLOOKUP(F5,{CCL!M:N;CCL!$P:$Q},2,FALSE))/(J5/VLOOKUP(D5,{CCL!M:N;CCL!$P:$Q},2,FALSE))-1))} -> 0.57092612 | T5: {=IF(B5=0,"...",(N5/IF(E5="ABIERTA",CCL!$E$2,VLOOKUP(F5,{CCL!M:N;CCL!$P:$Q},2,FALSE))-K5))} -> 96.72659 | V5: =IFERROR(__xludf.DUMMYFUNCTION("""COMPUTED_VALUE"""),"META") -> META | W5: =if(V5=0,"...",sumifs($H$2:$H$37,$B$2:$B$37,V5,$E$2:$E$37,"ABIERTA")) -> 7 | X5: =if(V5=0,"",Z5/$AH$19) -> 0.050219186 | Y5: =if(W5=0,"...",if(V5=0,"...",sumifs($J$2:$J$37,$B$2:$B$37,V5,$E$2:$E$37,"ABIERTA")/W5)) -> 31650 | Z5: =if(V5=0,"...",sumifs($N$2:$N$37,$B$2:$B$37,V5,$E$2:$E$37,"ABIERTA")) -> 249679.92 | AA5: =if(W5=0,"...",if(V5=0,"...",AB5/(Z5-AB5))) -> 0.12696872 | AB5: =if(W5=0,"...",if(V5=0,"...",sumifs($R$2:$R$37,$B$2:$B$37,V5,$E$2:$E$37,"ABIERTA"))) -> 28129.92 | AC5: =IF(W5=0,"...",IF(V5=0,"...",SUMIFS($K$2:$K$37,$B$2:$B$37,V5,$E$2:$E$37,"ABIERTA"))) -> 188.50025 | AD5: =IF(V5=0,"...",AE5/(AC5+AE5)) -> -0.11542689 | AE5: =IF(W5=0,"...",if(V5=0,"...",sumifs($T$2:$T$37,$B$2:$B$37,V5,$E$2:$E$37,"ABIERTA"))) -> -19.506431
A6: IOL | B6: JPM | C6: =IFERROR(__xludf.DUMMYFUNCTION("if(B6=0,""..."", sparkline(query(GOOGLEFINANCE(""BCBA:""&B6,""price"",today()-$AI$36,today()),""select Col2"",0),{""charttype"",$AI$35}))"),"") | D6: 45805 | E6: ABIERTA | G6: =if(B6=0,"...", IF(F6=0,today()-D6,F6-D6)) -> 312 | H6: 11 | I6: 20700 | J6: =if(B6=0,"...",H6*I6) -> 227700 | K6: {=IF(B6=0,"...",J6/VLOOKUP(D6,{CCL!M:N;CCL!$P:$Q},2,FALSE))} -> 193.73282 | L6: =IFERROR(__xludf.DUMMYFUNCTION("if(B6=0,""..."",if(E6=""CERRADA"",""Valor Venta"", GOOGLEFINANCE(""BCBA:""&B6)))"),29200.0) -> 29200 | M6: =if(B6=0,"...",L6*(1-VLOOKUP(A6,Config!$B$3:$C$22,2,FALSE))) -> 28995.6 | N6: =IF(B6=0,"...",H6*M6) -> 318951.6 | O6: =IFERROR(__xludf.DUMMYFUNCTION("if(B6=0,""..."",GOOGLEFINANCE(B6,""changepct"")/100)"),-0.0026) -> -0.0026 | P6: =IFERROR(__xludf.DUMMYFUNCTION("if(B6=0,""..."",GOOGLEFINANCE(B6,""change"")*H6)"),-8.58) -> -8.58 | Q6: =if(B6=0,"...",N6/J6-1) -> 0.40075362 | R6: =if(B6=0,"...",N6-J6) -> 91251.6 | S6: {=IF(B6=0,"...",(N6/IF(E6="ABIERTA",CCL!$E$2,VLOOKUP(F6,{CCL!M:N;CCL!$P:$Q},2,FALSE))/(J6/VLOOKUP(D6,{CCL!M:N;CCL!$P:$Q},2,FALSE))-1))} -> 0.11431707 | T6: {=IF(B6=0,"...",(N6/IF(E6="ABIERTA",CCL!$E$2,VLOOKUP(F6,{CCL!M:N;CCL!$P:$Q},2,FALSE))-K6))} -> 22.146969 | V6: =IFERROR(__xludf.DUMMYFUNCTION("""COMPUTED_VALUE"""),"NVDA") -> NVDA | W6: =if(V6=0,"...",sumifs($H$2:$H$37,$B$2:$B$37,V6,$E$2:$E$37,"ABIERTA")) -> 35 | X6: =if(V6=0,"",Z6/$AH$19) -> 0.076265496 | Y6: =if(W6=0,"...",if(V6=0,"...",sumifs($J$2:$J$37,$B$2:$B$37,V6,$E$2:$E$37,"ABIERTA")/W6)) -> 6700 | Z6: =if(V6=0,"...",sumifs($N$2:$N$37,$B$2:$B$37,V6,$E$2:$E$37,"ABIERTA")) -> 379177.05 | AA6: =if(W6=0,"...",if(V6=0,"...",AB6/(Z6-AB6))) -> 0.6169597 | AB6: =if(W6=0,"...",if(V6=0,"...",sumifs($R$2:$R$37,$B$2:$B$37,V6,$E$2:$E$37,"ABIERTA"))) -> 144677.05 | AC6: =IF(W6=0,"...",IF(V6=0,"...",SUMIFS($K$2:$K$37,$B$2:$B$37,V6,$E$2:$E$37,"ABIERTA"))) -> 199.51843 | AD6: =IF(V6=0,"...",AE6/(AC6+AE6)) -> 0.22258346 | AE6: =IF(W6=0,"...",if(V6=0,"...",sumifs($T$2:$T$37,$B$2:$B$37,V6,$E$2:$E$37,"ABIERTA"))) -> 57.124465
A7: IOL | B7: GOOGL | C7: =IFERROR(__xludf.DUMMYFUNCTION("if(B7=0,""..."", sparkline(query(GOOGLEFINANCE(""BCBA:""&B7,""price"",today()-$AI$36,today()),""select Col2"",0),{""charttype"",$AI$35}))"),"") | D7: 45805 | E7: CERRADA | F7: 45918 | G7: =if(B7=0,"...", IF(F7=0,today()-D7,F7-D7)) -> 113 | H7: 42 | I7: 3505 | J7: =if(B7=0,"...",H7*I7) -> 147210 | K7: {=IF(B7=0,"...",J7/VLOOKUP(D7,{CCL!M:N;CCL!$P:$Q},2,FALSE))} -> 125.24993 | L7: 6565 | M7: =if(B7=0,"...",L7*(1-VLOOKUP(A7,Config!$B$3:$C$22,2,FALSE))) -> 6519.045 | N7: =IF(B7=0,"...",H7*M7) -> 273799.89 | O7: =IFERROR(__xludf.DUMMYFUNCTION("if(B7=0,""..."",GOOGLEFINANCE(B7,""changepct"")/100)"),-0.0054) -> -0.0054 | P7: =IFERROR(__xludf.DUMMYFUNCTION("if(B7=0,""..."",GOOGLEFINANCE(B7,""change"")*H7)"),-68.04) -> -68.04 | Q7: =if(B7=0,"...",N7/J7-1) -> 0.85992725 | R7: =if(B7=0,"...",N7-J7) -> 126589.89 | S7: {=IF(B7=0,"...",(N7/IF(E7="ABIERTA",CCL!$E$2,VLOOKUP(F7,{CCL!M:N;CCL!$P:$Q},2,FALSE))/(J7/VLOOKUP(D7,{CCL!M:N;CCL!$P:$Q},2,FALSE))-1))} -> 0.39762694 | T7: {=IF(B7=0,"...",(N7/IF(E7="ABIERTA",CCL!$E$2,VLOOKUP(F7,{CCL!M:N;CCL!$P:$Q},2,FALSE))-K7))} -> 49.802746 | V7: =IFERROR(__xludf.DUMMYFUNCTION("""COMPUTED_VALUE"""),"MELI") -> MELI | W7: =if(V7=0,"...",sumifs($H$2:$H$37,$B$2:$B$37,V7,$E$2:$E$37,"ABIERTA")) -> 88 | X7: =if(V7=0,"",Z7/$AH$19) -> 0.37524581 | Y7: =if(W7=0,"...",if(V7=0,"...",sumifs($J$2:$J$37,$B$2:$B$37,V7,$E$2:$E$37,"ABIERTA")/W7)) -> 27143.409 | Z7: =if(V7=0,"...",sumifs($N$2:$N$37,$B$2:$B$37,V7,$E$2:$E$37,"ABIERTA")) -> 1865648.4 | AA7: =if(W7=0,"...",if(V7=0,"...",AB7/(Z7-AB7))) -> -0.21894299 | AB7: =if(W7=0,"...",if(V7=0,"...",sumifs($R$2:$R$37,$B$2:$B$37,V7,$E$2:$E$37,"ABIERTA"))) -> -522971.6 | AC7: =IF(W7=0,"...",IF(V7=0,"...",SUMIFS($K$2:$K$37,$B$2:$B$37,V7,$E$2:$E$37,"ABIERTA"))) -> 1615.5194 | AD7: =IF(V7=0,"...",AE7/(AC7+AE7)) -> -0.27936706 | AE7: =IF(W7=0,"...",if(V7=0,"...",sumifs($T$2:$T$37,$B$2:$B$37,V7,$E$2:$E$37,"ABIERTA"))) -> -352.77045
A8: IOL | B8: META | C8: =IFERROR(__xludf.DUMMYFUNCTION("if(B8=0,""..."", sparkline(query(GOOGLEFINANCE(""BCBA:""&B8,""price"",today()-$AI$36,today()),""select Col2"",0),{""charttype"",$AI$35}))"),"") | D8: 45805 | E8: ABIERTA | G8: =if(B8=0,"...", IF(F8=0,today()-D8,F8-D8)) -> 312 | H8: 7 | I8: 31650 | J8: =if(B8=0,"...",H8*I8) -> 221550 | K8: {=IF(B8=0,"...",J8/VLOOKUP(D8,{CCL!M:N;CCL!$P:$Q},2,FALSE))} -> 188.50025 | L8: =IFERROR(__xludf.DUMMYFUNCTION("if(B8=0,""..."",if(E8=""CERRADA"",""Valor Venta"", GOOGLEFINANCE(""BCBA:""&B8)))"),35920.0) -> 35920 | M8: =if(B8=0,"...",L8*(1-VLOOKUP(A8,Config!$B$3:$C$22,2,FALSE))) -> 35668.56 | N8: =IF(B8=0,"...",H8*M8) -> 249679.92 | O8: =IFERROR(__xludf.DUMMYFUNCTION("if(B8=0,""..."",GOOGLEFINANCE(B8,""changepct"")/100)"),-0.008199999999999999) -> -0.0082 | P8: =IFERROR(__xludf.DUMMYFUNCTION("if(B8=0,""..."",GOOGLEFINANCE(B8,""change"")*H8)"),-33.39) -> -33.39 | Q8: =if(B8=0,"...",N8/J8-1) -> 0.12696872 | R8: =if(B8=0,"...",N8-J8) -> 28129.92 | S8: {=IF(B8=0,"...",(N8/IF(E8="ABIERTA",CCL!$E$2,VLOOKUP(F8,{CCL!M:N;CCL!$P:$Q},2,FALSE))/(J8/VLOOKUP(D8,{CCL!M:N;CCL!$P:$Q},2,FALSE))-1))} -> -0.10348225 | T8: {=IF(B8=0,"...",(N8/IF(E8="ABIERTA",CCL!$E$2,VLOOKUP(F8,{CCL!M:N;CCL!$P:$Q},2,FALSE))-K8))} -> -19.506431 | V8: =IFERROR(__xludf.DUMMYFUNCTION("""COMPUTED_VALUE"""),"AAPL") -> AAPL | W8: =if(V8=0,"...",sumifs($H$2:$H$37,$B$2:$B$37,V8,$E$2:$E$37,"ABIERTA")) -> 28 | X8: =if(V8=0,"",Z8/$AH$19) -> 0.10619848 | Y8: =if(W8=0,"...",if(V8=0,"...",sumifs($J$2:$J$37,$B$2:$B$37,V8,$E$2:$E$37,"ABIERTA")/W8)) -> 16717.857 | Z8: =if(V8=0,"...",sumifs($N$2:$N$37,$B$2:$B$37,V8,$E$2:$E$37,"ABIERTA")) -> 527997.96 | AA8: =if(W8=0,"...",if(V8=0,"...",AB8/(Z8-AB8))) -> 0.12795975 | AB8: =if(W8=0,"...",if(V8=0,"...",sumifs($R$2:$R$37,$B$2:$B$37,V8,$E$2:$E$37,"ABIERTA"))) -> 59897.96 | AC8: =IF(W8=0,"...",IF(V8=0,"...",SUMIFS($K$2:$K$37,$B$2:$B$37,V8,$E$2:$E$37,"ABIERTA"))) -> 328.61881 | AD8: =IF(V8=0,"...",AE8/(AC8+AE8)) -> 0.080455051 | AE8: =IF(W8=0,"...",if(V8=0,"...",sumifs($T$2:$T$37,$B$2:$B$37,V8,$E$2:$E$37,"ABIERTA"))) -> 28.752312
A9: IOL | B9: NVDA | C9: =IFERROR(__xludf.DUMMYFUNCTION("if(B9=0,""..."", sparkline(query(GOOGLEFINANCE(""BCBA:""&B9,""price"",today()-$AI$36,today()),""select Col2"",0),{""charttype"",$AI$35}))"),"") | D9: 45805 | E9: ABIERTA | G9: =if(B9=0,"...", IF(F9=0,today()-D9,F9-D9)) -> 312 | H9: 35 | I9: 6700 | J9: =if(B9=0,"...",H9*I9) -> 234500 | K9: {=IF(B9=0,"...",J9/VLOOKUP(D9,{CCL!M:N;CCL!$P:$Q},2,FALSE))} -> 199.51843 | L9: =IFERROR(__xludf.DUMMYFUNCTION("if(B9=0,""..."",if(E9=""CERRADA"",""Valor Venta"", GOOGLEFINANCE(""BCBA:""&B9)))"),10910.0) -> 10910 | M9: =if(B9=0,"...",L9*(1-VLOOKUP(A9,Config!$B$3:$C$22,2,FALSE))) -> 10833.63 | N9: =IF(B9=0,"...",H9*M9) -> 379177.05 | O9: =IFERROR(__xludf.DUMMYFUNCTION("if(B9=0,""..."",GOOGLEFINANCE(B9,""changepct"")/100)"),0.009300000000000001) -> 0.0093 | P9: =IFERROR(__xludf.DUMMYFUNCTION("if(B9=0,""..."",GOOGLEFINANCE(B9,""change"")*H9)"),57.4) -> 57.4 | Q9: =if(B9=0,"...",N9/J9-1) -> 0.6169597 | R9: =if(B9=0,"...",N9-J9) -> 144677.05 | S9: {=IF(B9=0,"...",(N9/IF(E9="ABIERTA",CCL!$E$2,VLOOKUP(F9,{CCL!M:N;CCL!$P:$Q},2,FALSE))/(J9/VLOOKUP(D9,{CCL!M:N;CCL!$P:$Q},2,FALSE))-1))} -> 0.28631172 | T9: {=IF(B9=0,"...",(N9/IF(E9="ABIERTA",CCL!$E$2,VLOOKUP(F9,{CCL!M:N;CCL!$P:$Q},2,FALSE))-K9))} -> 57.124465 | V9: =IFERROR(__xludf.DUMMYFUNCTION("""COMPUTED_VALUE"""),"GLD") -> GLD | W9: =if(V9=0,"...",sumifs($H$2:$H$37,$B$2:$B$37,V9,$E$2:$E$37,"ABIERTA")) -> 10 | X9: =if(V9=0,"",Z9/$AH$19) -> 0.025342546 | Y9: =if(W9=0,"...",if(V9=0,"...",sumifs($J$2:$J$37,$B$2:$B$37,V9,$E$2:$E$37,"ABIERTA")/W9)) -> 10870 | Z9: =if(V9=0,"...",sumifs($N$2:$N$37,$B$2:$B$37,V9,$E$2:$E$37,"ABIERTA")) -> 125998.16 | AA9: =if(W9=0,"...",if(V9=0,"...",AB9/(Z9-AB9))) -> 0.15913667 | AB9: =if(W9=0,"...",if(V9=0,"...",sumifs($R$2:$R$37,$B$2:$B$37,V9,$E$2:$E$37,"ABIERTA"))) -> 17298.156 | AC9: =IF(W9=0,"...",IF(V9=0,"...",SUMIFS($K$2:$K$37,$B$2:$B$37,V9,$E$2:$E$37,"ABIERTA"))) -> 73.090371 | AD9: =IF(V9=0,"...",AE9/(AC9+AE9)) -> 0.14294485 | AE9: =IF(W9=0,"...",if(V9=0,"...",sumifs($T$2:$T$37,$B$2:$B$37,V9,$E$2:$E$37,"ABIERTA"))) -> 12.190455
A10: IOL | B10: AMZN | C10: =IFERROR(__xludf.DUMMYFUNCTION("if(B10=0,""..."", sparkline(query(GOOGLEFINANCE(""BCBA:""&B10,""price"",today()-$AI$36,today()),""select Col2"",0),{""charttype"",$AI$35}))"),"") | D10: 45805 | E10: CERRADA | F10: 46035 | G10: =if(B10=0,"...", IF(F10=0,today()-D10,F10-D10)) -> 230 | H10: 129 | I10: 1680 | J10: =if(B10=0,"...",H10*I10) -> 216720 | K10: {=IF(B10=0,"...",J10/VLOOKUP(D10,{CCL!M:N;CCL!$P:$Q},2,FALSE))} -> 184.39077 | L10: 2625 | M10: =if(B10=0,"...",L10*(1-VLOOKUP(A10,Config!$B$3:$C$22,2,FALSE))) -> 2606.625 | N10: =IF(B10=0,"...",H10*M10) -> 336254.62 | O10: =IFERROR(__xludf.DUMMYFUNCTION("if(B10=0,""..."",GOOGLEFINANCE(B10,""changepct"")/100)"),-0.0038) -> -0.0038 | P10: =IFERROR(__xludf.DUMMYFUNCTION("if(B10=0,""..."",GOOGLEFINANCE(B10,""change"")*H10)"),-103.2) -> -103.2 | Q10: =if(B10=0,"...",N10/J10-1) -> 0.5515625 | R10: =if(B10=0,"...",N10-J10) -> 119534.62 | S10: {=IF(B10=0,"...",(N10/IF(E10="ABIERTA",CCL!$E$2,VLOOKUP(F10,{CCL!M:N;CCL!$P:$Q},2,FALSE))/(J10/VLOOKUP(D10,{CCL!M:N;CCL!$P:$Q},2,FALSE))-1))} -> 0.19790711 | T10: {=IF(B10=0,"...",(N10/IF(E10="ABIERTA",CCL!$E$2,VLOOKUP(F10,{CCL!M:N;CCL!$P:$Q},2,FALSE))-K10))} -> 36.492244 | V10: =IFERROR(__xludf.DUMMYFUNCTION("""COMPUTED_VALUE"""),"KO") -> KO | W10: =if(V10=0,"...",sumifs($H$2:$H$37,$B$2:$B$37,V10,$E$2:$E$37,"ABIERTA")) -> 5 | X10: =if(V10=0,"",Z10/$AH$19) -> 0.022638978 | Y10: =if(W10=0,"...",if(V10=0,"...",sumifs($J$2:$J$37,$B$2:$B$37,V10,$E$2:$E$37,"ABIERTA")/W10)) -> 20690 | Z10: =if(V10=0,"...",sumifs($N$2:$N$37,$B$2:$B$37,V10,$E$2:$E$37,"ABIERTA")) -> 112556.55 | AA10: =if(W10=0,"...",if(V10=0,"...",AB10/(Z10-AB10))) -> 0.088028516 | AB10: =if(W10=0,"...",if(V10=0,"...",sumifs($R$2:$R$37,$B$2:$B$37,V10,$E$2:$E$37,"ABIERTA"))) -> 9106.55 | AC10: =IF(W10=0,"...",IF(V10=0,"...",SUMIFS($K$2:$K$37,$B$2:$B$37,V10,$E$2:$E$37,"ABIERTA"))) -> 68.362795 | AD10: =IF(V10=0,"...",AE10/(AC10+AE10)) -> 0.10265007 | AE10: =IF(W10=0,"...",if(V10=0,"...",sumifs($T$2:$T$37,$B$2:$B$37,V10,$E$2:$E$37,"ABIERTA"))) -> 7.8201889
A11: IOL | B11: AAPL | C11: =IFERROR(__xludf.DUMMYFUNCTION("if(B11=0,""..."", sparkline(query(GOOGLEFINANCE(""BCBA:""&B11,""price"",today()-$AI$36,today()),""select Col2"",0),{""charttype"",$AI$35}))"),"") | D11: 45818 | E11: CERRADA | F11: 45978 | G11: =if(B11=0,"...", IF(F11=0,today()-D11,F11-D11)) -> 160 | H11: 10 | I11: 12075 | J11: =if(B11=0,"...",H11*I11) -> 120750 | K11: {=IF(B11=0,"...",J11/VLOOKUP(D11,{CCL!M:N;CCL!$P:$Q},2,FALSE))} -> 101.14336 | L11: 19900 | M11: =if(B11=0,"...",L11*(1-VLOOKUP(A11,Config!$B$3:$C$22,2,FALSE))) -> 19760.7 | N11: =IF(B11=0,"...",H11*M11) -> 197607 | O11: =IFERROR(__xludf.DUMMYFUNCTION("if(B11=0,""..."",GOOGLEFINANCE(B11,""changepct"")/100)"),0.0011) -> 0.0011 | P11: =IFERROR(__xludf.DUMMYFUNCTION("if(B11=0,""..."",GOOGLEFINANCE(B11,""change"")*H11)"),2.9) -> 2.9 | Q11: =if(B11=0,"...",N11/J11-1) -> 0.63649689 | R11: =if(B11=0,"...",N11-J11) -> 76857 | S11: {=IF(B11=0,"...",(N11/IF(E11="ABIERTA",CCL!$E$2,VLOOKUP(F11,{CCL!M:N;CCL!$P:$Q},2,FALSE))/(J11/VLOOKUP(D11,{CCL!M:N;CCL!$P:$Q},2,FALSE))-1))} -> 0.30766624 | T11: {=IF(B11=0,"...",(N11/IF(E11="ABIERTA",CCL!$E$2,VLOOKUP(F11,{CCL!M:N;CCL!$P:$Q},2,FALSE))-K11))} -> 31.118397 | V11: =IFERROR(__xludf.DUMMYFUNCTION("""COMPUTED_VALUE"""),"NFLX") -> NFLX | W11: =if(V11=0,"...",sumifs($H$2:$H$37,$B$2:$B$37,V11,$E$2:$E$37,"ABIERTA")) -> 90 | X11: =if(V11=0,"",Z11/$AH$19) -> 0.053162153 | Y11: =if(W11=0,"...",if(V11=0,"...",sumifs($J$2:$J$37,$B$2:$B$37,V11,$E$2:$E$37,"ABIERTA")/W11)) -> 3448 | Z11: =if(V11=0,"...",sumifs($N$2:$N$37,$B$2:$B$37,V11,$E$2:$E$37,"ABIERTA")) -> 264311.78 | AA11: =if(W11=0,"...",if(V11=0,"...",AB11/(Z11-AB11))) -> -0.14826059 | AB11: =if(W11=0,"...",if(V11=0,"...",sumifs($R$2:$R$37,$B$2:$B$37,V11,$E$2:$E$37,"ABIERTA"))) -> -46008.225 | AC11: =IF(W11=0,"...",IF(V11=0,"...",SUMIFS($K$2:$K$37,$B$2:$B$37,V11,$E$2:$E$37,"ABIERTA"))) -> 205.06856 | AD11: =IF(V11=0,"...",AE11/(AC11+AE11)) -> -0.14629227 | AE11: =IF(W11=0,"...",if(V11=0,"...",sumifs($T$2:$T$37,$B$2:$B$37,V11,$E$2:$E$37,"ABIERTA"))) -> -26.171289
A12: IOL | B12: AAPL | C12: =IFERROR(__xludf.DUMMYFUNCTION("if(B12=0,""..."", sparkline(query(GOOGLEFINANCE(""BCBA:""&B12,""price"",today()-$AI$36,today()),""select Col2"",0),{""charttype"",$AI$35}))"),"") | D12: 45839 | E12: CERRADA | F12: 45978 | G12: =if(B12=0,"...", IF(F12=0,today()-D12,F12-D12)) -> 139 | H12: 15 | I12: 12675 | J12: =if(B12=0,"...",H12*I12) -> 190125 | K12: {=IF(B12=0,"...",J12/VLOOKUP(D12,{CCL!M:N;CCL!$P:$Q},2,FALSE))} -> 154.18708 | L12: 19900 | M12: =if(B12=0,"...",L12*(1-VLOOKUP(A12,Config!$B$3:$C$22,2,FALSE))) -> 19760.7 | N12: =IF(B12=0,"...",H12*M12) -> 296410.5 | O12: =IFERROR(__xludf.DUMMYFUNCTION("if(B12=0,""..."",GOOGLEFINANCE(B12,""changepct"")/100)"),0.0011) -> 0.0011 | P12: =IFERROR(__xludf.DUMMYFUNCTION("if(B12=0,""..."",GOOGLEFINANCE(B12,""change"")*H12)"),4.35) -> 4.35 | Q12: =if(B12=0,"...",N12/J12-1) -> 0.55902959 | R12: =if(B12=0,"...",N12-J12) -> 106285.5 | S12: {=IF(B12=0,"...",(N12/IF(E12="ABIERTA",CCL!$E$2,VLOOKUP(F12,{CCL!M:N;CCL!$P:$Q},2,FALSE))/(J12/VLOOKUP(D12,{CCL!M:N;CCL!$P:$Q},2,FALSE))-1))} -> 0.2867008 | T12: {=IF(B12=0,"...",(N12/IF(E12="ABIERTA",CCL!$E$2,VLOOKUP(F12,{CCL!M:N;CCL!$P:$Q},2,FALSE))-K12))} -> 44.205559 | V12: =IFERROR(__xludf.DUMMYFUNCTION("""COMPUTED_VALUE"""),"PFE") -> PFE | W12: =if(V12=0,"...",sumifs($H$2:$H$37,$B$2:$B$37,V12,$E$2:$E$37,"ABIERTA")) -> 10 | X12: =if(V12=0,"",Z12/$AH$19) -> 0.02117099 | Y12: =if(W12=0,"...",if(V12=0,"...",sumifs($J$2:$J$37,$B$2:$B$37,V12,$E$2:$E$37,"ABIERTA")/W12)) -> 9740 | Z12: =if(V12=0,"...",sumifs($N$2:$N$37,$B$2:$B$37,V12,$E$2:$E$37,"ABIERTA")) -> 105258 | AA12: =if(W12=0,"...",if(V12=0,"...",AB12/(Z12-AB12))) -> 0.080677618 | AB12: =if(W12=0,"...",if(V12=0,"...",sumifs($R$2:$R$37,$B$2:$B$37,V12,$E$2:$E$37,"ABIERTA"))) -> 7858 | AC12: =IF(W12=0,"...",IF(V12=0,"...",SUMIFS($K$2:$K$37,$B$2:$B$37,V12,$E$2:$E$37,"ABIERTA"))) -> 65.04608 | AD12: =IF(V12=0,"...",AE12/(AC12+AE12)) -> 0.08698312 | AE12: =IF(W12=0,"...",if(V12=0,"...",sumifs($T$2:$T$37,$B$2:$B$37,V12,$E$2:$E$37,"ABIERTA"))) -> 6.1969402
A13: IOL | B13: AMZN | C13: =IFERROR(__xludf.DUMMYFUNCTION("if(B13=0,""..."", sparkline(query(GOOGLEFINANCE(""BCBA:""&B13,""price"",today()-$AI$36,today()),""select Col2"",0),{""charttype"",$AI$35}))"),"") | D13: 45839 | E13: CERRADA | F13: 46035 | G13: =if(B13=0,"...", IF(F13=0,today()-D13,F13-D13)) -> 196 | H13: 107 | I13: 1855 | J13: =if(B13=0,"...",H13*I13) -> 198485 | K13: {=IF(B13=0,"...",J13/VLOOKUP(D13,{CCL!M:N;CCL!$P:$Q},2,FALSE))} -> 160.96685 | L13: 2625 | M13: =if(B13=0,"...",L13*(1-VLOOKUP(A13,Config!$B$3:$C$22,2,FALSE))) -> 2606.625 | N13: =IF(B13=0,"...",H13*M13) -> 278908.88 | O13: =IFERROR(__xludf.DUMMYFUNCTION("if(B13=0,""..."",GOOGLEFINANCE(B13,""changepct"")/100)"),-0.0038) -> -0.0038 | P13: =IFERROR(__xludf.DUMMYFUNCTION("if(B13=0,""..."",GOOGLEFINANCE(B13,""change"")*H13)"),-85.60000000000001) -> -85.6 | Q13: =if(B13=0,"...",N13/J13-1) -> 0.40518868 | R13: =if(B13=0,"...",N13-J13) -> 80423.875 | S13: {=IF(B13=0,"...",(N13/IF(E13="ABIERTA",CCL!$E$2,VLOOKUP(F13,{CCL!M:N;CCL!$P:$Q},2,FALSE))/(J13/VLOOKUP(D13,{CCL!M:N;CCL!$P:$Q},2,FALSE))-1))} -> 0.13820357 | T13: {=IF(B13=0,"...",(N13/IF(E13="ABIERTA",CCL!$E$2,VLOOKUP(F13,{CCL!M:N;CCL!$P:$Q},2,FALSE))-K13))} -> 22.246193 | V13: =IFERROR(__xludf.DUMMYFUNCTION("""COMPUTED_VALUE"""),"ADBE") -> ADBE | W13: =if(V13=0,"...",sumifs($H$2:$H$37,$B$2:$B$37,V13,$E$2:$E$37,"ABIERTA")) -> 9 | X13: =if(V13=0,"",Z13/$AH$19) -> 0.014703852 | Y13: =if(W13=0,"...",if(V13=0,"...",sumifs($J$2:$J$37,$B$2:$B$37,V13,$E$2:$E$37,"ABIERTA")/W13)) -> 10300 | Z13: =if(V13=0,"...",sumifs($N$2:$N$37,$B$2:$B$37,V13,$E$2:$E$37,"ABIERTA")) -> 73104.66 | AA13: =if(W13=0,"...",if(V13=0,"...",AB13/(Z13-AB13))) -> -0.21138447 | AB13: =if(W13=0,"...",if(V13=0,"...",sumifs($R$2:$R$37,$B$2:$B$37,V13,$E$2:$E$37,"ABIERTA"))) -> -19595.34 | AC13: =IF(W13=0,"...",IF(V13=0,"...",SUMIFS($K$2:$K$37,$B$2:$B$37,V13,$E$2:$E$37,"ABIERTA"))) -> 61.907306 | AD13: =IF(V13=0,"...",AE13/(AC13+AE13)) -> -0.25115074 | AE13: =IF(W13=0,"...",if(V13=0,"...",sumifs($T$2:$T$37,$B$2:$B$37,V13,$E$2:$E$37,"ABIERTA"))) -> -12.427012
A14: IOL | B14: GOOGL | C14: =IFERROR(__xludf.DUMMYFUNCTION("if(B14=0,""..."", sparkline(query(GOOGLEFINANCE(""BCBA:""&B14,""price"",today()-$AI$36,today()),""select Col2"",0),{""charttype"",$AI$35}))"),"") | D14: 45839 | E14: CERRADA | F14: 45918 | G14: =if(B14=0,"...", IF(F14=0,today()-D14,F14-D14)) -> 79 | H14: 54 | I14: 3660 | J14: =if(B14=0,"...",H14*I14) -> 197640 | K14: {=IF(B14=0,"...",J14/VLOOKUP(D14,{CCL!M:N;CCL!$P:$Q},2,FALSE))} -> 160.28157 | L14: 6565 | M14: =if(B14=0,"...",L14*(1-VLOOKUP(A14,Config!$B$3:$C$22,2,FALSE))) -> 6519.045 | N14: =IF(B14=0,"...",H14*M14) -> 352028.43 | O14: =IFERROR(__xludf.DUMMYFUNCTION("if(B14=0,""..."",GOOGLEFINANCE(B14,""changepct"")/100)"),-0.0054) -> -0.0054 | P14: =IFERROR(__xludf.DUMMYFUNCTION("if(B14=0,""..."",GOOGLEFINANCE(B14,""change"")*H14)"),-87.48) -> -87.48 | Q14: =if(B14=0,"...",N14/J14-1) -> 0.78115984 | R14: =if(B14=0,"...",N14-J14) -> 154388.43 | S14: {=IF(B14=0,"...",(N14/IF(E14="ABIERTA",CCL!$E$2,VLOOKUP(F14,{CCL!M:N;CCL!$P:$Q},2,FALSE))/(J14/VLOOKUP(D14,{CCL!M:N;CCL!$P:$Q},2,FALSE))-1))} -> 0.40420214 | T14: {=IF(B14=0,"...",(N14/IF(E14="ABIERTA",CCL!$E$2,VLOOKUP(F14,{CCL!M:N;CCL!$P:$Q},2,FALSE))-K14))} -> 64.786154 | V14: =IFERROR(__xludf.DUMMYFUNCTION("""COMPUTED_VALUE"""),"INTC") -> INTC | W14: =if(V14=0,"...",sumifs($H$2:$H$37,$B$2:$B$37,V14,$E$2:$E$37,"ABIERTA")) -> 6 | X14: =if(V14=0,"",Z14/$AH$19) -> 0.017052633 | Y14: =if(W14=0,"...",if(V14=0,"...",sumifs($J$2:$J$37,$B$2:$B$37,V14,$E$2:$E$37,"ABIERTA")/W14)) -> 14660 | Z14: =if(V14=0,"...",sumifs($N$2:$N$37,$B$2:$B$37,V14,$E$2:$E$37,"ABIERTA")) -> 84782.34 | AA14: =if(W14=0,"...",if(V14=0,"...",AB14/(Z14-AB14))) -> -0.036126194 | AB14: =if(W14=0,"...",if(V14=0,"...",sumifs($R$2:$R$37,$B$2:$B$37,V14,$E$2:$E$37,"ABIERTA"))) -> -3177.66 | AC14: =IF(W14=0,"...",IF(V14=0,"...",SUMIFS($K$2:$K$37,$B$2:$B$37,V14,$E$2:$E$37,"ABIERTA"))) -> 58.741819 | AD14: =IF(V14=0,"...",AE14/(AC14+AE14)) -> -0.023657765 | AE14: =IF(W14=0,"...",if(V14=0,"...",sumifs($T$2:$T$37,$B$2:$B$37,V14,$E$2:$E$37,"ABIERTA"))) -> -1.3575828
A15: IOL | B15: MELI | C15: =IFERROR(__xludf.DUMMYFUNCTION("if(B15=0,""..."", sparkline(query(GOOGLEFINANCE(""BCBA:""&B15,""price"",today()-$AI$36,today()),""select Col2"",0),{""charttype"",$AI$35}))"),"") | D15: 45840 | E15: ABIERTA | G15: =if(B15=0,"...", IF(F15=0,today()-D15,F15-D15)) -> 277 | H15: 8 | I15: 25875 | J15: =if(B15=0,"...",H15*I15) -> 207000 | K15: {=IF(B15=0,"...",J15/VLOOKUP(D15,{CCL!M:N;CCL!$P:$Q},2,FALSE))} -> 167.51368 | L15: =IFERROR(__xludf.DUMMYFUNCTION("if(B15=0,""..."",if(E15=""CERRADA"",""Valor Venta"", GOOGLEFINANCE(""BCBA:""&B15)))"),21350.0) -> 21350 | M15: =if(B15=0,"...",L15*(1-VLOOKUP(A15,Config!$B$3:$C$22,2,FALSE))) -> 21200.55 | N15: =IF(B15=0,"...",H15*M15) -> 169604.4 | O15: =IFERROR(__xludf.DUMMYFUNCTION("if(B15=0,""..."",GOOGLEFINANCE(B15,""changepct"")/100)"),-0.002) -> -0.002 | P15: =IFERROR(__xludf.DUMMYFUNCTION("if(B15=0,""..."",GOOGLEFINANCE(B15,""change"")*H15)"),-27.6) -> -27.6 | Q15: =if(B15=0,"...",N15/J15-1) -> -0.18065507 | R15: =if(B15=0,"...",N15-J15) -> -37395.6 | S15: {=IF(B15=0,"...",(N15/IF(E15="ABIERTA",CCL!$E$2,VLOOKUP(F15,{CCL!M:N;CCL!$P:$Q},2,FALSE))/(J15/VLOOKUP(D15,{CCL!M:N;CCL!$P:$Q},2,FALSE))-1))} -> -0.31471054 | T15: {=IF(B15=0,"...",(N15/IF(E15="ABIERTA",CCL!$E$2,VLOOKUP(F15,{CCL!M:N;CCL!$P:$Q},2,FALSE))-K15))} -> -52.718319 | V15: =IFERROR(__xludf.DUMMYFUNCTION("""COMPUTED_VALUE"""),"SPXL") -> SPXL | W15: =if(V15=0,"...",sumifs($H$2:$H$37,$B$2:$B$37,V15,$E$2:$E$37,"ABIERTA")) -> 17 | X15: =if(V15=0,"",Z15/$AH$19) -> 0.038095798 | Y15: =if(W15=0,"...",if(V15=0,"...",sumifs($J$2:$J$37,$B$2:$B$37,V15,$E$2:$E$37,"ABIERTA")/W15)) -> 13470 | Z15: =if(V15=0,"...",sumifs($N$2:$N$37,$B$2:$B$37,V15,$E$2:$E$37,"ABIERTA")) -> 189404.82 | AA15: =if(W15=0,"...",if(V15=0,"...",AB15/(Z15-AB15))) -> -0.1728686 | AB15: =if(W15=0,"...",if(V15=0,"...",sumifs($R$2:$R$37,$B$2:$B$37,V15,$E$2:$E$37,"ABIERTA"))) -> -39585.18 | AC15: =IF(W15=0,"...",IF(V15=0,"...",SUMIFS($K$2:$K$37,$B$2:$B$37,V15,$E$2:$E$37,"ABIERTA"))) -> 153.89113 | AD15: =IF(V15=0,"...",AE15/(AC15+AE15)) -> -0.20042588 | AE15: =IF(W15=0,"...",if(V15=0,"...",sumifs($T$2:$T$37,$B$2:$B$37,V15,$E$2:$E$37,"ABIERTA"))) -> -25.694019
A16: IOL | B16: MELI | C16: =IFERROR(__xludf.DUMMYFUNCTION("if(B16=0,""..."", sparkline(query(GOOGLEFINANCE(""BCBA:""&B16,""price"",today()-$AI$36,today()),""select Col2"",0),{""charttype"",$AI$35}))"),"") | D16: 45866 | E16: ABIERTA | G16: =if(B16=0,"...", IF(F16=0,today()-D16,F16-D16)) -> 251 | H16: 5 | I16: 25500 | J16: =if(B16=0,"...",H16*I16) -> 127500 | K16: {=IF(B16=0,"...",J16/VLOOKUP(D16,{CCL!M:N;CCL!$P:$Q},2,FALSE))} -> 98.095788 | L16: =IFERROR(__xludf.DUMMYFUNCTION("if(B16=0,""..."",if(E16=""CERRADA"",""Valor Venta"", GOOGLEFINANCE(""BCBA:""&B16)))"),21350.0) -> 21350 | M16: =if(B16=0,"...",L16*(1-VLOOKUP(A16,Config!$B$3:$C$22,2,FALSE))) -> 21200.55 | N16: =IF(B16=0,"...",H16*M16) -> 106002.75 | O16: =IFERROR(__xludf.DUMMYFUNCTION("if(B16=0,""..."",GOOGLEFINANCE(B16,""changepct"")/100)"),-0.002) -> -0.002 | P16: =IFERROR(__xludf.DUMMYFUNCTION("if(B16=0,""..."",GOOGLEFINANCE(B16,""change"")*H16)"),-17.25) -> -17.25 | Q16: =if(B16=0,"...",N16/J16-1) -> -0.16860588 | R16: =if(B16=0,"...",N16-J16) -> -21497.25 | S16: {=IF(B16=0,"...",(N16/IF(E16="ABIERTA",CCL!$E$2,VLOOKUP(F16,{CCL!M:N;CCL!$P:$Q},2,FALSE))/(J16/VLOOKUP(D16,{CCL!M:N;CCL!$P:$Q},2,FALSE))-1))} -> -0.26860164 | T16: {=IF(B16=0,"...",(N16/IF(E16="ABIERTA",CCL!$E$2,VLOOKUP(F16,{CCL!M:N;CCL!$P:$Q},2,FALSE))-K16))} -> -26.34869 | W16: =if(V16=0,"...",sumifs($H$2:$H$37,$B$2:$B$37,V16,$E$2:$E$37,"ABIERTA")) -> ... | X16: =if(V16=0,"",Z16/$AH$19) | Y16: =if(W16=0,"...",if(V16=0,"...",sumifs($J$2:$J$37,$B$2:$B$37,V16,$E$2:$E$37,"ABIERTA")/W16)) -> ... | Z16: =if(V16=0,"...",sumifs($N$2:$N$37,$B$2:$B$37,V16,$E$2:$E$37,"ABIERTA")) -> ... | AA16: =if(W16=0,"...",if(V16=0,"...",AB16/(Z16-AB16))) -> ... | AB16: =if(W16=0,"...",if(V16=0,"...",sumifs($R$2:$R$37,$B$2:$B$37,V16,$E$2:$E$37,"ABIERTA"))) -> ... | AC16: =IF(W16=0,"...",IF(V16=0,"...",SUMIFS($K$2:$K$37,$B$2:$B$37,V16,$E$2:$E$37,"ABIERTA"))) -> ... | AD16: =IF(V16=0,"...",AE16/(AC16+AE16)) -> ... | AE16: =IF(W16=0,"...",if(V16=0,"...",sumifs($T$2:$T$37,$B$2:$B$37,V16,$E$2:$E$37,"ABIERTA"))) -> ...
A17: IOL | B17: AAPL | C17: =IFERROR(__xludf.DUMMYFUNCTION("if(B17=0,""..."", sparkline(query(GOOGLEFINANCE(""BCBA:""&B17,""price"",today()-$AI$36,today()),""select Col2"",0),{""charttype"",$AI$35}))"),"") | D17: 45866 | E17: ABIERTA | G17: =if(B17=0,"...", IF(F17=0,today()-D17,F17-D17)) -> 251 | H17: 12 | I17: 13875 | J17: =if(B17=0,"...",H17*I17) -> 166500 | K17: {=IF(B17=0,"...",J17/VLOOKUP(D17,{CCL!M:N;CCL!$P:$Q},2,FALSE))} -> 128.10156 | L17: =IFERROR(__xludf.DUMMYFUNCTION("if(B17=0,""..."",if(E17=""CERRADA"",""Valor Venta"", GOOGLEFINANCE(""BCBA:""&B17)))"),18990.0) -> 18990 | M17: =if(B17=0,"...",L17*(1-VLOOKUP(A17,Config!$B$3:$C$22,2,FALSE))) -> 18857.07 | N17: =IF(B17=0,"...",H17*M17) -> 226284.84 | O17: =IFERROR(__xludf.DUMMYFUNCTION("if(B17=0,""..."",GOOGLEFINANCE(B17,""changepct"")/100)"),0.0011) -> 0.0011 | P17: =IFERROR(__xludf.DUMMYFUNCTION("if(B17=0,""..."",GOOGLEFINANCE(B17,""change"")*H17)"),3.4799999999999995) -> 3.48 | Q17: =if(B17=0,"...",N17/J17-1) -> 0.35906811 | R17: =if(B17=0,"...",N17-J17) -> 59784.84 | S17: {=IF(B17=0,"...",(N17/IF(E17="ABIERTA",CCL!$E$2,VLOOKUP(F17,{CCL!M:N;CCL!$P:$Q},2,FALSE))/(J17/VLOOKUP(D17,{CCL!M:N;CCL!$P:$Q},2,FALSE))-1))} -> 0.19560647 | T17: {=IF(B17=0,"...",(N17/IF(E17="ABIERTA",CCL!$E$2,VLOOKUP(F17,{CCL!M:N;CCL!$P:$Q},2,FALSE))-K17))} -> 25.057493 | X17: =if(V17=0,"",Z17/$AH$19) | Y17: =if(W17=0,"...",if(V17=0,"...",sumifs($J$2:$J$37,$B$2:$B$37,V17,$E$2:$E$37,"ABIERTA")/W17)) -> ... | Z17: =if(V17=0,"...",sumifs($N$2:$N$37,$B$2:$B$37,V17,$E$2:$E$37,"ABIERTA")) -> ... | AA17: =if(W17=0,"...",if(V17=0,"...",AB17/(Z17-AB17))) -> ... | AB17: =if(W17=0,"...",if(V17=0,"...",sumifs($R$2:$R$37,$B$2:$B$37,V17,$E$2:$E$37,"ABIERTA"))) -> ... | AC17: =IF(W17=0,"...",IF(V17=0,"...",SUMIFS($K$2:$K$37,$B$2:$B$37,V17,$E$2:$E$37,"ABIERTA"))) -> ... | AD17: =IF(V17=0,"...",AE17/(AC17+AE17)) -> ... | AE17: =IF(W17=0,"...",if(V17=0,"...",sumifs($T$2:$T$37,$B$2:$B$37,V17,$E$2:$E$37,"ABIERTA"))) -> ...
A18: IOL | B18: SPXL | C18: =IFERROR(__xludf.DUMMYFUNCTION("if(B18=0,""..."", sparkline(query(GOOGLEFINANCE(""BCBA:""&B18,""price"",today()-$AI$36,today()),""select Col2"",0),{""charttype"",$AI$35}))"),"") | D18: 45870 | E18: CERRADA | F18: 45904 | G18: =if(B18=0,"...", IF(F18=0,today()-D18,F18-D18)) -> 34 | H18: 62 | I18: 9549.52 | J18: =if(B18=0,"...",H18*I18) -> 592070.24 | K18: {=IF(B18=0,"...",J18/VLOOKUP(D18,{CCL!M:N;CCL!$P:$Q},2,FALSE))} -> 433.14817 | L18: 10525 | M18: =if(B18=0,"...",L18*(1-VLOOKUP(A18,Config!$B$3:$C$22,2,FALSE))) -> 10451.325 | N18: =IF(B18=0,"...",H18*M18) -> 647982.15 | O18: =IFERROR(__xludf.DUMMYFUNCTION("if(B18=0,""..."",GOOGLEFINANCE(B18,""changepct"")/100)"),0.0024) -> 0.0024 | P18: =IFERROR(__xludf.DUMMYFUNCTION("if(B18=0,""..."",GOOGLEFINANCE(B18,""change"")*H18)"),28.52) -> 28.52 | Q18: =if(B18=0,"...",N18/J18-1) -> 0.094434589 | R18: =if(B18=0,"...",N18-J18) -> 55911.91 | S18: {=IF(B18=0,"...",(N18/IF(E18="ABIERTA",CCL!$E$2,VLOOKUP(F18,{CCL!M:N;CCL!$P:$Q},2,FALSE))/(J18/VLOOKUP(D18,{CCL!M:N;CCL!$P:$Q},2,FALSE))-1))} -> 0.083299642 | T18: {=IF(B18=0,"...",(N18/IF(E18="ABIERTA",CCL!$E$2,VLOOKUP(F18,{CCL!M:N;CCL!$P:$Q},2,FALSE))-K18))} -> 36.081088 | W18: =if(V18=0,"...",sumifs($H$2:$H$37,$B$2:$B$37,V18,$E$2:$E$37,"ABIERTA")) -> ... | X18: =if(V18=0,"",Z18/$AH$19) | Y18: =if(W18=0,"...",if(V18=0,"...",sumifs($J$2:$J$37,$B$2:$B$37,V18,$E$2:$E$37,"ABIERTA")/W18)) -> ... | Z18: =if(V18=0,"...",sumifs($N$2:$N$37,$B$2:$B$37,V18,$E$2:$E$37,"ABIERTA")) -> ... | AA18: =if(W18=0,"...",if(V18=0,"...",AB18/(Z18-AB18))) -> ... | AB18: =if(W18=0,"...",if(V18=0,"...",sumifs($R$2:$R$37,$B$2:$B$37,V18,$E$2:$E$37,"ABIERTA"))) -> ... | AC18: =IF(W18=0,"...",IF(V18=0,"...",SUMIFS($K$2:$K$37,$B$2:$B$37,V18,$E$2:$E$37,"ABIERTA"))) -> ... | AD18: =IF(V18=0,"...",AE18/(AC18+AE18)) -> ... | AE18: =IF(W18=0,"...",if(V18=0,"...",sumifs($T$2:$T$37,$B$2:$B$37,V18,$E$2:$E$37,"ABIERTA"))) -> ...
A19: IOL | B19: MELI | C19: =IFERROR(__xludf.DUMMYFUNCTION("if(B19=0,""..."", sparkline(query(GOOGLEFINANCE(""BCBA:""&B19,""price"",today()-$AI$36,today()),""select Col2"",0),{""charttype"",$AI$35}))"),"") | D19: 45918 | E19: ABIERTA | G19: =if(B19=0,"...", IF(F19=0,today()-D19,F19-D19)) -> 199 | H19: 19 | I19: 31800 | J19: =if(B19=0,"...",H19*I19) -> 604200 | K19: {=IF(B19=0,"...",J19/VLOOKUP(D19,{CCL!M:N;CCL!$P:$Q},2,FALSE))} -> 386.29244 | L19: =IFERROR(__xludf.DUMMYFUNCTION("if(B19=0,""..."",if(E19=""CERRADA"",""Valor Venta"", GOOGLEFINANCE(""BCBA:""&B19)))"),21350.0) -> 21350 | M19: =if(B19=0,"...",L19*(1-VLOOKUP(A19,Config!$B$3:$C$22,2,FALSE))) -> 21200.55 | N19: =IF(B19=0,"...",H19*M19) -> 402810.45 | O19: =IFERROR(__xludf.DUMMYFUNCTION("if(B19=0,""..."",GOOGLEFINANCE(B19,""changepct"")/100)"),-0.002) -> -0.002 | P19: =IFERROR(__xludf.DUMMYFUNCTION("if(B19=0,""..."",GOOGLEFINANCE(B19,""change"")*H19)"),-65.55) -> -65.55 | Q19: =if(B19=0,"...",N19/J19-1) -> -0.33331604 | R19: =if(B19=0,"...",N19-J19) -> -201389.55 | S19: {=IF(B19=0,"...",(N19/IF(E19="ABIERTA",CCL!$E$2,VLOOKUP(F19,{CCL!M:N;CCL!$P:$Q},2,FALSE))/(J19/VLOOKUP(D19,{CCL!M:N;CCL!$P:$Q},2,FALSE))-1))} -> -0.29421613 | T19: {=IF(B19=0,"...",(N19/IF(E19="ABIERTA",CCL!$E$2,VLOOKUP(F19,{CCL!M:N;CCL!$P:$Q},2,FALSE))-K19))} -> -113.65346 | W19: =if(V19=0,"...",sumifs($H$2:$H$37,$B$2:$B$37,V19,$E$2:$E$37,"ABIERTA")) -> ... | X19: =if(V19=0,"",Z19/$AH$19) | Y19: =if(W19=0,"...",if(V19=0,"...",sumifs($J$2:$J$37,$B$2:$B$37,V19,$E$2:$E$37,"ABIERTA")/W19)) -> ... | Z19: =if(V19=0,"...",sumifs($N$2:$N$37,$B$2:$B$37,V19,$E$2:$E$37,"ABIERTA")) -> ... | AA19: =if(W19=0,"...",if(V19=0,"...",AB19/(Z19-AB19))) -> ... | AB19: =if(W19=0,"...",if(V19=0,"...",sumifs($R$2:$R$37,$B$2:$B$37,V19,$E$2:$E$37,"ABIERTA"))) -> ... | AC19: =IF(W19=0,"...",IF(V19=0,"...",SUMIFS($K$2:$K$37,$B$2:$B$37,V19,$E$2:$E$37,"ABIERTA"))) -> ... | AD19: =IF(V19=0,"...",AE19/(AC19+AE19)) -> ... | AE19: =IF(W19=0,"...",if(V19=0,"...",sumifs($T$2:$T$37,$B$2:$B$37,V19,$E$2:$E$37,"ABIERTA"))) -> ... | AG19: Total Abierto | AH19: =sumifs(N2:N36,E2:E36,"ABIERTA") -> 4971803.4 | AI19: Total Acumulado | AJ19: =sum(N2:N36) -> 8115294.3
A20: IOL | B20: JPM | C20: =IFERROR(__xludf.DUMMYFUNCTION("if(B20=0,""..."", sparkline(query(GOOGLEFINANCE(""BCBA:""&B20,""price"",today()-$AI$36,today()),""select Col2"",0),{""charttype"",$AI$35}))"),"") | D20: 45943 | E20: ABIERTA | G20: =if(B20=0,"...", IF(F20=0,today()-D20,F20-D20)) -> 174 | H20: 7 | I20: 29400 | J20: =if(B20=0,"...",H20*I20) -> 205800 | K20: {=IF(B20=0,"...",J20/VLOOKUP(D20,{CCL!M:N;CCL!$P:$Q},2,FALSE))} -> 142.90476 | L20: =IFERROR(__xludf.DUMMYFUNCTION("if(B20=0,""..."",if(E20=""CERRADA"",""Valor Venta"", GOOGLEFINANCE(""BCBA:""&B20)))"),29200.0) -> 29200 | M20: =if(B20=0,"...",L20*(1-VLOOKUP(A20,Config!$B$3:$C$22,2,FALSE))) -> 28995.6 | N20: =IF(B20=0,"...",H20*M20) -> 202969.2 | O20: =IFERROR(__xludf.DUMMYFUNCTION("if(B20=0,""..."",GOOGLEFINANCE(B20,""changepct"")/100)"),-0.0026) -> -0.0026 | P20: =IFERROR(__xludf.DUMMYFUNCTION("if(B20=0,""..."",GOOGLEFINANCE(B20,""change"")*H20)"),-5.46) -> -5.46 | Q20: =if(B20=0,"...",N20/J20-1) -> -0.013755102 | R20: =if(B20=0,"...",N20-J20) -> -2830.8 | S20: {=IF(B20=0,"...",(N20/IF(E20="ABIERTA",CCL!$E$2,VLOOKUP(F20,{CCL!M:N;CCL!$P:$Q},2,FALSE))/(J20/VLOOKUP(D20,{CCL!M:N;CCL!$P:$Q},2,FALSE))-1))} -> -0.038674065 | T20: {=IF(B20=0,"...",(N20/IF(E20="ABIERTA",CCL!$E$2,VLOOKUP(F20,{CCL!M:N;CCL!$P:$Q},2,FALSE))-K20))} -> -5.5267079 | W20: =if(V20=0,"...",sumifs($H$2:$H$37,$B$2:$B$37,V20,$E$2:$E$37,"ABIERTA")) -> ... | X20: =if(V20=0,"",Z20/$AH$19) | Y20: =if(W20=0,"...",if(V20=0,"...",sumifs($J$2:$J$37,$B$2:$B$37,V20,$E$2:$E$37,"ABIERTA")/W20)) -> ... | Z20: =if(V20=0,"...",sumifs($N$2:$N$37,$B$2:$B$37,V20,$E$2:$E$37,"ABIERTA")) -> ... | AA20: =if(W20=0,"...",if(V20=0,"...",AB20/(Z20-AB20))) -> ... | AB20: =if(W20=0,"...",if(V20=0,"...",sumifs($R$2:$R$37,$B$2:$B$37,V20,$E$2:$E$37,"ABIERTA"))) -> ... | AC20: =IF(W20=0,"...",IF(V20=0,"...",SUMIFS($K$2:$K$37,$B$2:$B$37,V20,$E$2:$E$37,"ABIERTA"))) -> ... | AD20: =IF(V20=0,"...",AE20/(AC20+AE20)) -> ... | AE20: =IF(W20=0,"...",if(V20=0,"...",sumifs($T$2:$T$37,$B$2:$B$37,V20,$E$2:$E$37,"ABIERTA"))) -> ...
A21: IOL | B21: MELI | C21: =IFERROR(__xludf.DUMMYFUNCTION("if(B21=0,""..."", sparkline(query(GOOGLEFINANCE(""BCBA:""&B21,""price"",today()-$AI$36,today()),""select Col2"",0),{""charttype"",$AI$35}))"),"") | D21: 45946 | E21: ABIERTA | G21: =if(B21=0,"...", IF(F21=0,today()-D21,F21-D21)) -> 171 | H21: 15 | I21: 25100 | J21: =if(B21=0,"...",H21*I21) -> 376500 | K21: {=IF(B21=0,"...",J21/VLOOKUP(D21,{CCL!M:N;CCL!$P:$Q},2,FALSE))} -> 252.45752 | L21: =IFERROR(__xludf.DUMMYFUNCTION("if(B21=0,""..."",if(E21=""CERRADA"",""Valor Venta"", GOOGLEFINANCE(""BCBA:""&B21)))"),21350.0) -> 21350 | M21: =if(B21=0,"...",L21*(1-VLOOKUP(A21,Config!$B$3:$C$22,2,FALSE))) -> 21200.55 | N21: =IF(B21=0,"...",H21*M21) -> 318008.25 | O21: =IFERROR(__xludf.DUMMYFUNCTION("if(B21=0,""..."",GOOGLEFINANCE(B21,""changepct"")/100)"),-0.002) -> -0.002 | P21: =IFERROR(__xludf.DUMMYFUNCTION("if(B21=0,""..."",GOOGLEFINANCE(B21,""change"")*H21)"),-51.75) -> -51.75 | Q21: =if(B21=0,"...",N21/J21-1) -> -0.15535657 | R21: =if(B21=0,"...",N21-J21) -> -58491.75 | S21: {=IF(B21=0,"...",(N21/IF(E21="ABIERTA",CCL!$E$2,VLOOKUP(F21,{CCL!M:N;CCL!$P:$Q},2,FALSE))/(J21/VLOOKUP(D21,{CCL!M:N;CCL!$P:$Q},2,FALSE))-1))} -> -0.1474158 | T21: {=IF(B21=0,"...",(N21/IF(E21="ABIERTA",CCL!$E$2,VLOOKUP(F21,{CCL!M:N;CCL!$P:$Q},2,FALSE))-K21))} -> -37.216227 | W21: =if(V21=0,"...",sumifs($H$2:$H$37,$B$2:$B$37,V21,$E$2:$E$37,"ABIERTA")) -> ... | X21: =if(V21=0,"",Z21/$AH$19) | Y21: =if(W21=0,"...",if(V21=0,"...",sumifs($J$2:$J$37,$B$2:$B$37,V21,$E$2:$E$37,"ABIERTA")/W21)) -> ... | Z21: =if(V21=0,"...",sumifs($N$2:$N$37,$B$2:$B$37,V21,$E$2:$E$37,"ABIERTA")) -> ... | AA21: =if(W21=0,"...",if(V21=0,"...",AB21/(Z21-AB21))) -> ... | AB21: =if(W21=0,"...",if(V21=0,"...",sumifs($R$2:$R$37,$B$2:$B$37,V21,$E$2:$E$37,"ABIERTA"))) -> ... | AC21: =IF(W21=0,"...",IF(V21=0,"...",SUMIFS($K$2:$K$37,$B$2:$B$37,V21,$E$2:$E$37,"ABIERTA"))) -> ... | AD21: =IF(V21=0,"...",AE21/(AC21+AE21)) -> ... | AE21: =IF(W21=0,"...",if(V21=0,"...",sumifs($T$2:$T$37,$B$2:$B$37,V21,$E$2:$E$37,"ABIERTA"))) -> ... | AG21: Ganancia Abierto | AH21: =sumifs(R2:R36,E2:E36,"ABIERTA") -> -176761.6 | AI21: Ganancia Acumulada | AJ21: =sum(R2:R36) -> 675389.07
A22: IOL | B22: GLD | C22: =IFERROR(__xludf.DUMMYFUNCTION("if(B22=0,""..."", sparkline(query(GOOGLEFINANCE(""BCBA:""&B22,""price"",today()-$AI$36,today()),""select Col2"",0),{""charttype"",$AI$35}))"),"") | D22: 45959 | E22: ABIERTA | G22: =if(B22=0,"...", IF(F22=0,today()-D22,F22-D22)) -> 158 | H22: 10 | I22: 10870 | J22: =if(B22=0,"...",H22*I22) -> 108700 | K22: {=IF(B22=0,"...",J22/VLOOKUP(D22,{CCL!M:N;CCL!$P:$Q},2,FALSE))} -> 73.090371 | L22: =IFERROR(__xludf.DUMMYFUNCTION("IF(B22=0,""..."",IF(E22=""CERRADA"",""Valor Venta"", GOOGLEFINANCE(B22)*CCL!$E$2/50))"),12688.636090000002) -> 12688.636 | M22: =if(B22=0,"...",L22*(1-VLOOKUP(A22,Config!$B$3:$C$22,2,FALSE))) -> 12599.816 | N22: =IF(B22=0,"...",H22*M22) -> 125998.16 | O22: =IFERROR(__xludf.DUMMYFUNCTION("if(B22=0,""..."",GOOGLEFINANCE(B22,""changepct"")/100)"),-0.0192) -> -0.0192 | P22: =IFERROR(__xludf.DUMMYFUNCTION("if(B22=0,""..."",GOOGLEFINANCE(B22,""change"")*H22)"),-84.1) -> -84.1 | Q22: =if(B22=0,"...",N22/J22-1) -> 0.15913667 | R22: =if(B22=0,"...",N22-J22) -> 17298.156 | S22: {=IF(B22=0,"...",(N22/IF(E22="ABIERTA",CCL!$E$2,VLOOKUP(F22,{CCL!M:N;CCL!$P:$Q},2,FALSE))/(J22/VLOOKUP(D22,{CCL!M:N;CCL!$P:$Q},2,FALSE))-1))} -> 0.16678606 | T22: {=IF(B22=0,"...",(N22/IF(E22="ABIERTA",CCL!$E$2,VLOOKUP(F22,{CCL!M:N;CCL!$P:$Q},2,FALSE))-K22))} -> 12.190455
A23: IOL | B23: KO | C23: =IFERROR(__xludf.DUMMYFUNCTION("if(B23=0,""..."", sparkline(query(GOOGLEFINANCE(""BCBA:""&B23,""price"",today()-$AI$36,today()),""select Col2"",0),{""charttype"",$AI$35}))"),"") | D23: 45965 | E23: ABIERTA | G23: =if(B23=0,"...", IF(F23=0,today()-D23,F23-D23)) -> 152 | H23: 5 | I23: 20690 | J23: =if(B23=0,"...",H23*I23) -> 103450 | K23: {=IF(B23=0,"...",J23/VLOOKUP(D23,{CCL!M:N;CCL!$P:$Q},2,FALSE))} -> 68.362795 | L23: =IFERROR(__xludf.DUMMYFUNCTION("if(B23=0,""..."",if(E23=""CERRADA"",""Valor Venta"", GOOGLEFINANCE(""BCBA:""&B23)))"),22670.0) -> 22670 | M23: =if(B23=0,"...",L23*(1-VLOOKUP(A23,Config!$B$3:$C$22,2,FALSE))) -> 22511.31 | N23: =IF(B23=0,"...",H23*M23) -> 112556.55 | O23: =IFERROR(__xludf.DUMMYFUNCTION("if(B23=0,""..."",GOOGLEFINANCE(B23,""changepct"")/100)"),0.0084) -> 0.0084 | P23: =IFERROR(__xludf.DUMMYFUNCTION("if(B23=0,""..."",GOOGLEFINANCE(B23,""change"")*H23)"),3.2) -> 3.2 | Q23: =if(B23=0,"...",N23/J23-1) -> 0.088028516 | R23: =if(B23=0,"...",N23-J23) -> 9106.55 | S23: {=IF(B23=0,"...",(N23/IF(E23="ABIERTA",CCL!$E$2,VLOOKUP(F23,{CCL!M:N;CCL!$P:$Q},2,FALSE))/(J23/VLOOKUP(D23,{CCL!M:N;CCL!$P:$Q},2,FALSE))-1))} -> 0.11439247 | T23: {=IF(B23=0,"...",(N23/IF(E23="ABIERTA",CCL!$E$2,VLOOKUP(F23,{CCL!M:N;CCL!$P:$Q},2,FALSE))-K23))} -> 7.8201889 | W23: =if(V23=0,"...",sumifs($H$2:$H$37,$B$2:$B$37,V23,$E$2:$E$37,"ABIERTA")) -> ... | X23: =if(V23=0,"",Z23/$AH$19) | Y23: =if(W23=0,"...",if(V23=0,"...",sumifs($J$2:$J$37,$B$2:$B$37,V23,$E$2:$E$37,"ABIERTA")/W23)) -> ... | Z23: =if(V23=0,"...",sumifs($N$2:$N$37,$B$2:$B$37,V23,$E$2:$E$37,"ABIERTA")) -> ... | AA23: =if(W23=0,"...",if(V23=0,"...",AB23/(Z23-AB23))) -> ... | AB23: =if(W23=0,"...",if(V23=0,"...",sumifs($R$2:$R$37,$B$2:$B$37,V23,$E$2:$E$37,"ABIERTA"))) -> ... | AC23: =IF(W23=0,"...",IF(V23=0,"...",SUMIFS($K$2:$K$37,$B$2:$B$37,V23,$E$2:$E$37,"ABIERTA"))) -> ... | AD23: =IF(V23=0,"...",AE23/(AC23+AE23)) -> ... | AE23: =IF(W23=0,"...",if(V23=0,"...",sumifs($T$2:$T$37,$B$2:$B$37,V23,$E$2:$E$37,"ABIERTA"))) -> ...
A24: IOL | B24: RACE | C24: =IFERROR(__xludf.DUMMYFUNCTION("if(B24=0,""..."", sparkline(query(GOOGLEFINANCE(""BCBA:""&B24,""price"",today()-$AI$36,today()),""select Col2"",0),{""charttype"",$AI$35}))"),"") | D24: 45965 | E24: CERRADA | F24: 46059 | G24: =if(B24=0,"...", IF(F24=0,today()-D24,F24-D24)) -> 94 | H24: 11 | I24: 7330 | J24: =if(B24=0,"...",H24*I24) -> 80630 | K24: {=IF(B24=0,"...",J24/VLOOKUP(D24,{CCL!M:N;CCL!$P:$Q},2,FALSE))} -> 53.28267 | L24: 6016.86 | M24: =if(B24=0,"...",L24*(1-VLOOKUP(A24,Config!$B$3:$C$22,2,FALSE))) -> 5974.742 | N24: =IF(B24=0,"...",H24*M24) -> 65722.162 | O24: =IFERROR(__xludf.DUMMYFUNCTION("if(B24=0,""..."",GOOGLEFINANCE(B24,""changepct"")/100)"),-0.0070999999999999995) -> -0.0071 | P24: =IFERROR(__xludf.DUMMYFUNCTION("if(B24=0,""..."",GOOGLEFINANCE(B24,""change"")*H24)"),-26.73) -> -26.73 | Q24: =if(B24=0,"...",N24/J24-1) -> -0.18489195 | R24: =if(B24=0,"...",N24-J24) -> -14907.838 | S24: {=IF(B24=0,"...",(N24/IF(E24="ABIERTA",CCL!$E$2,1488.04)/(J24/VLOOKUP(D24,{CCL!M:N;CCL!$P:$Q},2,FALSE))-1))} -> -0.1710826 | T24: =IF(B24=0,"...",(N24/IF(E24="ABIERTA",CCL!$E$2,1488.04)-K24)) -> -9.1157376 | W24: =if(V24=0,"...",sumifs($H$2:$H$37,$B$2:$B$37,V24,$E$2:$E$37,"ABIERTA")) -> ... | X24: =if(V24=0,"",Z24/$AH$19) | Y24: =if(W24=0,"...",if(V24=0,"...",sumifs($J$2:$J$37,$B$2:$B$37,V24,$E$2:$E$37,"ABIERTA")/W24)) -> ... | Z24: =if(V24=0,"...",sumifs($N$2:$N$37,$B$2:$B$37,V24,$E$2:$E$37,"ABIERTA")) -> ... | AA24: =if(W24=0,"...",if(V24=0,"...",AB24/(Z24-AB24))) -> ... | AB24: =if(W24=0,"...",if(V24=0,"...",sumifs($R$2:$R$37,$B$2:$B$37,V24,$E$2:$E$37,"ABIERTA"))) -> ... | AC24: =IF(W24=0,"...",IF(V24=0,"...",SUMIFS($K$2:$K$37,$B$2:$B$37,V24,$E$2:$E$37,"ABIERTA"))) -> ... | AD24: =IF(V24=0,"...",AE24/(AC24+AE24)) -> ... | AE24: =IF(W24=0,"...",if(V24=0,"...",sumifs($T$2:$T$37,$B$2:$B$37,V24,$E$2:$E$37,"ABIERTA"))) -> ... | AG24: (%) | AH24: =AH21/(AH19-AH21) -> -0.034332207 | AI24: (%) | AJ24: =AJ21/(AJ19-AJ21) -> 0.090779257
A25: IOL | B25: NFLX | C25: =IFERROR(__xludf.DUMMYFUNCTION("if(B25=0,""..."", sparkline(query(GOOGLEFINANCE(""BCBA:""&B25,""price"",today()-$AI$36,today()),""select Col2"",0),{""charttype"",$AI$35}))"),"") | D25: 45965 | E25: ABIERTA | G25: =if(B25=0,"...", IF(F25=0,today()-D25,F25-D25)) -> 152 | H25: 90 | I25: =34480/10 -> 3448 | J25: =if(B25=0,"...",H25*I25) -> 310320 | K25: {=IF(B25=0,"...",J25/VLOOKUP(D25,{CCL!M:N;CCL!$P:$Q},2,FALSE))} -> 205.06856 | L25: =IFERROR(__xludf.DUMMYFUNCTION("if(B25=0,""..."",if(E25=""CERRADA"",""Valor Venta"", GOOGLEFINANCE(""BCBA:""&B25)))"),2957.5) -> 2957.5 | M25: =if(B25=0,"...",L25*(1-VLOOKUP(A25,Config!$B$3:$C$22,2,FALSE))) -> 2936.7975 | N25: =IF(B25=0,"...",H25*M25) -> 264311.78 | O25: =IFERROR(__xludf.DUMMYFUNCTION("if(B25=0,""..."",GOOGLEFINANCE(B25,""changepct"")/100)"),0.0325) -> 0.0325 | P25: =IFERROR(__xludf.DUMMYFUNCTION("if(B25=0,""..."",GOOGLEFINANCE(B25,""change"")*H25)"),279.9) -> 279.9 | Q25: =if(B25=0,"...",N25/J25-1) -> -0.14826059 | R25: =if(B25=0,"...",N25-J25) -> -46008.225 | S25: {=IF(B25=0,"...",(N25/IF(E25="ABIERTA",CCL!$E$2,VLOOKUP(F25,{CCL!M:N;CCL!$P:$Q},2,FALSE))/(J25/VLOOKUP(D25,{CCL!M:N;CCL!$P:$Q},2,FALSE))-1))} -> -0.12762214 | T25: {=IF(B25=0,"...",(N25/IF(E25="ABIERTA",CCL!$E$2,VLOOKUP(F25,{CCL!M:N;CCL!$P:$Q},2,FALSE))-K25))} -> -26.171289 | W25: =if(V25=0,"...",sumifs($H$2:$H$37,$B$2:$B$37,V25,$E$2:$E$37,"ABIERTA")) -> ... | X25: =if(V25=0,"",Z25/$AH$19) | Y25: =if(W25=0,"...",if(V25=0,"...",sumifs($J$2:$J$37,$B$2:$B$37,V25,$E$2:$E$37,"ABIERTA")/W25)) -> ... | Z25: =if(V25=0,"...",sumifs($N$2:$N$37,$B$2:$B$37,V25,$E$2:$E$37,"ABIERTA")) -> ... | AA25: =if(W25=0,"...",if(V25=0,"...",AB25/(Z25-AB25))) -> ... | AB25: =if(W25=0,"...",if(V25=0,"...",sumifs($R$2:$R$37,$B$2:$B$37,V25,$E$2:$E$37,"ABIERTA"))) -> ... | AC25: =IF(W25=0,"...",IF(V25=0,"...",SUMIFS($K$2:$K$37,$B$2:$B$37,V25,$E$2:$E$37,"ABIERTA"))) -> ... | AD25: =IF(V25=0,"...",AE25/(AC25+AE25)) -> ... | AE25: =IF(W25=0,"...",if(V25=0,"...",sumifs($T$2:$T$37,$B$2:$B$37,V25,$E$2:$E$37,"ABIERTA"))) -> ...
A26: IOL | B26: MELI | C26: =IFERROR(__xludf.DUMMYFUNCTION("if(B26=0,""..."", sparkline(query(GOOGLEFINANCE(""BCBA:""&B26,""price"",today()-$AI$36,today()),""select Col2"",0),{""charttype"",$AI$35}))"),"") | D26: 45978 | E26: ABIERTA | G26: =if(B26=0,"...", IF(F26=0,today()-D26,F26-D26)) -> 139 | H26: 19 | I26: 25580 | J26: =if(B26=0,"...",H26*I26) -> 486020 | K26: {=IF(B26=0,"...",J26/VLOOKUP(D26,{CCL!M:N;CCL!$P:$Q},2,FALSE))} -> 325.30153 | L26: =IFERROR(__xludf.DUMMYFUNCTION("if(B26=0,""..."",if(E26=""CERRADA"",""Valor Venta"", GOOGLEFINANCE(""BCBA:""&B26)))"),21350.0) -> 21350 | M26: =if(B26=0,"...",L26*(1-VLOOKUP(A26,Config!$B$3:$C$22,2,FALSE))) -> 21200.55 | N26: =IF(B26=0,"...",H26*M26) -> 402810.45 | O26: =IFERROR(__xludf.DUMMYFUNCTION("if(B26=0,""..."",GOOGLEFINANCE(B26,""changepct"")/100)"),-0.002) -> -0.002 | P26: =IFERROR(__xludf.DUMMYFUNCTION("if(B26=0,""..."",GOOGLEFINANCE(B26,""change"")*H26)"),-65.55) -> -65.55 | Q26: =if(B26=0,"...",N26/J26-1) -> -0.17120602 | R26: =if(B26=0,"...",N26-J26) -> -83209.55 | S26: {=IF(B26=0,"...",(N26/IF(E26="ABIERTA",CCL!$E$2,VLOOKUP(F26,{CCL!M:N;CCL!$P:$Q},2,FALSE))/(J26/VLOOKUP(D26,{CCL!M:N;CCL!$P:$Q},2,FALSE))-1))} -> -0.16188843 | T26: {=IF(B26=0,"...",(N26/IF(E26="ABIERTA",CCL!$E$2,VLOOKUP(F26,{CCL!M:N;CCL!$P:$Q},2,FALSE))-K26))} -> -52.662555 | W26: =if(V26=0,"...",sumifs($H$2:$H$37,$B$2:$B$37,V26,$E$2:$E$37,"ABIERTA")) -> ... | X26: =if(V26=0,"",Z26/$AH$19) | Y26: =if(W26=0,"...",if(V26=0,"...",sumifs($J$2:$J$37,$B$2:$B$37,V26,$E$2:$E$37,"ABIERTA")/W26)) -> ... | Z26: =if(V26=0,"...",sumifs($N$2:$N$37,$B$2:$B$37,V26,$E$2:$E$37,"ABIERTA")) -> ... | AA26: =if(W26=0,"...",if(V26=0,"...",AB26/(Z26-AB26))) -> ... | AB26: =if(W26=0,"...",if(V26=0,"...",sumifs($R$2:$R$37,$B$2:$B$37,V26,$E$2:$E$37,"ABIERTA"))) -> ... | AC26: =IF(W26=0,"...",IF(V26=0,"...",SUMIFS($K$2:$K$37,$B$2:$B$37,V26,$E$2:$E$37,"ABIERTA"))) -> ... | AD26: =IF(V26=0,"...",AE26/(AC26+AE26)) -> ... | AE26: =IF(W26=0,"...",if(V26=0,"...",sumifs($T$2:$T$37,$B$2:$B$37,V26,$E$2:$E$37,"ABIERTA"))) -> ...
A27: IOL | B27: SPXL | C27: =IFERROR(__xludf.DUMMYFUNCTION("if(B27=0,""..."", sparkline(query(GOOGLEFINANCE(""BCBA:""&B27,""price"",today()-$AI$36,today()),""select Col2"",0),{""charttype"",$AI$35}))"),"") | D27: 46024 | E27: CERRADA | F27: 46024 | G27: =if(B27=0,"...", IF(F27=0,today()-D27,F27-D27)) -> 0 | H27: 18 | I27: 13770 | J27: =if(B27=0,"...",H27*I27) -> 247860 | K27: {=IF(B27=0,"...",J27/VLOOKUP(D27,{CCL!M:N;CCL!$P:$Q},2,FALSE))} -> 160.33793 | L27: 13600 | M27: =if(B27=0,"...",L27*(1-VLOOKUP(A27,Config!$B$3:$C$22,2,FALSE))) -> 13504.8 | N27: =IF(B27=0,"...",H27*M27) -> 243086.4 | O27: =IFERROR(__xludf.DUMMYFUNCTION("if(B27=0,""..."",GOOGLEFINANCE(B27,""changepct"")/100)"),0.0024) -> 0.0024 | P27: =IFERROR(__xludf.DUMMYFUNCTION("if(B27=0,""..."",GOOGLEFINANCE(B27,""change"")*H27)"),8.280000000000001) -> 8.28 | Q27: =if(B27=0,"...",N27/J27-1) -> -0.019259259 | R27: =if(B27=0,"...",N27-J27) -> -4773.6 | S27: {=IF(B27=0,"...",(N27/IF(E27="ABIERTA",CCL!$E$2,VLOOKUP(F27,{CCL!M:N;CCL!$P:$Q},2,FALSE))/(J27/VLOOKUP(D27,{CCL!M:N;CCL!$P:$Q},2,FALSE))-1))} -> -0.019259259 | T27: {=IF(B27=0,"...",(N27/IF(E27="ABIERTA",CCL!$E$2,VLOOKUP(F27,{CCL!M:N;CCL!$P:$Q},2,FALSE))-K27))} -> -3.0879899 | W27: =if(V27=0,"...",sumifs($H$2:$H$37,$B$2:$B$37,V27,$E$2:$E$37,"ABIERTA")) -> ... | X27: =if(V27=0,"",Z27/$AH$19) | Y27: =if(W27=0,"...",if(V27=0,"...",sumifs($J$2:$J$37,$B$2:$B$37,V27,$E$2:$E$37,"ABIERTA")/W27)) -> ... | Z27: =if(V27=0,"...",sumifs($N$2:$N$37,$B$2:$B$37,V27,$E$2:$E$37,"ABIERTA")) -> ... | AA27: =if(W27=0,"...",if(V27=0,"...",AB27/(Z27-AB27))) -> ... | AB27: =if(W27=0,"...",if(V27=0,"...",sumifs($R$2:$R$37,$B$2:$B$37,V27,$E$2:$E$37,"ABIERTA"))) -> ... | AC27: =IF(W27=0,"...",IF(V27=0,"...",SUMIFS($K$2:$K$37,$B$2:$B$37,V27,$E$2:$E$37,"ABIERTA"))) -> ... | AD27: =IF(V27=0,"...",AE27/(AC27+AE27)) -> ... | AE27: =IF(W27=0,"...",if(V27=0,"...",sumifs($T$2:$T$37,$B$2:$B$37,V27,$E$2:$E$37,"ABIERTA"))) -> ... | AG27: Total Abierto USD | AH27: =SUMIFS(K2:K235,E2:E235,"ABIERTA") -> 3660.386 | AI27: Valor cartera | AJ27: =AH27+AH29 -> 3365.1246
A28: IOL | B28: MELI | C28: =IFERROR(__xludf.DUMMYFUNCTION("if(B28=0,""..."", sparkline(query(GOOGLEFINANCE(""BCBA:""&B28,""price"",today()-$AI$36,today()),""select Col2"",0),{""charttype"",$AI$35}))"),"") | D28: 46035 | E28: ABIERTA | G28: =if(B28=0,"...", IF(F28=0,today()-D28,F28-D28)) -> 82 | H28: 22 | I28: 26700 | J28: =if(B28=0,"...",H28*I28) -> 587400 | K28: {=IF(B28=0,"...",J28/VLOOKUP(D28,{CCL!M:N;CCL!$P:$Q},2,FALSE))} -> 385.85843 | L28: =IFERROR(__xludf.DUMMYFUNCTION("if(B28=0,""..."",if(E28=""CERRADA"",""Valor Venta"", GOOGLEFINANCE(""BCBA:""&B28)))"),21350.0) -> 21350 | M28: =if(B28=0,"...",L28*(1-VLOOKUP(A28,Config!$B$3:$C$22,2,FALSE))) -> 21200.55 | N28: =IF(B28=0,"...",H28*M28) -> 466412.1 | O28: =IFERROR(__xludf.DUMMYFUNCTION("if(B28=0,""..."",GOOGLEFINANCE(B28,""changepct"")/100)"),-0.002) -> -0.002 | P28: =IFERROR(__xludf.DUMMYFUNCTION("if(B28=0,""..."",GOOGLEFINANCE(B28,""change"")*H28)"),-75.9) -> -75.9 | Q28: =if(B28=0,"...",N28/J28-1) -> -0.20597191 | R28: =if(B28=0,"...",N28-J28) -> -120987.9 | S28: {=IF(B28=0,"...",(N28/IF(E28="ABIERTA",CCL!$E$2,VLOOKUP(F28,{CCL!M:N;CCL!$P:$Q},2,FALSE))/(J28/VLOOKUP(D28,{CCL!M:N;CCL!$P:$Q},2,FALSE))-1))} -> -0.18185736 | T28: {=IF(B28=0,"...",(N28/IF(E28="ABIERTA",CCL!$E$2,VLOOKUP(F28,{CCL!M:N;CCL!$P:$Q},2,FALSE))-K28))} -> -70.171195 | W28: =if(V28=0,"...",sumifs($H$2:$H$37,$B$2:$B$37,V28,$E$2:$E$37,"ABIERTA")) -> ... | X28: =if(V28=0,"",Z28/$AH$19) | Y28: =if(W28=0,"...",if(V28=0,"...",sumifs($J$2:$J$37,$B$2:$B$37,V28,$E$2:$E$37,"ABIERTA")/W28)) -> ... | Z28: =if(V28=0,"...",sumifs($N$2:$N$37,$B$2:$B$37,V28,$E$2:$E$37,"ABIERTA")) -> ... | AA28: =if(W28=0,"...",if(V28=0,"...",AB28/(Z28-AB28))) -> ... | AB28: =if(W28=0,"...",if(V28=0,"...",sumifs($R$2:$R$37,$B$2:$B$37,V28,$E$2:$E$37,"ABIERTA"))) -> ... | AC28: =IF(W28=0,"...",IF(V28=0,"...",SUMIFS($K$2:$K$37,$B$2:$B$37,V28,$E$2:$E$37,"ABIERTA"))) -> ... | AD28: =IF(V28=0,"...",AE28/(AC28+AE28)) -> ... | AE28: =IF(W28=0,"...",if(V28=0,"...",sumifs($T$2:$T$37,$B$2:$B$37,V28,$E$2:$E$37,"ABIERTA"))) -> ...
A29: IOL | B29: AAPL | C29: =IFERROR(__xludf.DUMMYFUNCTION("if(B29=0,""..."", sparkline(query(GOOGLEFINANCE(""BCBA:""&B29,""price"",today()-$AI$36,today()),""select Col2"",0),{""charttype"",$AI$35}))"),"") | D29: 46044 | E29: ABIERTA | G29: =if(B29=0,"...", IF(F29=0,today()-D29,F29-D29)) -> 73 | H29: 16 | I29: 18850 | J29: =if(B29=0,"...",H29*I29) -> 301600 | K29: {=IF(B29=0,"...",J29/VLOOKUP(D29,{CCL!M:N;CCL!$P:$Q},2,FALSE))} -> 200.51725 | L29: =IFERROR(__xludf.DUMMYFUNCTION("if(B29=0,""..."",if(E29=""CERRADA"",""Valor Venta"", GOOGLEFINANCE(""BCBA:""&B29)))"),18990.0) -> 18990 | M29: =if(B29=0,"...",L29*(1-VLOOKUP(A29,Config!$B$3:$C$22,2,FALSE))) -> 18857.07 | N29: =IF(B29=0,"...",H29*M29) -> 301713.12 | O29: =IFERROR(__xludf.DUMMYFUNCTION("if(B29=0,""..."",GOOGLEFINANCE(B29,""changepct"")/100)"),0.0011) -> 0.0011 | P29: =IFERROR(__xludf.DUMMYFUNCTION("if(B29=0,""..."",GOOGLEFINANCE(B29,""change"")*H29)"),4.64) -> 4.64 | Q29: =if(B29=0,"...",N29/J29-1) -> 0.00037506631 | R29: =if(B29=0,"...",N29-J29) -> 113.12 | S29: {=IF(B29=0,"...",(N29/IF(E29="ABIERTA",CCL!$E$2,VLOOKUP(F29,{CCL!M:N;CCL!$P:$Q},2,FALSE))/(J29/VLOOKUP(D29,{CCL!M:N;CCL!$P:$Q},2,FALSE))-1))} -> 0.018426438 | T29: =IF(B29=0,"...",(N29/IF(E29="ABIERTA",CCL!$E$2,VLOOKUP(F29,CCL!$A$12:$B$773,2,FALSE))-K29)) -> 3.6948187 | W29: =if(V29=0,"...",sumifs($H$2:$H$37,$B$2:$B$37,V29,$E$2:$E$37,"ABIERTA")) -> ... | X29: =if(V29=0,"",Z29/$AH$19) | Y29: =if(W29=0,"...",if(V29=0,"...",sumifs($J$2:$J$37,$B$2:$B$37,V29,$E$2:$E$37,"ABIERTA")/W29)) -> ... | Z29: =if(V29=0,"...",sumifs($N$2:$N$37,$B$2:$B$37,V29,$E$2:$E$37,"ABIERTA")) -> ... | AA29: =if(W29=0,"...",if(V29=0,"...",AB29/(Z29-AB29))) -> ... | AB29: =if(W29=0,"...",if(V29=0,"...",sumifs($R$2:$R$37,$B$2:$B$37,V29,$E$2:$E$37,"ABIERTA"))) -> ... | AC29: =IF(W29=0,"...",IF(V29=0,"...",SUMIFS($K$2:$K$37,$B$2:$B$37,V29,$E$2:$E$37,"ABIERTA"))) -> ... | AD29: =IF(V29=0,"...",AE29/(AC29+AE29)) -> ... | AE29: =IF(W29=0,"...",if(V29=0,"...",sumifs($T$2:$T$37,$B$2:$B$37,V29,$E$2:$E$37,"ABIERTA"))) -> ... | AG29: Ganancia Abierto USD | AH29: =sumifs(T2:T235,E2:E235,"ABIERTA") -> -295.26132 | AI29: Ganancia Acum USD | AJ29: =SUMIFS(T2:T235,E2:E235,"CERRADA") -> 375.59535
